Workbook

Sheet Dashboard
A1: DASHBOARD — RESUMEN EJECUTIVO ULOGIX × FEMSA/INDEGA FONTIBÓN
A2: Resumen vivo: demanda desde Demanda; capacidad/OEE desde Tiempos; caso de negocio desde las formulas nativas de Flujo_Caja/CAPEX; nomina desde RRHH. Las metricas MAPE siguen siendo resultados del backtest Python y se actualizan al volver a publicar el pronostico.
A4: ① DEMANDA (pronóstico Base, próximos 12 meses)
A5: producto | B5: demanda anual (und) | C5: MAPE backtest
A6: P1-CC350-RGB | B6: =SUM(Demanda!D$5:D$16) -> 188337814 | C6: 2.9%
A7: P2-QT1500-PET | B7: =SUM(Demanda!E$5:E$16) -> 54228683 | C7: 2.9%
A8: P3-GARR25L | B8: =SUM(Demanda!F$5:F$16) -> 279149 | C8: 2.1%
A10: ② CAPACIDAD Y OEE — ANTES vs. DESPUÉS DEL PROYECTO
A11: línea | B11: OEE antes → después | C11: utilización antes → después | D11: capacidad antes → después | E11: dictamen antes | F11: dictamen después
A12: L1 | B12: =TEXT(Tiempos!I104,"0.0%")&" → "&TEXT(Tiempos!J104,"0.0%") -> 77,1% → 81,0% | C12: =TEXT(Tiempos!U104,"0%")&" → "&TEXT(Tiempos!V104,"0%") -> 126% → 77% | D12: =TEXT(Tiempos!R104/1000000,"0.0")&"M → "&TEXT(Tiempos!T104/1000000,"0.0")&"M" -> 150,0M → 244,5M | E12: =Tiempos!X104 -> INFACTIBLE | F12: =Tiempos!Y104 -> Factible
A13: L2 | B13: =TEXT(Tiempos!I105,"0.0%")&" → "&TEXT(Tiempos!J105,"0.0%") -> 76,5% → 80,3% | C13: =TEXT(Tiempos!U105,"0%")&" → "&TEXT(Tiempos!V105,"0%") -> 129% → 55% | D13: =TEXT(Tiempos!R105/1000000,"0.0")&"M → "&TEXT(Tiempos!T105/1000000,"0.0")&"M" -> 42,0M → 99,2M | E13: =Tiempos!X105 -> INFACTIBLE | F13: =Tiempos!Y105 -> Factible
A14: L3 | B14: =TEXT(Tiempos!I106,"0.0%")&" → "&TEXT(Tiempos!J106,"0.0%") -> 75,4% → 79,1% | C14: =TEXT(Tiempos!U106,"0%")&" → "&TEXT(Tiempos!V106,"0%") -> 80% → 61% | D14: =TEXT(Tiempos!R106/1000000,"0.0")&"M → "&TEXT(Tiempos!T106/1000000,"0.0")&"M" -> 0,3M → 0,5M | E14: =Tiempos!X106 -> Factible | F14: =Tiempos!Y106 -> Factible
A16: ③ CASO DE NEGOCIO (modelo nativo vivo de Sheets)
A17: CAPEX total | B17: {=INDEX(CAPEX!$G:$G,MATCH("CAPEX TOTAL (con contingencia)",CAPEX!$C:$C,0))} -> 9165554245
A18: VPN | B18: =Flujo_Caja!B19 -> 11032069063
A19: TIR anual | B19: =Flujo_Caja!B21 -> 0.78159428
A20: ROI 60 meses | B20: =Flujo_Caja!B24 -> 2.2668912
A21: Payback simple | B21: =Flujo_Caja!B26 -> 22
A22: Payback descontado | B22: =Flujo_Caja!B27 -> 25
A23: EBITDA incremental (año 1 operativo) | B23: =Flujo_Caja!B28 -> 9406419488
A25: ④ RRHH (roster activo)
A26: rol | B26: conteo | C26: fase | D26: costo total mes COP
A27: Equipo diseno y desarrollo ULogix | B27: {=INDEX(RRHH!$B:$B,MATCH(A27,RRHH!$A:$A,0))} -> 7 | C27: {=INDEX(RRHH!$C:$C,MATCH(A27,RRHH!$A:$A,0))} -> Implementacion | D27: {=INDEX(RRHH!$H:$H,MATCH(A27,RRHH!$A:$A,0))} -> 87161760
A28: Operarios de linea (3 turnos) | B28: {=INDEX(RRHH!$B:$B,MATCH(A28,RRHH!$A:$A,0))} -> 18 | C28: {=INDEX(RRHH!$C:$C,MATCH(A28,RRHH!$A:$A,0))} -> Operacion | D28: {=INDEX(RRHH!$H:$H,MATCH(A28,RRHH!$A:$A,0))} -> 68865804
A29: Supervisor de planta | B29: {=INDEX(RRHH!$B:$B,MATCH(A29,RRHH!$A:$A,0))} -> 1 | C29: {=INDEX(RRHH!$C:$C,MATCH(A29,RRHH!$A:$A,0))} -> Operacion | D29: {=INDEX(RRHH!$H:$H,MATCH(A29,RRHH!$A:$A,0))} -> 6732768
A30: Supervisores de turno | B30: {=INDEX(RRHH!$B:$B,MATCH(A30,RRHH!$A:$A,0))} -> 2 | C30: {=INDEX(RRHH!$C:$C,MATCH(A30,RRHH!$A:$A,0))} -> Operacion | D30: {=INDEX(RRHH!$H:$H,MATCH(A30,RRHH!$A:$A,0))} -> 10316810
A31: TOTAL nómina/mes | D31: =SUM(D27:D30) -> 173077142
A33: ⑤ NAVEGACIÓN DEL LIBRO
A34: Demanda/DemandaEscenario | B34: pronóstico y escenario activo (ERP → Sheets)
A35: Tiempos | B35: equipos, tiempos, OEE y capacidad antes vs. después del proyecto
A36: CAPEX | B36: inversión por área (Sheets gobierna — el usuario edita aquí)
A37: RRHH | B37: roster + resumen por rol + carga prestacional
A38: Parametros | B38: supuestos financieros vivos (TRM, TMAR, nómina, precios...)
A39: Sensibilidad | B39: análisis tornado — dónde vale la pena invertir en mejor información
A40: APU_Ingenieria | B40: justificación de los costos de ingeniería que cobra ULogix

Sheet Reportes
A1: REPORTES — tablero financiero integral
A2: Todo por referencia (se recalcula solo): indicadores base vs escenario, resumen anual, sensibilidad, rotacion de inventarios y mapa del ERP.
A4: 1 · INDICADORES DEL PROYECTO
A5: indicador | B5: Base (Demanda v4) | C5: Escenario activo | D5: Δ
A6: VPN @ TMAR (COP) | B6: =Flujo_Caja!B19 -> 11032069063 | C6: =FinancieroEscenario!B21 -> 10832941906 | D6: =C6-B6 -> -1.9912716e+08
A7: TIR anual (E.A.) | B7: =Flujo_Caja!B21 -> 0.78159428 | C7: =FinancieroEscenario!B24 -> 0.76976275 | D7: =C7-B7 -> -0.011831524
A8: ROI 60 meses | B8: =Flujo_Caja!B24 -> 2.2668912 | C8: =FinancieroEscenario!B25 -> 2.2357461 | D8: =C8-B8 -> -0.031145144
A9: ROI anualizado | B9: =Flujo_Caja!B25 -> 0.26714681 | C9: =FinancieroEscenario!B29 -> 0.26472146 | D9: =C9-B9 -> -0.0024253538
A10: Payback simple (mes) | B10: =Flujo_Caja!B26 -> 22 | C10: =FinancieroEscenario!B26 -> 22 | D10: =C10-B10 -> 0
A11: Payback descontado (mes) | B11: =Flujo_Caja!B27 -> 25 | C11: =FinancieroEscenario!B27 -> 26 | D11: =C11-B11 -> 1
A12: EBITDA incremental 12m operativos | B12: =Flujo_Caja!B28 -> 9406419488 | C12: =FinancieroEscenario!B28 -> 9349060283 | D12: =C12-B12 -> -57359205
A13: Inversion pre-operativa (COP) | B13: =Flujo_Caja!B22 -> 9514201285
A14: CAPEX total (COP) | B14: {=INDEX(CAPEX!$G:$G,MATCH("CAPEX TOTAL (con contingencia)",CAPEX!$C:$C,0))} -> 9165554245
A15: Capital de trabajo (COP) | B15: =Flujo_Caja!B29 -> 1.2499736e+08
A17: 2 · RESUMEN ANUAL (incremental)
A18: concepto | B18: Año 1 | C18: Año 2 | D18: Año 3 | E18: Año 4 | F18: Año 5
A19: Ingresos incrementales | B19: =SUM(ER_Proyecto!B17:M17)-SUM(ER_Proyecto!B9:M9) -> 12624025002 | C19: =SUM(ER_Proyecto!N17:Y17)-SUM(ER_Proyecto!N9:Y9) -> 19533494678 | D19: =SUM(ER_Proyecto!Z17:AK17)-SUM(ER_Proyecto!Z9:AK9) -> 19533494678 | E19: =SUM(ER_Proyecto!AL17:AW17)-SUM(ER_Proyecto!AL9:AW9) -> 19533494678 | F19: =SUM(ER_Proyecto!AX17:BI17)-SUM(ER_Proyecto!AX9:BI9) -> 19533494678
A20: EBITDA incremental | B20: =SUM(ER_Proyecto!B25:M25) -> 6237422529 | C20: =SUM(ER_Proyecto!N25:Y25) -> 9678151543 | D20: =SUM(ER_Proyecto!Z25:AK25) -> 9678151543 | E20: =SUM(ER_Proyecto!AL25:AW25) -> 9678151543 | F20: =SUM(ER_Proyecto!AX25:BI25) -> 9678151543
A21: Utilidad neta incremental | B21: =SUM(ER_Proyecto!B29:M29) -> 3559703270 | C21: =SUM(ER_Proyecto!N29:Y29) -> 5548866443 | D21: =SUM(ER_Proyecto!Z29:AK29) -> 5548866443 | E21: =SUM(ER_Proyecto!AL29:AW29) -> 5548866443 | F21: =SUM(ER_Proyecto!AX29:BI29) -> 5548866443
A22: FCF del proyecto | B22: =SUM(Flujo_Caja!B11:M11) -> -5318539419 | C22: =SUM(Flujo_Caja!N11:Y11) -> 6690300382 | D22: =SUM(Flujo_Caja!Z11:AK11) -> 6690300382 | E22: =SUM(Flujo_Caja!AL11:AW11) -> 6690300382 | F22: =SUM(Flujo_Caja!AX11:BI11) -> 6815297745
A23: FCF acumulado (cierre de año) | B23: =Flujo_Caja!M14 -> -5318539419 | C23: =Flujo_Caja!Y14 -> 1371760962 | D23: =Flujo_Caja!AK14 -> 8062061344 | E23: =Flujo_Caja!AW14 -> 14752361726 | F23: =Flujo_Caja!BI14 -> 21567659470
A25: 3 · SENSIBILIDAD RESUMIDA
A26: escenario | B26: VPN (COP) | C26: TIR anual
A27: Conservador | B27: =Sensibilidad!$E$5 -> 8014994753 | C27: =Sensibilidad!$F$5 -> 0.59806155
A28: Base | B28: =Sensibilidad!$E$6 -> 11032069063 | C28: =Sensibilidad!$F$6 -> 0.78159428
A29: Optimista | B29: =Sensibilidad!$E$7 -> 13751069360 | C29: =Sensibilidad!$F$7 -> 0.95882509
A31: 4 · INVENTARIOS
A32: Rotacion del portafolio (veces/año) | B32: =Inventarios!$E$15 -> 21.470588
A33: Dias de inventario | B33: =Inventarios!$F$15 -> 17
A35: 5 · MAPA DEL ERP (quien alimenta cada hoja)
A36: Ventas | B36: Demanda · DemandaEscenario | D36: APP (pronostico v4 / escenario activo)
A37: Produccion | B37: KPIs_UNS · LibroProduccion | D37: Middleware via MQTT-UNS (el ERP NO gestiona OEE)
A38: Produccion (doc.) | B38: Tiempos · OEE_TEEP | D38: Documental para disenos (no conectado)
A39: Compras | B39: PlanCompras | D39: APP (MRP del escenario activo)
A40: Inventario | B40: Inventarios | D40: APP (politica s,Q) + formulas de rotacion
A41: RRHH | B41: Personal | D41: Equipo (editable)
A42: Finanzas | B42: Parametros→CAPEX→Licencias→Costos_Lote→Dep_Amort→ER→Flujo_Caja→Balance→Sensibilidad→Reportes | D42: Formulas vivas

Sheet Parametros
A1: Parametros del modelo — la app los LEE por API
A2: Editar SOLO la columna valor (azul). Amarillo = palancas clave. Fuente: Supuestos/Costos_Lote/Personal/Licencias de la base financiera + BOM reales.
A4: parametro | B4: valor | C4: unidad | D4: fuente / nota
A5: trm_cop_usd | B5: 3248.87 | C5: COP/USD | D5: Superfinanciera; vigencia 11-14 jul-2026
A6: factor_rfq_benchmark | B6: 0.97 | D6: Negociacion RFQ (solo benchmark; celdas ya cotizadas)
A7: tmar_anual | B7: 0.18 | C7: E.A. | D7: BanRep + primas de riesgo
A8: tasa_renta | B8: 0.35 | D8: Art. 240 ET
A9: inflacion_anual | B9: 0.0529 | C9: E.A. | D9: DANE IPC feb-2026
A10: crecimiento_demanda | B10: 0 | C10: anual | D10: YA NO SE APLICA -- pedido explicito del dueno del proyecto: la evaluacion financiera sigue SIEMPRE la demanda que manda el ERP (pronostico/escenario activo), sin inflarla con una tasa de crecimiento interanual aparte. Fila conservada para registro (antes 1,50% aplicado a meses 13-60 via (1+B10)^N en ER_Proyecto/FinancieroEscenario).
A11: uplift_throughput | B11: 0.11 | D11: Objetivo del modelo de negocio (+11%)
A12: factor_monetizacion | B12: 0.31 | D12: Parte del uplift que se vende (demanda > capacidad: hoja Tiempos)
A13: rampa_mes5 | B13: 0.67 | D13: Arranque parcial del primer mes operativo
A14: scrap_pp | B14: 0.0004 | D14: Reduccion de rechazo por inspeccion (0.04 pp)
A15: mant_evitado_mes | B15: 85000000 | C15: COP/mes | D15: Correctivo evitado (base financiera)
A16: wc_pct_ingreso | B16: 0.08 | D16: Capital de trabajo sobre ingreso incremental mensual
A17: dso_dias | B17: 25 | C17: dias | D17: Cuentas por cobrar (Balance)
A18: dio_dias | B18: 17 | C18: dias | D18: Inventarios (Balance y rotacion)
A19: dpo_dias | B19: 30 | C19: dias | D19: Cuentas por pagar (Balance)
A20: precio_p1_350ml | B20: 1800 | C20: COP/u | D20: Costos_Lote (precio ex-factory)
A21: precio_p2_pet15 | B21: 4250 | C21: COP/u | D21: Costos_Lote
A22: precio_p3_garrafon | B22: 12000 | C22: COP/u | D22: Costos_Lote
A23: nomina_operacion_mes | B23: {=INDEX(RRHH!$E:$E,MATCH("Costo mensual OPERACION (→ ER)",RRHH!$A:$A,0))} -> 85915382 | C23: COP/mes | D23: RRHH (resumen por rol, en vivo -- ya no 'Personal', consolidada)
A24: nomina_implementacion_mes | B24: {=INDEX(RRHH!$E:$E,MATCH("Costo mensual IMPLEMENTACION (→ pre-op)",RRHH!$A:$A,0))} -> 87161760 | C24: COP/mes | D24: RRHH (resumen por rol, en vivo -- ya no 'Personal', consolidada)
A25: otros_fijos_base_mes | B25: 250000000 | C25: COP/mes | D25: Base financiera
A26: otros_fijos_proyecto_mes | B26: 280000000 | C26: COP/mes | D26: Base financiera (+30M soporte digital)
A27: contingencia_capex | B27: 0.1 | D27: Sobre subtotal CAPEX
A28: fase_capex_1 | B28: 0.2 | D28: Desembolso mes 1 (ingenieria)
A29: fase_capex_2 | B29: 0.35 | D29: Mes 2 (compra equipos)
A30: fase_capex_3 | B30: 0.27 | D30: Mes 3 (instalacion)
A31: fase_capex_4 | B31: 0.18 | D31: Mes 4 (commissioning)
A32: mejora_oee_relativa | B32: 0.05 | D32: Fase 1: OEE por linea x 1.05 (hoja Tiempos, bloque 'MEJORA DE OEE A IMPLEMENTAR') -- documental, ver core/tiempos_oee.py (data/parametros_planta.json es la fuente real que usa el ERP, decision #1 de CLAUDE.md: OEE/TEEP no se gobierna desde Sheets).
A33: oee_objetivo | B33: 0.82 | D33: Meta de programa
A34: meses_preoperativos | B34: 4 | C34: meses | D34: Cronograma
A35: meses_modelo | B35: 60 | C35: meses | D35: Horizonte
A36: gbp_cop | B36: 4437 | C36: COP/GBP | D36: Referencia de mercado jul-2026 para cotizacion EUROBOTS
A37: fte_manual_equivalente | B37: 10 | C37: FTE | D37: L1: 6 (encajonado+paletizado, 2 turnos); L2: 2; L3: 2
A38: pct_monetizacion_ahorro_laboral | B38: 0.7 | C38: % | D38: Conservador: reconoce reasignacion; editable
A39: ahorro_laboral_monetizable_mes | B39: {=INDEX(Viabilidad_Automatizacion!$B:$B,MATCH("Ahorro laboral bruto mensual",Viabilidad_Automatizacion!$A:$A,0))*B38} -> 26781146 | C39: COP/mes | D39: Formula viva: costo FTE RRHH x FTE equivalentes x monetizacion
A40: eur_cop | B40: 3815.5 | C40: COP/EUR | D40: Referencia 08-jul-2026 para Coreflux; supuesto editable

Sheet Modelo_Negocio
A1: Modelo de negocio — retrofit brownfield FEMSA Fontibon (v3)
A4: elemento | B4: descripcion | C4: hojas relacionadas
A5: Tesis | B5: Conservar las 3 lineas existentes e invertir SOLO donde el estudio de tiempos corregido y el OEE bottom-up demuestran perdidas: paletizado, llenadoras e inspeccion, con gemelo digital por equipo y trazabilidad MES/Cloud via UNS. | C5: Tiempos · OEE_TEEP
A6: Objetivo +11% throughput | B6: Uplift tecnico por OEE (77→81% fase 1) y eliminacion del cuello de paletizado; se monetiza el 31% (parametrizable) porque la demanda SUPERA la capacidad actual. | C6: ER_Proyecto
A7: Hallazgo de capacidad | B7: Con 2 turnos U_2026 = 1.25 (L1) y 1.30 (L2): INFACTIBLE. El 3er turno (nomina ya modelada en Personal) devuelve U a 0.83/0.86. En L3, la celda robotica evita el 2do operario (U=1.61 con uno solo). | C7: Tiempos · Personal
A8: OEE | B8: Fase 1 comprometida: +5% relativo por linea, justificado (+2.0pp disponibilidad celdas/MTTR · +1.2pp rendimiento retrofit llenadoras · +0.7pp calidad inspeccion). Meta de programa ≥86% con mejora continua. KPIs vivos por UNS. | C8: OEE_TEEP · KPIs_UNS
A9: +5% flujo de caja | B9: Verificable en Flujo_Caja/Reportes: EBITDA incremental sobre el caso base supera el objetivo con la demanda v4. | C9: Flujo_Caja · Reportes
A10: Inversion | B10: CAPEX benchmark de retrofit + BOM REAL de celdas (gantry L1-L2 USD 107,993 · robot L3 USD 131,896) + software; contingencia 10%. ⚠ GRP001 pendiente de consolidar. | C10: CAPEX · Licencias
A11: Gobernanza de datos | B11: ERP Ulogix ↔ UNS FEMSA (MQTT) ↔ Odoo ↔ este libro (API Sheets): la demanda elegida en el ERP evalua escenarios financieros en vivo. | C11: Demanda(Escenario) · FinancieroEscenario

Sheet Demanda
A1: Demanda — la escribe la APP (rango fijo A4:F16, NO mover)
A2: VENTAS · Pronostico v4 Base (Abr-26→Mar-27). ER_Proyecto/Flujo_Caja/Balance leen D5:F16. La app la reescribe con publicar_demanda().
A4: escenario | B4: mes_num | C4: etiqueta | D4: P1-CC350-RGB_unidades | E4: P2-QT1500-PET_unidades | F4: P3-GARR25L_unidades
A5: Base | B5: 1 | C5: 46138 | D5: 14359006 | E5: 4241454 | F5: 21691
A6: Base | B6: 2 | C6: 46168 | D6: 14803557 | E6: 4372768 | F6: 22362
A7: Base | B7: 3 | C7: 46199 | D7: 15705552 | E7: 4414001 | F7: 23034
A8: Base | B8: 4 | C8: 46229 | D8: 16744208 | E8: 4651364 | F8: 25180
A9: Base | B9: 5 | C9: 46260 | D9: 15329328 | E9: 4475219 | F9: 23737
A10: Base | B10: 6 | C10: Sep-26 | D10: 14854626 | E10: 4424244 | F10: 23232
A11: Base | B11: 7 | C11: 46321 | D11: 15537720 | E11: 4355974 | F11: 21894
A12: Base | B12: 8 | C12: 46352 | D12: 16178840 | E12: 4673157 | F12: 23028
A13: Base | B13: 9 | C13: 46382 | D13: 18771980 | E13: 5469074 | F13: 25933
A14: Base | B14: 10 | C14: 46049 | D14: 15568902 | E14: 4430554 | F14: 23273
A15: Base | B15: 11 | C15: 46080 | D15: 14407009 | E15: 4099488 | F15: 21753
A16: Base | B16: 12 | C16: 46108 | D16: 16077086 | E16: 4621386 | F16: 24032

Sheet DemandaEscenario
A1: DemandaEscenario — la escribe la APP (rango fijo A4:F16, NO mover)
A2: VENTAS · Demanda del ESCENARIO ACTIVO elegido en el ERP (pagina Escenarios → Activar). FinancieroEscenario la evalua. publicar_demanda_escenario().
A4: escenario | B4: mes_num | C4: etiqueta | D4: P1-CC350-RGB_unidades | E4: P2-QT1500-PET_unidades | F4: P3-GARR25L_unidades
A5: Paro nacional / choque logistico | B5: 1 | C5: 46138 | D5: 14359007 | E5: 4241455 | F5: 21681
A6: Paro nacional / choque logistico | B6: 2 | C6: 46168 | D6: 14803558 | E6: 4372769 | F6: 22352
A7: Paro nacional / choque logistico | B7: 3 | C7: 46199 | D7: 15705553 | E7: 4414002 | F7: 23023
A8: Paro nacional / choque logistico | B8: 4 | C8: 46229 | D8: 16744208 | E8: 4651367 | F8: 25177
A9: Paro nacional / choque logistico | B9: 5 | C9: 46260 | D9: 12570049 | E9: 3669682 | F9: 19462
A10: Paro nacional / choque logistico | B10: 6 | C10: Sep-26 | D10: 14854626 | E10: 4424247 | F10: 23229
A11: Paro nacional / choque logistico | B11: 7 | C11: 46321 | D11: 16159229 | E11: 4530217 | F11: 22767
A12: Paro nacional / choque logistico | B12: 8 | C12: 46352 | D12: 16178840 | E12: 4673161 | F12: 23024
A13: Paro nacional / choque logistico | B13: 9 | C13: 46382 | D13: 18771980 | E13: 5469078 | F13: 25929
A14: Paro nacional / choque logistico | B14: 10 | C14: 46049 | D14: 15568902 | E14: 4430558 | F14: 23267
A15: Paro nacional / choque logistico | B15: 11 | C15: 46080 | D15: 14407009 | E15: 4099491 | F15: 21748
A16: Paro nacional / choque logistico | B16: 12 | C16: 46108 | D16: 16077085 | E16: 4621389 | F16: 24027

Sheet ER_Proyecto
A1: Estado de resultados mensual — caso BASE vs PROYECTO (demanda v4)
A2: Proyecto incluye ahorro laboral monetizable vinculado a Viabilidad_Automatizacion/Parametros; porcentaje editable y conservador.
A4: Mes | B4: 1 | C4: 2 | D4: 3 | E4: 4 | F4: 5 | G4: 6 | H4: 7 | I4: 8 | J4: 9 | K4: 10 | L4: 11 | M4: 12 | N4: 13 | O4: 14 | P4: 15 | Q4: 16 | R4: 17 | S4: 18 | T4: 19 | U4: 20 | V4: 21 | W4: 22 | X4: 23 | Y4: 24 | Z4: 25 | AA4: 26 | AB4: 27 | AC4: 28 | AD4: 29 | AE4: 30 | AF4: 31 | AG4: 32 | AH4: 33 | AI4: 34 | AJ4: 35 | AK4: 36 | AL4: 37 | AM4: 38 | AN4: 39 | AO4: 40 | AP4: 41 | AQ4: 42 | AR4: 43 | AS4: 44 | AT4: 45 | AU4: 46 | AV4: 47 | AW4: 48 | AX4: 49 | AY4: 50 | AZ4: 51 | BA4: 52 | BB4: 53 | BC4: 54 | BD4: 55 | BE4: 56 | BF4: 57 | BG4: 58 | BH4: 59 | BI4: 60
A5: CASO BASE (sin proyecto)
A6: Ventas u P1 (330/350 mL) | B6: =Demanda!$D$5 -> 14359006 | C6: =Demanda!$D$6 -> 14803557 | D6: =Demanda!$D$7 -> 15705552 | E6: =Demanda!$D$8 -> 16744208 | F6: =Demanda!$D$9 -> 15329328 | G6: =Demanda!$D$10 -> 14854626 | H6: =Demanda!$D$11 -> 15537720 | I6: =Demanda!$D$12 -> 16178840 | J6: =Demanda!$D$13 -> 18771980 | K6: =Demanda!$D$14 -> 15568902 | L6: =Demanda!$D$15 -> 14407009 | M6: =Demanda!$D$16 -> 16077086 | N6: =Demanda!$D$5*(1+Parametros!$B$10)^1 -> 14359006 | O6: =Demanda!$D$6*(1+Parametros!$B$10)^1 -> 14803557 | P6: =Demanda!$D$7*(1+Parametros!$B$10)^1 -> 15705552 | Q6: =Demanda!$D$8*(1+Parametros!$B$10)^1 -> 16744208 | R6: =Demanda!$D$9*(1+Parametros!$B$10)^1 -> 15329328 | S6: =Demanda!$D$10*(1+Parametros!$B$10)^1 -> 14854626 | T6: =Demanda!$D$11*(1+Parametros!$B$10)^1 -> 15537720 | U6: =Demanda!$D$12*(1+Parametros!$B$10)^1 -> 16178840 | V6: =Demanda!$D$13*(1+Parametros!$B$10)^1 -> 18771980 | W6: =Demanda!$D$14*(1+Parametros!$B$10)^1 -> 15568902 | X6: =Demanda!$D$15*(1+Parametros!$B$10)^1 -> 14407009 | Y6: =Demanda!$D$16*(1+Parametros!$B$10)^1 -> 16077086 | Z6: =Demanda!$D$5*(1+Parametros!$B$10)^2 -> 14359006 | AA6: =Demanda!$D$6*(1+Parametros!$B$10)^2 -> 14803557 | AB6: =Demanda!$D$7*(1+Parametros!$B$10)^2 -> 15705552 | AC6: =Demanda!$D$8*(1+Parametros!$B$10)^2 -> 16744208 | AD6: =Demanda!$D$9*(1+Parametros!$B$10)^2 -> 15329328 | AE6: =Demanda!$D$10*(1+Parametros!$B$10)^2 -> 14854626 | AF6: =Demanda!$D$11*(1+Parametros!$B$10)^2 -> 15537720 | AG6: =Demanda!$D$12*(1+Parametros!$B$10)^2 -> 16178840 | AH6: =Demanda!$D$13*(1+Parametros!$B$10)^2 -> 18771980 | AI6: =Demanda!$D$14*(1+Parametros!$B$10)^2 -> 15568902 | AJ6: =Demanda!$D$15*(1+Parametros!$B$10)^2 -> 14407009 | AK6: =Demanda!$D$16*(1+Parametros!$B$10)^2 -> 16077086 | AL6: =Demanda!$D$5*(1+Parametros!$B$10)^3 -> 14359006 | AM6: =Demanda!$D$6*(1+Parametros!$B$10)^3 -> 14803557 | AN6: =Demanda!$D$7*(1+Parametros!$B$10)^3 -> 15705552 | AO6: =Demanda!$D$8*(1+Parametros!$B$10)^3 -> 16744208 | AP6: =Demanda!$D$9*(1+Parametros!$B$10)^3 -> 15329328 | AQ6: =Demanda!$D$10*(1+Parametros!$B$10)^3 -> 14854626 | AR6: =Demanda!$D$11*(1+Parametros!$B$10)^3 -> 15537720 | AS6: =Demanda!$D$12*(1+Parametros!$B$10)^3 -> 16178840 | AT6: =Demanda!$D$13*(1+Parametros!$B$10)^3 -> 18771980 | AU6: =Demanda!$D$14*(1+Parametros!$B$10)^3 -> 15568902 | AV6: =Demanda!$D$15*(1+Parametros!$B$10)^3 -> 14407009 | AW6: =Demanda!$D$16*(1+Parametros!$B$10)^3 -> 16077086 | AX6: =Demanda!$D$5*(1+Parametros!$B$10)^4 -> 14359006 | AY6: =Demanda!$D$6*(1+Parametros!$B$10)^4 -> 14803557 | AZ6: =Demanda!$D$7*(1+Parametros!$B$10)^4 -> 15705552 | BA6: =Demanda!$D$8*(1+Parametros!$B$10)^4 -> 16744208 | BB6: =Demanda!$D$9*(1+Parametros!$B$10)^4 -> 15329328 | BC6: =Demanda!$D$10*(1+Parametros!$B$10)^4 -> 14854626 | BD6: =Demanda!$D$11*(1+Parametros!$B$10)^4 -> 15537720 | BE6: =Demanda!$D$12*(1+Parametros!$B$10)^4 -> 16178840 | BF6: =Demanda!$D$13*(1+Parametros!$B$10)^4 -> 18771980 | BG6: =Demanda!$D$14*(1+Parametros!$B$10)^4 -> 15568902 | BH6: =Demanda!$D$15*(1+Parametros!$B$10)^4 -> 14407009 | BI6: =Demanda!$D$16*(1+Parametros!$B$10)^4 -> 16077086
A7: Ventas u P2 (PET 1.5 L) | B7: =Demanda!$E$5 -> 4241454 | C7: =Demanda!$E$6 -> 4372768 | D7: =Demanda!$E$7 -> 4414001 | E7: =Demanda!$E$8 -> 4651364 | F7: =Demanda!$E$9 -> 4475219 | G7: =Demanda!$E$10 -> 4424244 | H7: =Demanda!$E$11 -> 4355974 | I7: =Demanda!$E$12 -> 4673157 | J7: =Demanda!$E$13 -> 5469074 | K7: =Demanda!$E$14 -> 4430554 | L7: =Demanda!$E$15 -> 4099488 | M7: =Demanda!$E$16 -> 4621386 | N7: =Demanda!$E$5*(1+Parametros!$B$10)^1 -> 4241454 | O7: =Demanda!$E$6*(1+Parametros!$B$10)^1 -> 4372768 | P7: =Demanda!$E$7*(1+Parametros!$B$10)^1 -> 4414001 | Q7: =Demanda!$E$8*(1+Parametros!$B$10)^1 -> 4651364 | R7: =Demanda!$E$9*(1+Parametros!$B$10)^1 -> 4475219 | S7: =Demanda!$E$10*(1+Parametros!$B$10)^1 -> 4424244 | T7: =Demanda!$E$11*(1+Parametros!$B$10)^1 -> 4355974 | U7: =Demanda!$E$12*(1+Parametros!$B$10)^1 -> 4673157 | V7: =Demanda!$E$13*(1+Parametros!$B$10)^1 -> 5469074 | W7: =Demanda!$E$14*(1+Parametros!$B$10)^1 -> 4430554 | X7: =Demanda!$E$15*(1+Parametros!$B$10)^1 -> 4099488 | Y7: =Demanda!$E$16*(1+Parametros!$B$10)^1 -> 4621386 | Z7: =Demanda!$E$5*(1+Parametros!$B$10)^2 -> 4241454 | AA7: =Demanda!$E$6*(1+Parametros!$B$10)^2 -> 4372768 | AB7: =Demanda!$E$7*(1+Parametros!$B$10)^2 -> 4414001 | AC7: =Demanda!$E$8*(1+Parametros!$B$10)^2 -> 4651364 | AD7: =Demanda!$E$9*(1+Parametros!$B$10)^2 -> 4475219 | AE7: =Demanda!$E$10*(1+Parametros!$B$10)^2 -> 4424244 | AF7: =Demanda!$E$11*(1+Parametros!$B$10)^2 -> 4355974 | AG7: =Demanda!$E$12*(1+Parametros!$B$10)^2 -> 4673157 | AH7: =Demanda!$E$13*(1+Parametros!$B$10)^2 -> 5469074 | AI7: =Demanda!$E$14*(1+Parametros!$B$10)^2 -> 4430554 | AJ7: =Demanda!$E$15*(1+Parametros!$B$10)^2 -> 4099488 | AK7: =Demanda!$E$16*(1+Parametros!$B$10)^2 -> 4621386 | AL7: =Demanda!$E$5*(1+Parametros!$B$10)^3 -> 4241454 | AM7: =Demanda!$E$6*(1+Parametros!$B$10)^3 -> 4372768 | AN7: =Demanda!$E$7*(1+Parametros!$B$10)^3 -> 4414001 | AO7: =Demanda!$E$8*(1+Parametros!$B$10)^3 -> 4651364 | AP7: =Demanda!$E$9*(1+Parametros!$B$10)^3 -> 4475219 | AQ7: =Demanda!$E$10*(1+Parametros!$B$10)^3 -> 4424244 | AR7: =Demanda!$E$11*(1+Parametros!$B$10)^3 -> 4355974 | AS7: =Demanda!$E$12*(1+Parametros!$B$10)^3 -> 4673157 | AT7: =Demanda!$E$13*(1+Parametros!$B$10)^3 -> 5469074 | AU7: =Demanda!$E$14*(1+Parametros!$B$10)^3 -> 4430554 | AV7: =Demanda!$E$15*(1+Parametros!$B$10)^3 -> 4099488 | AW7: =Demanda!$E$16*(1+Parametros!$B$10)^3 -> 4621386 | AX7: =Demanda!$E$5*(1+Parametros!$B$10)^4 -> 4241454 | AY7: =Demanda!$E$6*(1+Parametros!$B$10)^4 -> 4372768 | AZ7: =Demanda!$E$7*(1+Parametros!$B$10)^4 -> 4414001 | BA7: =Demanda!$E$8*(1+Parametros!$B$10)^4 -> 4651364 | BB7: =Demanda!$E$9*(1+Parametros!$B$10)^4 -> 4475219 | BC7: =Demanda!$E$10*(1+Parametros!$B$10)^4 -> 4424244 | BD7: =Demanda!$E$11*(1+Parametros!$B$10)^4 -> 4355974 | BE7: =Demanda!$E$12*(1+Parametros!$B$10)^4 -> 4673157 | BF7: =Demanda!$E$13*(1+Parametros!$B$10)^4 -> 5469074 | BG7: =Demanda!$E$14*(1+Parametros!$B$10)^4 -> 4430554 | BH7: =Demanda!$E$15*(1+Parametros!$B$10)^4 -> 4099488 | BI7: =Demanda!$E$16*(1+Parametros!$B$10)^4 -> 4621386
A8: Ventas u P3 (garrafon) | B8: =Demanda!$F$5 -> 21691 | C8: =Demanda!$F$6 -> 22362 | D8: =Demanda!$F$7 -> 23034 | E8: =Demanda!$F$8 -> 25180 | F8: =Demanda!$F$9 -> 23737 | G8: =Demanda!$F$10 -> 23232 | H8: =Demanda!$F$11 -> 21894 | I8: =Demanda!$F$12 -> 23028 | J8: =Demanda!$F$13 -> 25933 | K8: =Demanda!$F$14 -> 23273 | L8: =Demanda!$F$15 -> 21753 | M8: =Demanda!$F$16 -> 24032 | N8: =Demanda!$F$5*(1+Parametros!$B$10)^1 -> 21691 | O8: =Demanda!$F$6*(1+Parametros!$B$10)^1 -> 22362 | P8: =Demanda!$F$7*(1+Parametros!$B$10)^1 -> 23034 | Q8: =Demanda!$F$8*(1+Parametros!$B$10)^1 -> 25180 | R8: =Demanda!$F$9*(1+Parametros!$B$10)^1 -> 23737 | S8: =Demanda!$F$10*(1+Parametros!$B$10)^1 -> 23232 | T8: =Demanda!$F$11*(1+Parametros!$B$10)^1 -> 21894 | U8: =Demanda!$F$12*(1+Parametros!$B$10)^1 -> 23028 | V8: =Demanda!$F$13*(1+Parametros!$B$10)^1 -> 25933 | W8: =Demanda!$F$14*(1+Parametros!$B$10)^1 -> 23273 | X8: =Demanda!$F$15*(1+Parametros!$B$10)^1 -> 21753 | Y8: =Demanda!$F$16*(1+Parametros!$B$10)^1 -> 24032 | Z8: =Demanda!$F$5*(1+Parametros!$B$10)^2 -> 21691 | AA8: =Demanda!$F$6*(1+Parametros!$B$10)^2 -> 22362 | AB8: =Demanda!$F$7*(1+Parametros!$B$10)^2 -> 23034 | AC8: =Demanda!$F$8*(1+Parametros!$B$10)^2 -> 25180 | AD8: =Demanda!$F$9*(1+Parametros!$B$10)^2 -> 23737 | AE8: =Demanda!$F$10*(1+Parametros!$B$10)^2 -> 23232 | AF8: =Demanda!$F$11*(1+Parametros!$B$10)^2 -> 21894 | AG8: =Demanda!$F$12*(1+Parametros!$B$10)^2 -> 23028 | AH8: =Demanda!$F$13*(1+Parametros!$B$10)^2 -> 25933 | AI8: =Demanda!$F$14*(1+Parametros!$B$10)^2 -> 23273 | AJ8: =Demanda!$F$15*(1+Parametros!$B$10)^2 -> 21753 | AK8: =Demanda!$F$16*(1+Parametros!$B$10)^2 -> 24032 | AL8: =Demanda!$F$5*(1+Parametros!$B$10)^3 -> 21691 | AM8: =Demanda!$F$6*(1+Parametros!$B$10)^3 -> 22362 | AN8: =Demanda!$F$7*(1+Parametros!$B$10)^3 -> 23034 | AO8: =Demanda!$F$8*(1+Parametros!$B$10)^3 -> 25180 | AP8: =Demanda!$F$9*(1+Parametros!$B$10)^3 -> 23737 | AQ8: =Demanda!$F$10*(1+Parametros!$B$10)^3 -> 23232 | AR8: =Demanda!$F$11*(1+Parametros!$B$10)^3 -> 21894 | AS8: =Demanda!$F$12*(1+Parametros!$B$10)^3 -> 23028 | AT8: =Demanda!$F$13*(1+Parametros!$B$10)^3 -> 25933 | AU8: =Demanda!$F$14*(1+Parametros!$B$10)^3 -> 23273 | AV8: =Demanda!$F$15*(1+Parametros!$B$10)^3 -> 21753 | AW8: =Demanda!$F$16*(1+Parametros!$B$10)^3 -> 24032 | AX8: =Demanda!$F$5*(1+Parametros!$B$10)^4 -> 21691 | AY8: =Demanda!$F$6*(1+Parametros!$B$10)^4 -> 22362 | AZ8: =Demanda!$F$7*(1+Parametros!$B$10)^4 -> 23034 | BA8: =Demanda!$F$8*(1+Parametros!$B$10)^4 -> 25180 | BB8: =Demanda!$F$9*(1+Parametros!$B$10)^4 -> 23737 | BC8: =Demanda!$F$10*(1+Parametros!$B$10)^4 -> 23232 | BD8: =Demanda!$F$11*(1+Parametros!$B$10)^4 -> 21894 | BE8: =Demanda!$F$12*(1+Parametros!$B$10)^4 -> 23028 | BF8: =Demanda!$F$13*(1+Parametros!$B$10)^4 -> 25933 | BG8: =Demanda!$F$14*(1+Parametros!$B$10)^4 -> 23273 | BH8: =Demanda!$F$15*(1+Parametros!$B$10)^4 -> 21753 | BI8: =Demanda!$F$16*(1+Parametros!$B$10)^4 -> 24032
A9: Ingresos base | B9: =B6*Parametros!$B$20+B7*Parametros!$B$21+B8*Parametros!$B$22 -> 44132682300 | C9: =C6*Parametros!$B$20+C7*Parametros!$B$21+C8*Parametros!$B$22 -> 45499010600 | D9: =D6*Parametros!$B$20+D7*Parametros!$B$21+D8*Parametros!$B$22 -> 47305905850 | E9: =E6*Parametros!$B$20+E7*Parametros!$B$21+E8*Parametros!$B$22 -> 50210031400 | F9: =F6*Parametros!$B$20+F7*Parametros!$B$21+F8*Parametros!$B$22 -> 46897315150 | G9: =G6*Parametros!$B$20+G7*Parametros!$B$21+G8*Parametros!$B$22 -> 45820147800 | H9: =H6*Parametros!$B$20+H7*Parametros!$B$21+H8*Parametros!$B$22 -> 46743513500 | I9: =I6*Parametros!$B$20+I7*Parametros!$B$21+I8*Parametros!$B$22 -> 49259165250 | ... BI9: =BI6*Parametros!$B$20+BI7*Parametros!$B$21+BI8*Parametros!$B$22 -> 48868029300
A10: COGS variable base | B10: =B6*Costos_Lote!$B$18+B7*Costos_Lote!$B$33+B8*Costos_Lote!$B$46 -> 24814796268 | C10: =C6*Costos_Lote!$B$18+C7*Costos_Lote!$B$33+C8*Costos_Lote!$B$46 -> 25583051184 | D10: =D6*Costos_Lote!$B$18+D7*Costos_Lote!$B$33+D8*Costos_Lote!$B$46 -> 26535762249 | E10: =E6*Costos_Lote!$B$18+E7*Costos_Lote!$B$33+E8*Costos_Lote!$B$46 -> 28149332255 | F10: =F6*Costos_Lote!$B$18+F7*Costos_Lote!$B$33+F8*Costos_Lote!$B$46 -> 26354583042 | G10: =G6*Costos_Lote!$B$18+G7*Costos_Lote!$B$33+G8*Costos_Lote!$B$46 -> 25773975491 | H10: =H6*Costos_Lote!$B$18+H7*Costos_Lote!$B$33+H8*Costos_Lote!$B$46 -> 26216999374 | I10: =I6*Costos_Lote!$B$18+I7*Costos_Lote!$B$33+I8*Costos_Lote!$B$46 -> 27667351664 | ... BI10: =BI6*Costos_Lote!$B$18+BI7*Costos_Lote!$B$33+BI8*Costos_Lote!$B$46 -> 27441564257
A11: Utilidad bruta base | B11: =B9-B10 -> 19317886032 | C11: =C9-C10 -> 19915959416 | D11: =D9-D10 -> 20770143601 | E11: =E9-E10 -> 22060699145 | F11: =F9-F10 -> 20542732108 | G11: =G9-G10 -> 20046172309 | H11: =H9-H10 -> 20526514126 | I11: =I9-I10 -> 21591813586 | ... BI11: =BI9-BI10 -> 21426465043
A12: Nomina operacion | B12: {=INDEX(RRHH!$E:$E,MATCH("Costo mensual OPERACION (→ ER)",RRHH!$A:$A,0))} -> 85915382 | C12: {=INDEX(RRHH!$E:$E,MATCH("Costo mensual OPERACION (→ ER)",RRHH!$A:$A,0))} -> 85915382 | D12: {=INDEX(RRHH!$E:$E,MATCH("Costo mensual OPERACION (→ ER)",RRHH!$A:$A,0))} -> 85915382 | E12: {=INDEX(RRHH!$E:$E,MATCH("Costo mensual OPERACION (→ ER)",RRHH!$A:$A,0))} -> 85915382 | F12: {=INDEX(RRHH!$E:$E,MATCH("Costo mensual OPERACION (→ ER)",RRHH!$A:$A,0))} -> 85915382 | G12: {=INDEX(RRHH!$E:$E,MATCH("Costo mensual OPERACION (→ ER)",RRHH!$A:$A,0))} -> 85915382 | H12: {=INDEX(RRHH!$E:$E,MATCH("Costo mensual OPERACION (→ ER)",RRHH!$A:$A,0))} -> 85915382 | I12: {=INDEX(RRHH!$E:$E,MATCH("Costo mensual OPERACION (→ ER)",RRHH!$A:$A,0))} -> 85915382 | ... BI12: {=INDEX(RRHH!$E:$E,MATCH("Costo mensual OPERACION (→ ER)",RRHH!$A:$A,0))} -> 85915382
A13: Otros fijos base | B13: =Parametros!$B$25 -> 250000000 | C13: =Parametros!$B$25 -> 250000000 | D13: =Parametros!$B$25 -> 250000000 | E13: =Parametros!$B$25 -> 250000000 | F13: =Parametros!$B$25 -> 250000000 | G13: =Parametros!$B$25 -> 250000000 | H13: =Parametros!$B$25 -> 250000000 | I13: =Parametros!$B$25 -> 250000000 | ... BI13: =Parametros!$B$25 -> 250000000
A14: EBITDA base | B14: =B11-B12-B13 -> 18981970650 | C14: =C11-C12-C13 -> 19580044034 | D14: =D11-D12-D13 -> 20434228219 | E14: =E11-E12-E13 -> 21724783763 | F14: =F11-F12-F13 -> 20206816726 | G14: =G11-G12-G13 -> 19710256927 | H14: =H11-H12-H13 -> 20190598744 | I14: =I11-I12-I13 -> 21255898204 | ... BI14: =BI11-BI12-BI13 -> 21090549661
A15: CASO PROYECTO (retrofit)
A16: Factor ventas (uplift monetizado) | B16: =1 -> 1 | C16: =1 -> 1 | D16: =1 -> 1 | E16: =1 -> 1 | F16: =1+Parametros!$B$13*Parametros!$B$11*Parametros!$B$12 -> 1.022847 | G16: =1+Parametros!$B$11*Parametros!$B$12 -> 1.0341 | H16: =1+Parametros!$B$11*Parametros!$B$12 -> 1.0341 | I16: =1+Parametros!$B$11*Parametros!$B$12 -> 1.0341 | J16: =1+Parametros!$B$11*Parametros!$B$12 -> 1.0341 | K16: =1+Parametros!$B$11*Parametros!$B$12 -> 1.0341 | L16: =1+Parametros!$B$11*Parametros!$B$12 -> 1.0341 | M16: =1+Parametros!$B$11*Parametros!$B$12 -> 1.0341 | N16: =1+Parametros!$B$11*Parametros!$B$12 -> 1.0341 | ... BI16: =1+Parametros!$B$11*Parametros!$B$12 -> 1.0341
A17: Ingresos proyecto | B17: =B9*B16 -> 44132682300 | C17: =C9*C16 -> 45499010600 | D17: =D9*D16 -> 47305905850 | E17: =E9*E16 -> 50210031400 | F17: =F9*F16 -> 47968778109 | G17: =G9*G16 -> 47382614840 | H17: =H9*H16 -> 48337467310 | I17: =I9*I16 -> 50938902785 | ... BI17: =BI9*BI16 -> 50534429099
A18: COGS variable proyecto | B18: =B10*B16 -> 24814796268 | C18: =C10*C16 -> 25583051184 | D18: =D10*D16 -> 26535762249 | E18: =E10*E16 -> 28149332255 | F18: =F10*F16 -> 26956706201 | G18: =G10*G16 -> 26652868055 | H18: =H10*H16 -> 27110999053 | I18: =I10*I16 -> 28610808356 | ... BI18: =BI10*BI16 -> 28377321598
A19: (+) Ahorro de scrap | B19: =B18*Parametros!$B$14*0 -> 0 | C19: =C18*Parametros!$B$14*0 -> 0 | D19: =D18*Parametros!$B$14*0 -> 0 | E19: =E18*Parametros!$B$14*0 -> 0 | F19: =F18*Parametros!$B$14*Parametros!$B$13 -> 7224397.3 | G19: =G18*Parametros!$B$14*1 -> 10661147 | H19: =H18*Parametros!$B$14*1 -> 10844400 | I19: =I18*Parametros!$B$14*1 -> 11444323 | J19: =J18*Parametros!$B$14*1 -> 13328162 | K19: =K18*Parametros!$B$14*1 -> 10942710 | L19: =L18*Parametros!$B$14*1 -> 10126227 | M19: =M18*Parametros!$B$14*1 -> 11350929 | N19: =N18*Parametros!$B$14*1 -> 10264392 | ... BI19: =BI18*Parametros!$B$14*1 -> 11350929
A20: (+) Mantenimiento correctivo evitado | B20: =Parametros!$B$15*0 -> 0 | C20: =Parametros!$B$15*0 -> 0 | D20: =Parametros!$B$15*0 -> 0 | E20: =Parametros!$B$15*0 -> 0 | F20: =Parametros!$B$15*Parametros!$B$13 -> 56950000 | G20: =Parametros!$B$15*1 -> 85000000 | H20: =Parametros!$B$15*1 -> 85000000 | I20: =Parametros!$B$15*1 -> 85000000 | J20: =Parametros!$B$15*1 -> 85000000 | K20: =Parametros!$B$15*1 -> 85000000 | L20: =Parametros!$B$15*1 -> 85000000 | M20: =Parametros!$B$15*1 -> 85000000 | N20: =Parametros!$B$15*1 -> 85000000 | ... BI20: =Parametros!$B$15*1 -> 85000000
A21: Otros fijos proyecto | B21: =Parametros!$B$25 -> 250000000 | C21: =Parametros!$B$25 -> 250000000 | D21: =Parametros!$B$25 -> 250000000 | E21: =Parametros!$B$25 -> 250000000 | F21: =Parametros!$B$26 -> 280000000 | G21: =Parametros!$B$26 -> 280000000 | H21: =Parametros!$B$26 -> 280000000 | I21: =Parametros!$B$26 -> 280000000 | J21: =Parametros!$B$26 -> 280000000 | K21: =Parametros!$B$26 -> 280000000 | L21: =Parametros!$B$26 -> 280000000 | M21: =Parametros!$B$26 -> 280000000 | ... BI21: =Parametros!$B$26 -> 280000000
A22: OPEX licencias | B22: =Licencias!$H$14 -> 0 | C22: =Licencias!$H$14 -> 0 | D22: =Licencias!$H$14 -> 0 | E22: =Licencias!$H$14 -> 0 | F22: =Licencias!$H$14 -> 0 | G22: =Licencias!$H$14 -> 0 | H22: =Licencias!$H$14 -> 0 | I22: =Licencias!$H$14 -> 0 | ... BI22: =Licencias!$H$14 -> 0
A23: EBITDA proyecto | B23: {=B17-B18-B12-B21-B22+B19+B20+INDEX(Parametros!$B:$B,MATCH("ahorro_laboral_monetizable_mes",Parametros!$A:$A,0))*IF(1<=4,0,IF(1=5,Parametros!$B$13,1))} -> 18981970650 | C23: {=C17-C18-C12-C21-C22+C19+C20+INDEX(Parametros!$B:$B,MATCH("ahorro_laboral_monetizable_mes",Parametros!$A:$A,0))*IF(2<=4,0,IF(2=5,Parametros!$B$13,1))} -> 19580044034 | D23: {=D17-D18-D12-D21-D22+D19+D20+INDEX(Parametros!$B:$B,MATCH("ahorro_laboral_monetizable_mes",Parametros!$A:$A,0))*IF(3<=4,0,IF(3=5,Parametros!$B$13,1))} -> 20434228219 | E23: {=E17-E18-E12-E21-E22+E19+E20+INDEX(Parametros!$B:$B,MATCH("ahorro_laboral_monetizable_mes",Parametros!$A:$A,0))*IF(4<=4,0,IF(4=5,Parametros!$B$13,1))} -> 21724783763 | F23: {=F17-F18-F12-F21-F22+F19+F20+INDEX(Parametros!$B:$B,MATCH("ahorro_laboral_monetizable_mes",Parametros!$A:$A,0))*IF(5<=4,0,IF(5=5,Parametros!$B$13,1))} -> 20728274292 | G23: {=G17-G18-G12-G21-G22+G19+G20+INDEX(Parametros!$B:$B,MATCH("ahorro_laboral_monetizable_mes",Parametros!$A:$A,0))*IF(6<=4,0,IF(6=5,Parametros!$B$13,1))} -> 20486273696 | H23: {=H17-H18-H12-H21-H22+H19+H20+INDEX(Parametros!$B:$B,MATCH("ahorro_laboral_monetizable_mes",Parametros!$A:$A,0))*IF(7<=4,0,IF(7=5,Parametros!$B$13,1))} -> 20983178421 | I23: {=I17-I18-I12-I21-I22+I19+I20+INDEX(Parametros!$B:$B,MATCH("ahorro_laboral_monetizable_mes",Parametros!$A:$A,0))*IF(8<=4,0,IF(8=5,Parametros!$B$13,1))} -> 22085404516 | J23: {=J17-J18-J12-J21-J22+J19+J20+INDEX(Parametros!$B:$B,MATCH("ahorro_laboral_monetizable_mes",Parametros!$A:$A,0))*IF(9<=4,0,IF(9=5,Parametros!$B$13,1))} -> 25738555644 | K23: {=K17-K18-K12-K21-K22+K19+K20+INDEX(Parametros!$B:$B,MATCH("ahorro_laboral_monetizable_mes",Parametros!$A:$A,0))*IF(10<=4,0,IF(10=5,Parametros!$B$13,1))} -> 21140428621 | L23: {=L17-L18-L12-L21-L22+L19+L20+INDEX(Parametros!$B:$B,MATCH("ahorro_laboral_monetizable_mes",Parametros!$A:$A,0))*IF(11<=4,0,IF(11=5,Parametros!$B$13,1))} -> 19544223401 | M23: {=M17-M18-M12-M21-M22+M19+M20+INDEX(Parametros!$B:$B,MATCH("ahorro_laboral_monetizable_mes",Parametros!$A:$A,0))*IF(12<=4,0,IF(12=5,Parametros!$B$13,1))} -> 21914324194 | N23: {=N17-N18-N12-N21-N22+N19+N20+INDEX(Parametros!$B:$B,MATCH("ahorro_laboral_monetizable_mes",Parametros!$A:$A,0))*IF(13<=4,0,IF(13=5,Parametros!$B$13,1))} -> 19732756102 | O23: {=O17-O18-O12-O21-O22+O19+O20+INDEX(Parametros!$B:$B,MATCH("ahorro_laboral_monetizable_mes",Parametros!$A:$A,0))*IF(14<=4,0,IF(14=5,Parametros!$B$13,1))} -> 20351541569 | P23: {=P17-P18-P12-P21-P22+P19+P20+INDEX(Parametros!$B:$B,MATCH("ahorro_laboral_monetizable_mes",Parametros!$A:$A,0))*IF(15<=4,0,IF(15=5,Parametros!$B$13,1))} -> 21235247514 | Q23: {=Q17-Q18-Q12-Q21-Q22+Q19+Q20+INDEX(Parametros!$B:$B,MATCH("ahorro_laboral_monetizable_mes",Parametros!$A:$A,0))*IF(16<=4,0,IF(16=5,Parametros!$B$13,1))} -> 22570478440 | R23: {=R17-R18-R12-R21-R22+R19+R20+INDEX(Parametros!$B:$B,MATCH("ahorro_laboral_monetizable_mes",Parametros!$A:$A,0))*IF(17<=4,0,IF(17=5,Parametros!$B$13,1))} -> 21000006347 | S23: {=S17-S18-S12-S21-S22+S19+S20+INDEX(Parametros!$B:$B,MATCH("ahorro_laboral_monetizable_mes",Parametros!$A:$A,0))*IF(18<=4,0,IF(18=5,Parametros!$B$13,1))} -> 20486273696 | T23: {=T17-T18-T12-T21-T22+T19+T20+INDEX(Parametros!$B:$B,MATCH("ahorro_laboral_monetizable_mes",Parametros!$A:$A,0))*IF(19<=4,0,IF(19=5,Parametros!$B$13,1))} -> 20983178421 | U23: {=U17-U18-U12-U21-U22+U19+U20+INDEX(Parametros!$B:$B,MATCH("ahorro_laboral_monetizable_mes",Parametros!$A:$A,0))*IF(20<=4,0,IF(20=5,Parametros!$B$13,1))} -> 22085404516 | V23: {=V17-V18-V12-V21-V22+V19+V20+INDEX(Parametros!$B:$B,MATCH("ahorro_laboral_monetizable_mes",Parametros!$A:$A,0))*IF(21<=4,0,IF(21=5,Parametros!$B$13,1))} -> 25738555644 | W23: {=W17-W18-W12-W21-W22+W19+W20+INDEX(Parametros!$B:$B,MATCH("ahorro_laboral_monetizable_mes",Parametros!$A:$A,0))*IF(22<=4,0,IF(22=5,Parametros!$B$13,1))} -> 21140428621 | X23: {=X17-X18-X12-X21-X22+X19+X20+INDEX(Parametros!$B:$B,MATCH("ahorro_laboral_monetizable_mes",Parametros!$A:$A,0))*IF(23<=4,0,IF(23=5,Parametros!$B$13,1))} -> 19544223401 | Y23: {=Y17-Y18-Y12-Y21-Y22+Y19+Y20+INDEX(Parametros!$B:$B,MATCH("ahorro_laboral_monetizable_mes",Parametros!$A:$A,0))*IF(24<=4,0,IF(24=5,Parametros!$B$13,1))} -> 21914324194 | Z23: {=Z17-Z18-Z12-Z21-Z22+Z19+Z20+INDEX(Parametros!$B:$B,MATCH("ahorro_laboral_monetizable_mes",Parametros!$A:$A,0))*IF(25<=4,0,IF(25=5,Parametros!$B$13,1))} -> 19732756102 | AA23: {=AA17-AA18-AA12-AA21-AA22+AA19+AA20+INDEX(Parametros!$B:$B,MATCH("ahorro_laboral_monetizable_mes",Parametros!$A:$A,0))*IF(26<=4,0,IF(26=5,Parametros!$B$13,1))} -> 20351541569 | AB23: {=AB17-AB18-AB12-AB21-AB22+AB19+AB20+INDEX(Parametros!$B:$B,MATCH("ahorro_laboral_monetizable_mes",Parametros!$A:$A,0))*IF(27<=4,0,IF(27=5,Parametros!$B$13,1))} -> 21235247514 | AC23: {=AC17-AC18-AC12-AC21-AC22+AC19+AC20+INDEX(Parametros!$B:$B,MATCH("ahorro_laboral_monetizable_mes",Parametros!$A:$A,0))*IF(28<=4,0,IF(28=5,Parametros!$B$13,1))} -> 22570478440 | AD23: {=AD17-AD18-AD12-AD21-AD22+AD19+AD20+INDEX(Parametros!$B:$B,MATCH("ahorro_laboral_monetizable_mes",Parametros!$A:$A,0))*IF(29<=4,0,IF(29=5,Parametros!$B$13,1))} -> 21000006347 | AE23: {=AE17-AE18-AE12-AE21-AE22+AE19+AE20+INDEX(Parametros!$B:$B,MATCH("ahorro_laboral_monetizable_mes",Parametros!$A:$A,0))*IF(30<=4,0,IF(30=5,Parametros!$B$13,1))} -> 20486273696 | AF23: {=AF17-AF18-AF12-AF21-AF22+AF19+AF20+INDEX(Parametros!$B:$B,MATCH("ahorro_laboral_monetizable_mes",Parametros!$A:$A,0))*IF(31<=4,0,IF(31=5,Parametros!$B$13,1))} -> 20983178421 | AG23: {=AG17-AG18-AG12-AG21-AG22+AG19+AG20+INDEX(Parametros!$B:$B,MATCH("ahorro_laboral_monetizable_mes",Parametros!$A:$A,0))*IF(32<=4,0,IF(32=5,Parametros!$B$13,1))} -> 22085404516 | AH23: {=AH17-AH18-AH12-AH21-AH22+AH19+AH20+INDEX(Parametros!$B:$B,MATCH("ahorro_laboral_monetizable_mes",Parametros!$A:$A,0))*IF(33<=4,0,IF(33=5,Parametros!$B$13,1))} -> 25738555644 | AI23: {=AI17-AI18-AI12-AI21-AI22+AI19+AI20+INDEX(Parametros!$B:$B,MATCH("ahorro_laboral_monetizable_mes",Parametros!$A:$A,0))*IF(34<=4,0,IF(34=5,Parametros!$B$13,1))} -> 21140428621 | AJ23: {=AJ17-AJ18-AJ12-AJ21-AJ22+AJ19+AJ20+INDEX(Parametros!$B:$B,MATCH("ahorro_laboral_monetizable_mes",Parametros!$A:$A,0))*IF(35<=4,0,IF(35=5,Parametros!$B$13,1))} -> 19544223401 | AK23: {=AK17-AK18-AK12-AK21-AK22+AK19+AK20+INDEX(Parametros!$B:$B,MATCH("ahorro_laboral_monetizable_mes",Parametros!$A:$A,0))*IF(36<=4,0,IF(36=5,Parametros!$B$13,1))} -> 21914324194 | AL23: {=AL17-AL18-AL12-AL21-AL22+AL19+AL20+INDEX(Parametros!$B:$B,MATCH("ahorro_laboral_monetizable_mes",Parametros!$A:$A,0))*IF(37<=4,0,IF(37=5,Parametros!$B$13,1))} -> 19732756102 | AM23: {=AM17-AM18-AM12-AM21-AM22+AM19+AM20+INDEX(Parametros!$B:$B,MATCH("ahorro_laboral_monetizable_mes",Parametros!$A:$A,0))*IF(38<=4,0,IF(38=5,Parametros!$B$13,1))} -> 20351541569 | AN23: {=AN17-AN18-AN12-AN21-AN22+AN19+AN20+INDEX(Parametros!$B:$B,MATCH("ahorro_laboral_monetizable_mes",Parametros!$A:$A,0))*IF(39<=4,0,IF(39=5,Parametros!$B$13,1))} -> 21235247514 | AO23: {=AO17-AO18-AO12-AO21-AO22+AO19+AO20+INDEX(Parametros!$B:$B,MATCH("ahorro_laboral_monetizable_mes",Parametros!$A:$A,0))*IF(40<=4,0,IF(40=5,Parametros!$B$13,1))} -> 22570478440 | AP23: {=AP17-AP18-AP12-AP21-AP22+AP19+AP20+INDEX(Parametros!$B:$B,MATCH("ahorro_laboral_monetizable_mes",Parametros!$A:$A,0))*IF(41<=4,0,IF(41=5,Parametros!$B$13,1))} -> 21000006347 | AQ23: {=AQ17-AQ18-AQ12-AQ21-AQ22+AQ19+AQ20+INDEX(Parametros!$B:$B,MATCH("ahorro_laboral_monetizable_mes",Parametros!$A:$A,0))*IF(42<=4,0,IF(42=5,Parametros!$B$13,1))} -> 20486273696 | AR23: {=AR17-AR18-AR12-AR21-AR22+AR19+AR20+INDEX(Parametros!$B:$B,MATCH("ahorro_laboral_monetizable_mes",Parametros!$A:$A,0))*IF(43<=4,0,IF(43=5,Parametros!$B$13,1))} -> 20983178421 | AS23: {=AS17-AS18-AS12-AS21-AS22+AS19+AS20+INDEX(Parametros!$B:$B,MATCH("ahorro_laboral_monetizable_mes",Parametros!$A:$A,0))*IF(44<=4,0,IF(44=5,Parametros!$B$13,1))} -> 22085404516 | AT23: {=AT17-AT18-AT12-AT21-AT22+AT19+AT20+INDEX(Parametros!$B:$B,MATCH("ahorro_laboral_monetizable_mes",Parametros!$A:$A,0))*IF(45<=4,0,IF(45=5,Parametros!$B$13,1))} -> 25738555644 | AU23: {=AU17-AU18-AU12-AU21-AU22+AU19+AU20+INDEX(Parametros!$B:$B,MATCH("ahorro_laboral_monetizable_mes",Parametros!$A:$A,0))*IF(46<=4,0,IF(46=5,Parametros!$B$13,1))} -> 21140428621 | AV23: {=AV17-AV18-AV12-AV21-AV22+AV19+AV20+INDEX(Parametros!$B:$B,MATCH("ahorro_laboral_monetizable_mes",Parametros!$A:$A,0))*IF(47<=4,0,IF(47=5,Parametros!$B$13,1))} -> 19544223401 | AW23: {=AW17-AW18-AW12-AW21-AW22+AW19+AW20+INDEX(Parametros!$B:$B,MATCH("ahorro_laboral_monetizable_mes",Parametros!$A:$A,0))*IF(48<=4,0,IF(48=5,Parametros!$B$13,1))} -> 21914324194 | AX23: {=AX17-AX18-AX12-AX21-AX22+AX19+AX20+INDEX(Parametros!$B:$B,MATCH("ahorro_laboral_monetizable_mes",Parametros!$A:$A,0))*IF(49<=4,0,IF(49=5,Parametros!$B$13,1))} -> 19732756102 | AY23: {=AY17-AY18-AY12-AY21-AY22+AY19+AY20+INDEX(Parametros!$B:$B,MATCH("ahorro_laboral_monetizable_mes",Parametros!$A:$A,0))*IF(50<=4,0,IF(50=5,Parametros!$B$13,1))} -> 20351541569 | AZ23: {=AZ17-AZ18-AZ12-AZ21-AZ22+AZ19+AZ20+INDEX(Parametros!$B:$B,MATCH("ahorro_laboral_monetizable_mes",Parametros!$A:$A,0))*IF(51<=4,0,IF(51=5,Parametros!$B$13,1))} -> 21235247514 | BA23: {=BA17-BA18-BA12-BA21-BA22+BA19+BA20+INDEX(Parametros!$B:$B,MATCH("ahorro_laboral_monetizable_mes",Parametros!$A:$A,0))*IF(52<=4,0,IF(52=5,Parametros!$B$13,1))} -> 22570478440 | BB23: {=BB17-BB18-BB12-BB21-BB22+BB19+BB20+INDEX(Parametros!$B:$B,MATCH("ahorro_laboral_monetizable_mes",Parametros!$A:$A,0))*IF(53<=4,0,IF(53=5,Parametros!$B$13,1))} -> 21000006347 | BC23: {=BC17-BC18-BC12-BC21-BC22+BC19+BC20+INDEX(Parametros!$B:$B,MATCH("ahorro_laboral_monetizable_mes",Parametros!$A:$A,0))*IF(54<=4,0,IF(54=5,Parametros!$B$13,1))} -> 20486273696 | BD23: {=BD17-BD18-BD12-BD21-BD22+BD19+BD20+INDEX(Parametros!$B:$B,MATCH("ahorro_laboral_monetizable_mes",Parametros!$A:$A,0))*IF(55<=4,0,IF(55=5,Parametros!$B$13,1))} -> 20983178421 | BE23: {=BE17-BE18-BE12-BE21-BE22+BE19+BE20+INDEX(Parametros!$B:$B,MATCH("ahorro_laboral_monetizable_mes",Parametros!$A:$A,0))*IF(56<=4,0,IF(56=5,Parametros!$B$13,1))} -> 22085404516 | BF23: {=BF17-BF18-BF12-BF21-BF22+BF19+BF20+INDEX(Parametros!$B:$B,MATCH("ahorro_laboral_monetizable_mes",Parametros!$A:$A,0))*IF(57<=4,0,IF(57=5,Parametros!$B$13,1))} -> 25738555644 | BG23: {=BG17-BG18-BG12-BG21-BG22+BG19+BG20+INDEX(Parametros!$B:$B,MATCH("ahorro_laboral_monetizable_mes",Parametros!$A:$A,0))*IF(58<=4,0,IF(58=5,Parametros!$B$13,1))} -> 21140428621 | BH23: {=BH17-BH18-BH12-BH21-BH22+BH19+BH20+INDEX(Parametros!$B:$B,MATCH("ahorro_laboral_monetizable_mes",Parametros!$A:$A,0))*IF(59<=4,0,IF(59=5,Parametros!$B$13,1))} -> 19544223401 | BI23: {=BI17-BI18-BI12-BI21-BI22+BI19+BI20+INDEX(Parametros!$B:$B,MATCH("ahorro_laboral_monetizable_mes",Parametros!$A:$A,0))*IF(60<=4,0,IF(60=5,Parametros!$B$13,1))} -> 21914324194
A24: INCREMENTAL (proyecto − base)
A25: EBITDA incremental | B25: =B23-B14 -> 0 | C25: =C23-C14 -> 0 | D25: =D23-D14 -> 0 | E25: =E23-E14 -> 0 | F25: =F23-F14 -> 5.2145757e+08 | G25: =G23-G14 -> 776016769 | H25: =H23-H14 -> 7.9257968e+08 | I25: =I23-I14 -> 8.2950631e+08 | ... BI25: =BI23-BI14 -> 8.2377453e+08
A26: D&A (desde mes 5) | B26: =0 -> 0 | C26: =0 -> 0 | D26: =0 -> 0 | E26: =0 -> 0 | F26: =Dep_Amort!$D$10 -> 95119495 | G26: =Dep_Amort!$D$10 -> 95119495 | H26: =Dep_Amort!$D$10 -> 95119495 | I26: =Dep_Amort!$D$10 -> 95119495 | J26: =Dep_Amort!$D$10 -> 95119495 | K26: =Dep_Amort!$D$10 -> 95119495 | L26: =Dep_Amort!$D$10 -> 95119495 | M26: =Dep_Amort!$D$10 -> 95119495 | ... BI26: =Dep_Amort!$D$10 -> 95119495
A27: EBIT incremental | B27: =B25-B26 -> 0 | C27: =C25-C26 -> 0 | D27: =D25-D26 -> 0 | E27: =E25-E26 -> 0 | F27: =F25-F26 -> 4.2633807e+08 | G27: =G25-G26 -> 680897274 | H27: =H25-H26 -> 6.9746018e+08 | I27: =I25-I26 -> 7.3438682e+08 | ... BI27: =BI25-BI26 -> 7.2865504e+08
A28: Impuesto de renta (35%) | B28: =MAX(0,B27)*Parametros!$B$8 -> 0 | C28: =MAX(0,C27)*Parametros!$B$8 -> 0 | D28: =MAX(0,D27)*Parametros!$B$8 -> 0 | E28: =MAX(0,E27)*Parametros!$B$8 -> 0 | F28: =MAX(0,F27)*Parametros!$B$8 -> 1.4921832e+08 | G28: =MAX(0,G27)*Parametros!$B$8 -> 2.3831405e+08 | H28: =MAX(0,H27)*Parametros!$B$8 -> 2.4411106e+08 | I28: =MAX(0,I27)*Parametros!$B$8 -> 2.5703539e+08 | ... BI28: =MAX(0,BI27)*Parametros!$B$8 -> 2.5502926e+08
A29: Utilidad neta incremental | B29: =B27-B28 -> 0 | C29: =C27-C28 -> 0 | D29: =D27-D28 -> 0 | E29: =E27-E28 -> 0 | F29: =F27-F28 -> 2.7711975e+08 | G29: =G27-G28 -> 4.4258323e+08 | H29: =H27-H28 -> 4.5334912e+08 | I29: =I27-I28 -> 4.7735143e+08 | ... BI29: =BI27-BI28 -> 4.7362577e+08

Sheet CAPEX
A1: CAPEX ULOGIX — L1 / L2 / L3 + infraestructura transversal
A2: Fuente viva del ERP. Cantidad y costo unitario son entradas editables; CAPEX COP, subtotales y total son fórmulas. Licencias perpetuas vienen de la hoja Licencias.
A4: seccion | B4: linea | C4: activo / paquete | D4: cant. | E4: moneda | F4: costo unitario | G4: CAPEX COP | H4: vida (años) | I4: categoria D&A
C5: ▍ L1 — COCA-COLA 350 ml · VIDRIO RETORNABLE
A6: Maquinaria usada | B6: L1 | C6: Llenadora/tapadora KRONES usada 44.000 bph (VODM/Modulfill; reserva RFQ) | D6: 1 | E6: USD | F6: 550000 | G6: {=IF($E6="COP",$D6*$F6,IF($E6="USD*",$D6*$F6*Parametros!$B$5,IF($E6="GBP*",$D6*$F6*INDEX(Parametros!$B:$B,MATCH("gbp_cop",Parametros!$A:$A,0)),$D6*$F6*Parametros!$B$5*Parametros!$B$6)))} -> 1733272145 | H6: 10 | I6: equipos
A7: Maquinaria usada | B7: L1 | C7: Conveyors, motores y VFD para llenado y encajonado | D7: 1 | E7: USD | F7: 100000 | G7: {=IF($E7="COP",$D7*$F7,IF($E7="USD*",$D7*$F7*Parametros!$B$5,IF($E7="GBP*",$D7*$F7*INDEX(Parametros!$B:$B,MATCH("gbp_cop",Parametros!$A:$A,0)),$D7*$F7*Parametros!$B$5*Parametros!$B$6)))} -> 315140390 | H7: 7 | I7: equipos
A8: Diseño ULogix | B8: L1 | C8: Encajonadora custom para canastilla 30x30 (BOM de ingenieria; reserva RFQ) | D8: 1 | E8: USD | F8: 60000 | G8: {=IF($E8="COP",$D8*$F8,IF($E8="USD*",$D8*$F8*Parametros!$B$5,IF($E8="GBP*",$D8*$F8*INDEX(Parametros!$B:$B,MATCH("gbp_cop",Parametros!$A:$A,0)),$D8*$F8*Parametros!$B$5*Parametros!$B$6)))} -> 189084234 | H8: 10 | I8: automatizacion
A9: Benchmark retrofit | B9: L1 | C9: Upgrade lavadora retornable / prewash (KRONES Lavatec) | D9: 0 | E9: USD | F9: 450000 | G9: {=IF($E9="COP",$D9*$F9,IF($E9="USD*",$D9*$F9*Parametros!$B$5,IF($E9="GBP*",$D9*$F9*INDEX(Parametros!$B:$B,MATCH("gbp_cop",Parametros!$A:$A,0)),$D9*$F9*Parametros!$B$5*Parametros!$B$6)))} -> 0 | H9: 10 | I9: equipos
A10: Benchmark retrofit | B10: L1 | C10: Inspeccion envase vacio (HEUFT SPECTRUM II SX) | D10: 0 | E10: USD | F10: 180000 | G10: {=IF($E10="COP",$D10*$F10,IF($E10="USD*",$D10*$F10*Parametros!$B$5,IF($E10="GBP*",$D10*$F10*INDEX(Parametros!$B:$B,MATCH("gbp_cop",Parametros!$A:$A,0)),$D10*$F10*Parametros!$B$5*Parametros!$B$6)))} -> 0 | H10: 7 | I10: automatizacion
A11: Benchmark retrofit | B11: L1 | C11: Etiquetadora y sincronizacion (servos) | D11: 0 | E11: USD | F11: 120000 | G11: {=IF($E11="COP",$D11*$F11,IF($E11="USD*",$D11*$F11*Parametros!$B$5,IF($E11="GBP*",$D11*$F11*INDEX(Parametros!$B:$B,MATCH("gbp_cop",Parametros!$A:$A,0)),$D11*$F11*Parametros!$B$5*Parametros!$B$6)))} -> 0 | H11: 7 | I11: automatizacion
C12: Subtotal — L1 — COCA-COLA 350 ml · VIDRIO RETORNABLE | G12: =SUM(G6:G11) -> 2237496769
C14: ▍ L2 — QuAtro 1,5 L · PET
A15: Maquinaria usada | B15: L2 | C15: Llenadora KRONES usada CSD PET 18.000 bph (Mecafill/Contiform; reserva RFQ) | D15: 1 | E15: USD | F15: 425000 | G15: {=IF($E15="COP",$D15*$F15,IF($E15="USD*",$D15*$F15*Parametros!$B$5,IF($E15="GBP*",$D15*$F15*INDEX(Parametros!$B:$B,MATCH("gbp_cop",Parametros!$A:$A,0)),$D15*$F15*Parametros!$B$5*Parametros!$B$6)))} -> 1339346658 | H15: 10 | I15: equipos
A16: Maquinaria usada | B16: L2 | C16: KRONES Variopac 459 usada para termoencogible (Machinio) | D16: 1 | E16: USD* | F16: 79900 | G16: {=IF($E16="COP",$D16*$F16,IF($E16="USD*",$D16*$F16*Parametros!$B$5,IF($E16="GBP*",$D16*$F16*INDEX(Parametros!$B:$B,MATCH("gbp_cop",Parametros!$A:$A,0)),$D16*$F16*Parametros!$B$5*Parametros!$B$6)))} -> 259584713 | H16: 7 | I16: equipos
A17: Maquinaria usada | B17: L2 | C17: Conveyors / transporte PET y enlace al GANTRY compartido | D17: 1 | E17: USD | F17: 90000 | G17: {=IF($E17="COP",$D17*$F17,IF($E17="USD*",$D17*$F17*Parametros!$B$5,IF($E17="GBP*",$D17*$F17*INDEX(Parametros!$B:$B,MATCH("gbp_cop",Parametros!$A:$A,0)),$D17*$F17*Parametros!$B$5*Parametros!$B$6)))} -> 283626351 | H17: 10 | I17: equipos
A18: Benchmark retrofit | B18: L2 | C18: Inspeccion botella llena (HEUFT PRIME) | D18: 0 | E18: USD | F18: 160000 | G18: {=IF($E18="COP",$D18*$F18,IF($E18="USD*",$D18*$F18*Parametros!$B$5,IF($E18="GBP*",$D18*$F18*INDEX(Parametros!$B:$B,MATCH("gbp_cop",Parametros!$A:$A,0)),$D18*$F18*Parametros!$B$5*Parametros!$B$6)))} -> 0 | H18: 7 | I18: automatizacion
C19: Subtotal — L2 — QuAtro 1,5 L · PET | G19: =SUM(G15:G18) -> 1882557722
C21: ▍ L1-L2 — GANTRY DE PALETIZADO COMPARTIDO
A22: Celdas roboticas (BOM real) | B22: L1-L2 | C22: Servomotor MU 300 (ABB) | D22: 1 | E22: USD* | F22: 2800 | G22: {=IF($E22="COP",$D22*$F22,IF($E22="USD*",$D22*$F22*Parametros!$B$5,IF($E22="GBP*",$D22*$F22*INDEX(Parametros!$B:$B,MATCH("gbp_cop",Parametros!$A:$A,0)),$D22*$F22*Parametros!$B$5*Parametros!$B$6)))} -> 9096836 | H22: 10 | I22: equipos
A23: Celdas roboticas (BOM real) | B23: L1-L2 | C23: Servomotor MU 200 (ABB) | D23: 1 | E23: USD* | F23: 2000 | G23: {=IF($E23="COP",$D23*$F23,IF($E23="USD*",$D23*$F23*Parametros!$B$5,IF($E23="GBP*",$D23*$F23*INDEX(Parametros!$B:$B,MATCH("gbp_cop",Parametros!$A:$A,0)),$D23*$F23*Parametros!$B$5*Parametros!$B$6)))} -> 6497740 | H23: 10 | I23: equipos
A24: Celdas roboticas (BOM real) | B24: L1-L2 | C24: Controlador IRC5 (ABB) - cotizacion IGAM, envio/logistica incluidos | D24: 1 | E24: USD* | F24: 6500 | G24: {=IF($E24="COP",$D24*$F24,IF($E24="USD*",$D24*$F24*Parametros!$B$5,IF($E24="GBP*",$D24*$F24*INDEX(Parametros!$B:$B,MATCH("gbp_cop",Parametros!$A:$A,0)),$D24*$F24*Parametros!$B$5*Parametros!$B$6)))} -> 21117655 | H24: 10 | I24: equipos
A25: Celdas roboticas (BOM real) | B25: L1-L2 | C25: Reductor AB115-005-S2-P2 (Apex Dynamics) | D25: 1 | E25: USD* | F25: 1100 | G25: {=IF($E25="COP",$D25*$F25,IF($E25="USD*",$D25*$F25*Parametros!$B$5,IF($E25="GBP*",$D25*$F25*INDEX(Parametros!$B:$B,MATCH("gbp_cop",Parametros!$A:$A,0)),$D25*$F25*Parametros!$B$5*Parametros!$B$6)))} -> 3573757 | H25: 10 | I25: equipos
A26: Celdas roboticas (BOM real) | B26: L1-L2 | C26: Eje lineal Rexroth_CKK280_S2200 (Bosch-Rexroth) | D26: 1 | E26: USD* | F26: 5500 | G26: {=IF($E26="COP",$D26*$F26,IF($E26="USD*",$D26*$F26*Parametros!$B$5,IF($E26="GBP*",$D26*$F26*INDEX(Parametros!$B:$B,MATCH("gbp_cop",Parametros!$A:$A,0)),$D26*$F26*Parametros!$B$5*Parametros!$B$6)))} -> 17868785 | H26: 10 | I26: equipos
A27: Celdas roboticas (BOM real) | B27: L1-L2 | C27: Eje lineal Rexroth_CKR280_S4600 (Bosch-Rexroth) | D27: 1 | E27: USD* | F27: 7500 | G27: {=IF($E27="COP",$D27*$F27,IF($E27="USD*",$D27*$F27*Parametros!$B$5,IF($E27="GBP*",$D27*$F27*INDEX(Parametros!$B:$B,MATCH("gbp_cop",Parametros!$A:$A,0)),$D27*$F27*Parametros!$B$5*Parametros!$B$6)))} -> 24366525 | H27: 10 | I27: equipos
A28: Celdas roboticas (BOM real) | B28: L1-L2 | C28: Acople ACP001 (Manufacturado) | D28: 1 | E28: USD* | F28: 450 | G28: {=IF($E28="COP",$D28*$F28,IF($E28="USD*",$D28*$F28*Parametros!$B$5,IF($E28="GBP*",$D28*$F28*INDEX(Parametros!$B:$B,MATCH("gbp_cop",Parametros!$A:$A,0)),$D28*$F28*Parametros!$B$5*Parametros!$B$6)))} -> 1461991.5 | H28: 10 | I28: equipos
A29: Celdas roboticas (BOM real) | B29: L1-L2 | C29: Perfil de soporte gantry SP001 (Manufacturado) | D29: 2 | E29: USD* | F29: 1200 | G29: {=IF($E29="COP",$D29*$F29,IF($E29="USD*",$D29*$F29*Parametros!$B$5,IF($E29="GBP*",$D29*$F29*INDEX(Parametros!$B:$B,MATCH("gbp_cop",Parametros!$A:$A,0)),$D29*$F29*Parametros!$B$5*Parametros!$B$6)))} -> 7797288 | H29: 10 | I29: equipos
A30: Celdas roboticas (BOM real) | B30: L1-L2 | C30: Gripper neumatico GRP001 4 mordazas 40 kg (Manufacturado) | D30: 1 | E30: USD* | F30: 9000 | G30: {=IF($E30="COP",$D30*$F30,IF($E30="USD*",$D30*$F30*Parametros!$B$5,IF($E30="GBP*",$D30*$F30*INDEX(Parametros!$B:$B,MATCH("gbp_cop",Parametros!$A:$A,0)),$D30*$F30*Parametros!$B$5*Parametros!$B$6)))} -> 29239830 | H30: 10 | I30: equipos
A31: Celdas roboticas (BOM real) | B31: L1-L2 | C31: Cilindro neumatico DSBC-80-150-PPSA-N3 (Festo) | D31: 8 | E31: USD* | F31: 220 | G31: {=IF($E31="COP",$D31*$F31,IF($E31="USD*",$D31*$F31*Parametros!$B$5,IF($E31="GBP*",$D31*$F31*INDEX(Parametros!$B:$B,MATCH("gbp_cop",Parametros!$A:$A,0)),$D31*$F31*Parametros!$B$5*Parametros!$B$6)))} -> 5718011.2 | H31: 10 | I31: equipos
A32: Celdas roboticas (BOM real) | B32: L1-L2 | C32: Valvula antirretorno HGL-3/8-QS-8 (Festo) | D32: 8 | E32: USD* | F32: 55 | G32: {=IF($E32="COP",$D32*$F32,IF($E32="USD*",$D32*$F32*Parametros!$B$5,IF($E32="GBP*",$D32*$F32*INDEX(Parametros!$B:$B,MATCH("gbp_cop",Parametros!$A:$A,0)),$D32*$F32*Parametros!$B$5*Parametros!$B$6)))} -> 1429502.8 | H32: 10 | I32: equipos
A33: Celdas roboticas (BOM real) | B33: L1-L2 | C33: Electrovalvula VUVS-L30-B52-D-G38-F8-1B2 (Festo) | D33: 1 | E33: USD* | F33: 220 | G33: {=IF($E33="COP",$D33*$F33,IF($E33="USD*",$D33*$F33*Parametros!$B$5,IF($E33="GBP*",$D33*$F33*INDEX(Parametros!$B:$B,MATCH("gbp_cop",Parametros!$A:$A,0)),$D33*$F33*Parametros!$B$5*Parametros!$B$6)))} -> 714751.4 | H33: 10 | I33: equipos
... A57: Celdas roboticas (BOM real) | B57: L1-L2 | C57: HMI CP620 (ABB) | D57: 1 | E57: USD* | F57: 650 | G57: {=IF($E57="COP",$D57*$F57,IF($E57="USD*",$D57*$F57*Parametros!$B$5,IF($E57="GBP*",$D57*$F57*INDEX(Parametros!$B:$B,MATCH("gbp_cop",Parametros!$A:$A,0)),$D57*$F57*Parametros!$B$5*Parametros!$B$6)))} -> 2111765.5 | H57: 10 | I57: equipos
C58: Subtotal — L1-L2 — GANTRY DE PALETIZADO COMPARTIDO | G58: =SUM(G22:G57) -> 3.1349321e+08
C60: ▍ L3 — GARRAFÓN 25 L · LLENADORA EXISTENTE
A61: Celdas roboticas (BOM real) | B61: L3 | C61: Robot ABB para garrafones - cotizacion EUROBOTS, envio/logistica incluidos | D61: 1 | E61: GBP* | F61: 13500 | G61: {=IF($E61="COP",$D61*$F61,IF($E61="USD*",$D61*$F61*Parametros!$B$5,IF($E61="GBP*",$D61*$F61*INDEX(Parametros!$B:$B,MATCH("gbp_cop",Parametros!$A:$A,0)),$D61*$F61*Parametros!$B$5*Parametros!$B$6)))} -> 59899500 | H61: 10 | I61: equipos
A62: Celdas roboticas (BOM real) | B62: L3 | C62: Controlador del robot (incluido en paquete EUROBOTS; no duplicar) | D62: 0 | E62: USD* | F62: 22000 | G62: {=IF($E62="COP",$D62*$F62,IF($E62="USD*",$D62*$F62*Parametros!$B$5,IF($E62="GBP*",$D62*$F62*INDEX(Parametros!$B:$B,MATCH("gbp_cop",Parametros!$A:$A,0)),$D62*$F62*Parametros!$B$5*Parametros!$B$6)))} -> 0 | H62: 10 | I62: equipos
A63: Celdas roboticas (BOM real) | B63: L3 | C63: Transportador PM 9710 (Interroll) | D63: 5 | E63: USD* | F63: 5500 | G63: {=IF($E63="COP",$D63*$F63,IF($E63="USD*",$D63*$F63*Parametros!$B$5,IF($E63="GBP*",$D63*$F63*INDEX(Parametros!$B:$B,MATCH("gbp_cop",Parametros!$A:$A,0)),$D63*$F63*Parametros!$B$5*Parametros!$B$6)))} -> 89343925 | H63: 10 | I63: equipos
A64: Celdas roboticas (BOM real) | B64: L3 | C64: Gripper neumatico GRP001 3 ventosas 15.5 kg (Manufacturado) | D64: 1 | E64: USD* | F64: 4500 | G64: {=IF($E64="COP",$D64*$F64,IF($E64="USD*",$D64*$F64*Parametros!$B$5,IF($E64="GBP*",$D64*$F64*INDEX(Parametros!$B:$B,MATCH("gbp_cop",Parametros!$A:$A,0)),$D64*$F64*Parametros!$B$5*Parametros!$B$6)))} -> 14619915 | H64: 10 | I64: equipos
A65: Celdas roboticas (BOM real) | B65: L3 | C65: Generador de vacio OVEM-14-L-B-QO-CE-N-1P (Festo) | D65: 3 | E65: USD* | F65: 320 | G65: {=IF($E65="COP",$D65*$F65,IF($E65="USD*",$D65*$F65*Parametros!$B$5,IF($E65="GBP*",$D65*$F65*INDEX(Parametros!$B:$B,MATCH("gbp_cop",Parametros!$A:$A,0)),$D65*$F65*Parametros!$B$5*Parametros!$B$6)))} -> 3118915.2 | H65: 10 | I65: equipos
A66: Celdas roboticas (BOM real) | B66: L3 | C66: Acumulador de vacio CRVZS-0.1 (Festo) | D66: 3 | E66: USD* | F66: 45 | G66: {=IF($E66="COP",$D66*$F66,IF($E66="USD*",$D66*$F66*Parametros!$B$5,IF($E66="GBP*",$D66*$F66*INDEX(Parametros!$B:$B,MATCH("gbp_cop",Parametros!$A:$A,0)),$D66*$F66*Parametros!$B$5*Parametros!$B$6)))} -> 438597.45 | H66: 10 | I66: equipos
A67: Celdas roboticas (BOM real) | B67: L3 | C67: Filtro de vacio VAF-PK-6 (Festo) | D67: 3 | E67: USD* | F67: 55 | G67: {=IF($E67="COP",$D67*$F67,IF($E67="USD*",$D67*$F67*Parametros!$B$5,IF($E67="GBP*",$D67*$F67*INDEX(Parametros!$B:$B,MATCH("gbp_cop",Parametros!$A:$A,0)),$D67*$F67*Parametros!$B$5*Parametros!$B$6)))} -> 536063.55 | H67: 10 | I67: equipos
A68: Celdas roboticas (BOM real) | B68: L3 | C68: Unidad FRL MS4-LFR-1/4-D6-C-P-M-AG-BAR-B (Festo) | D68: 1 | E68: USD* | F68: 220 | G68: {=IF($E68="COP",$D68*$F68,IF($E68="USD*",$D68*$F68*Parametros!$B$5,IF($E68="GBP*",$D68*$F68*INDEX(Parametros!$B:$B,MATCH("gbp_cop",Parametros!$A:$A,0)),$D68*$F68*Parametros!$B$5*Parametros!$B$6)))} -> 714751.4 | H68: 10 | I68: equipos
A69: Celdas roboticas (BOM real) | B69: L3 | C69: Vallado modular ImpactGuard System-H3120-S60-T30 (Satech) | D69: 20 | E69: USD* | F69: 220 | G69: {=IF($E69="COP",$D69*$F69,IF($E69="USD*",$D69*$F69*Parametros!$B$5,IF($E69="GBP*",$D69*$F69*INDEX(Parametros!$B:$B,MATCH("gbp_cop",Parametros!$A:$A,0)),$D69*$F69*Parametros!$B$5*Parametros!$B$6)))} -> 14295028 | H69: 10 | I69: equipos
A70: Celdas roboticas (BOM real) | B70: L3 | C70: Puerta Single Leaf Door ImpactGuard-H3120-S60-T30 (Satech) | D70: 1 | E70: USD* | F70: 750 | G70: {=IF($E70="COP",$D70*$F70,IF($E70="USD*",$D70*$F70*Parametros!$B$5,IF($E70="GBP*",$D70*$F70*INDEX(Parametros!$B:$B,MATCH("gbp_cop",Parametros!$A:$A,0)),$D70*$F70*Parametros!$B$5*Parametros!$B$6)))} -> 2436652.5 | H70: 10 | I70: equipos
A71: Celdas roboticas (BOM real) | B71: L3 | C71: Interlock AZM 415-02/02ZPK 24VAC/DC (Satech/Schmerzal) | D71: 1 | E71: USD* | F71: 320 | G71: {=IF($E71="COP",$D71*$F71,IF($E71="USD*",$D71*$F71*Parametros!$B$5,IF($E71="GBP*",$D71*$F71*INDEX(Parametros!$B:$B,MATCH("gbp_cop",Parametros!$A:$A,0)),$D71*$F71*Parametros!$B$5*Parametros!$B$6)))} -> 1039638.4 | H71: 10 | I71: equipos
A72: Celdas roboticas (BOM real) | B72: L3 | C72: Cortina optica ADMIRAL AD 1651 (ReeR) | D72: 2 | E72: USD* | F72: 1100 | G72: {=IF($E72="COP",$D72*$F72,IF($E72="USD*",$D72*$F72*Parametros!$B$5,IF($E72="GBP*",$D72*$F72*INDEX(Parametros!$B:$B,MATCH("gbp_cop",Parametros!$A:$A,0)),$D72*$F72*Parametros!$B$5*Parametros!$B$6)))} -> 7147514 | H72: 10 | I72: equipos
... A89: Fuera de alcance | B89: L3 | C89: Conveyors generales de garrafon (manejo de celda ya esta en BOM) | D89: 0 | E89: USD | F89: 110000 | G89: {=IF($E89="COP",$D89*$F89,IF($E89="USD*",$D89*$F89*Parametros!$B$5,IF($E89="GBP*",$D89*$F89*INDEX(Parametros!$B:$B,MATCH("gbp_cop",Parametros!$A:$A,0)),$D89*$F89*Parametros!$B$5*Parametros!$B$6)))} -> 0 | H89: 7 | I89: equipos
C90: Subtotal — L3 — GARRAFÓN 25 L · LLENADORA EXISTENTE | G90: =SUM(G61:G89) -> 2.0576077e+08
C92: ▍ TRANSVERSAL — L1 + L2 + L3
A93: Benchmark retrofit | B93: COMÚN | C93: PLC panels / I/O / seguridad (CompactLogix + safety) | D93: 3 | E93: USD | F93: 106667 | G93: {=IF($E93="COP",$D93*$F93,IF($E93="USD*",$D93*$F93*Parametros!$B$5,IF($E93="GBP*",$D93*$F93*INDEX(Parametros!$B:$B,MATCH("gbp_cop",Parametros!$A:$A,0)),$D93*$F93*Parametros!$B$5*Parametros!$B$6)))} -> 1008452399 | H93: 7 | I93: automatizacion
A94: Benchmark retrofit | B94: COMÚN | C94: HMIs / estaciones SCADA | D94: 6 | E94: USD | F94: 10000 | G94: {=IF($E94="COP",$D94*$F94,IF($E94="USD*",$D94*$F94*Parametros!$B$5,IF($E94="GBP*",$D94*$F94*INDEX(Parametros!$B:$B,MATCH("gbp_cop",Parametros!$A:$A,0)),$D94*$F94*Parametros!$B$5*Parametros!$B$6)))} -> 189084234 | H94: 5 | I94: automatizacion
A95: Benchmark retrofit | B95: COMÚN | C95: Camaras y vision artificial (Cognex) | D95: 0 | E95: USD | F95: 95000 | G95: {=IF($E95="COP",$D95*$F95,IF($E95="USD*",$D95*$F95*Parametros!$B$5,IF($E95="GBP*",$D95*$F95*INDEX(Parametros!$B:$B,MATCH("gbp_cop",Parametros!$A:$A,0)),$D95*$F95*Parametros!$B$5*Parametros!$B$6)))} -> 0 | H95: 5 | I95: automatizacion
A96: Benchmark retrofit | B96: COMÚN | C96: Sensores / transmisores / valvulas (pack) | D96: 1 | E96: USD | F96: 55000 | G96: {=IF($E96="COP",$D96*$F96,IF($E96="USD*",$D96*$F96*Parametros!$B$5,IF($E96="GBP*",$D96*$F96*INDEX(Parametros!$B:$B,MATCH("gbp_cop",Parametros!$A:$A,0)),$D96*$F96*Parametros!$B$5*Parametros!$B$6)))} -> 1.7332721e+08 | H96: 5 | I96: automatizacion
A97: Benchmark retrofit | B97: COMÚN | C97: Red industrial y ciberseguridad (switches/FW/UPS) | D97: 1 | E97: USD | F97: 75000 | G97: {=IF($E97="COP",$D97*$F97,IF($E97="USD*",$D97*$F97*Parametros!$B$5,IF($E97="GBP*",$D97*$F97*INDEX(Parametros!$B:$B,MATCH("gbp_cop",Parametros!$A:$A,0)),$D97*$F97*Parametros!$B$5*Parametros!$B$6)))} -> 2.3635529e+08 | H97: 5 | I97: automatizacion
A98: Benchmark retrofit | B98: COMÚN | C98: Servidor edge / historian / gateway MES-UNS (MQTT) | D98: 1 | E98: USD | F98: 90000 | G98: {=IF($E98="COP",$D98*$F98,IF($E98="USD*",$D98*$F98*Parametros!$B$5,IF($E98="GBP*",$D98*$F98*INDEX(Parametros!$B:$B,MATCH("gbp_cop",Parametros!$A:$A,0)),$D98*$F98*Parametros!$B$5*Parametros!$B$6)))} -> 283626351 | H98: 5 | I98: automatizacion
A99: Servicios | B99: COMÚN | C99: Ingenieria de detalle, FAT/SAT y PMO (ver hoja APU_Ingenieria) | D99: 1 | E99: COP | F99: {=INDEX(APU_Ingenieria!$H:$H,MATCH("Ingenieria de detalle, FAT/SAT y PMO",APU_Ingenieria!$A:$A,0))} -> 546493840 | G99: {=IF($E99="COP",$D99*$F99,IF($E99="USD*",$D99*$F99*Parametros!$B$5,IF($E99="GBP*",$D99*$F99*INDEX(Parametros!$B:$B,MATCH("gbp_cop",Parametros!$A:$A,0)),$D99*$F99*Parametros!$B$5*Parametros!$B$6)))} -> 546493840 | H99: 5 | I99: servicios
A100: Servicios | B100: COMÚN | C100: Instalacion y puesta en marcha (EPC) (ver hoja APU_Ingenieria) | D100: 1 | E100: COP | F100: {=INDEX(APU_Ingenieria!$H:$H,MATCH("Instalacion y puesta en marcha (EPC)",APU_Ingenieria!$A:$A,0))} -> 964336128 | G100: {=IF($E100="COP",$D100*$F100,IF($E100="USD*",$D100*$F100*Parametros!$B$5,IF($E100="GBP*",$D100*$F100*INDEX(Parametros!$B:$B,MATCH("gbp_cop",Parametros!$A:$A,0)),$D100*$F100*Parametros!$B$5*Parametros!$B$6)))} -> 964336128 | H100: 5 | I100: servicios
A101: Servicios | B101: COMÚN | C101: Capacitacion y gestion del cambio (ver hoja APU_Ingenieria) | D101: 1 | E101: COP | F101: {=INDEX(APU_Ingenieria!$H:$H,MATCH("Capacitacion y gestion del cambio",APU_Ingenieria!$A:$A,0))} -> 179252096 | G101: {=IF($E101="COP",$D101*$F101,IF($E101="USD*",$D101*$F101*Parametros!$B$5,IF($E101="GBP*",$D101*$F101*INDEX(Parametros!$B:$B,MATCH("gbp_cop",Parametros!$A:$A,0)),$D101*$F101*Parametros!$B$5*Parametros!$B$6)))} -> 179252096 | H101: 3 | I101: intangibles
A102: Software | B102: COMÚN | C102: Software capitalizable (detalle vivo en hoja Licencias) | D102: 1 | E102: COP | F102: {=INDEX(Licencias!$G:$G,MATCH("CAPEX software capitalizable",Licencias!$A:$A,0))} -> 112086015 | G102: {=IF($E102="COP",$D102*$F102,IF($E102="USD*",$D102*$F102*Parametros!$B$5,IF($E102="GBP*",$D102*$F102*INDEX(Parametros!$B:$B,MATCH("gbp_cop",Parametros!$A:$A,0)),$D102*$F102*Parametros!$B$5*Parametros!$B$6)))} -> 112086015 | H102: 3 | I102: software
C103: Subtotal — TRANSVERSAL — L1 + L2 + L3 | G103: =SUM(G93:G102) -> 3693013570
C105: ⚠ GRP001: se conservan separados el gripper GANTRY L1-L2 (4 mordazas) y el del robot L3 (3 ventosas).
C107: Subtotal CAPEX | G107: =G12+G19+G58+G90+G103 -> 8332322041
C108: Contingencia | G108: =G107*Parametros!$B$27 -> 8.332322e+08
C109: CAPEX TOTAL (con contingencia) | G109: =G107+G108 -> 9165554245

Sheet Proveedores_CAPEX
A1: PROVEEDORES Y FUENTES DEL CAPEX — registro de procura
A2: Los valores 'cotizacion usuario' incluyen la logistica indicada. Los benchmarks usados requieren inspeccion, RFQ y validacion de formato/voltaje antes de adjudicar.
A4: linea | B4: equipo / alcance | C4: proveedor | D4: tipo_fuente | E4: valor | F4: moneda | G4: logistica | H4: capacidad / criterio | I4: url / referencia | J4: estado
A5: L3 | B5: Robot ABB celda garrafones | C5: EUROBOTS | D5: Cotizacion informada por propietario | E5: 13500 | F5: GBP | G5: Envio y logistica incluidos | H5: Llenadora existente 600 gfn/h; robot elimina cuello manual | I5: Cotizacion directa; solicitar PDF y seriales | J5: Seleccionado / validar alcance del controlador
A6: L1-L2 | B6: Controlador ABB IRC5 GANTRY compartido | C6: IGAM | D6: Cotizacion informada por propietario | E6: 6500 | F6: USD | G6: Envio y logistica incluidos | H6: Un controlador para celda compartida y alternada L1/L2 | I6: Cotizacion directa; solicitar PDF | J6: Seleccionado
A7: L2 | B7: KRONES Variopac 459 usada | C7: Machinio / vendedor Chicago | D7: Listado publico usado | E7: 79900 | F7: USD | G7: No confirmada | H7: 28-30 paquetes/min; formatos hasta 1,5 L | I7: https://www.machinio.com/cat/variopac | J7: Benchmark con precio; RFQ pendiente
A8: L2 | B8: KRONES Variopac Pro TFS-4-DS 2021 | C8: MachinePoint | D8: Listado publico usado | E8: Precio a consultar | F8: USD/EUR | G8: Servicios de transporte disponibles | H8: 45 paquetes/min; 1.200 h | I8: https://www.machinepoint.com/machinepoint/inventory.nsf/idmaquina/300047107?ln=es&opendocument= | J8: Alternativa RFQ
A9: L1 | B9: KRONES VODM usada 2012 | C9: MachinePoint | D9: Listado publico usado | E9: Precio a consultar | F9: EUR | G9: No confirmada | H9: 44.000 bph; cumple demanda con holgura | I9: https://www.machinepoint.com/machinepoint/inventory.nsf/idmaquina/300049529?ln=en&opendocument= | J9: Alternativa RFQ / inspeccion
A10: L1 | B10: KRONES glass line 4.000 L/h (1997) | C10: Truck1 / vendedor italiano | D10: Listado publico usado | E10: 138000 | F10: EUR | G10: No confirmada | H10: ≈11.429 bph a 350 ml: NO cumple capacidad L1 | I10: https://www.truck1.eu/industrial-equipment/liquid-filling-machines/used-krones-filling-line-for-flat-drinks-in-glass-a11361978.html | J10: Descartado por capacidad
A11: L1 | B11: KRONES CSD vidrio 36.000 bph usada 2012 | C11: Used German Machines | D11: Listado publico usado | E11: Precio a consultar | F11: EUR | G11: No confirmada | H11: 36.000 bph: menor holgura que alternativa 44.000 | I11: https://used-german-machines.de/machines/99922681 | J11: Alternativa condicionada
A12: L2 | B12: KRONES PET CSD usada 18.000 bph | C12: Used Bottling Lines / Exapro | D12: Listado publico usado | E12: Precio a consultar | F12: EUR/USD | G12: No confirmada | H12: 18.000 bph a 1,5 L; amplia holgura | I12: https://www.exapro.com/krones-ultra-clean-pet-p260108037/ | J12: Base tecnica; RFQ pendiente
A13: Comun | B13: Sensores, neumatica, seguridad y tableros | C13: ABB / Festo / ReeR / Satech / Interroll | D13: Fabricantes BOM | E13: Ver CAPEX | F13: USD | G13: Segun RFQ | H13: Referencias detalladas en BOM de celdas | I13: Hojas CAPEX y APU_Ingenieria | J13: RFQ por paquete
A14: Digital | B14: Ignition SCADA / MES / Coreflux UNS / Siemens / ABB RobotStudio | C14: Inductive Automation / Coreflux / Siemens / ABB | D14: Fabricante / alcance ULogix | E14: Ver Licencias y APU | F14: COP/USD | G14: Digital | H14: SCADA, MES, MQTT, simulacion y gemelos digitales | I14: Hojas Licencias y APU_Ingenieria | J14: Incluido en arquitectura

Sheet Licencias
A1: LICENCIAS Y PLATAFORMAS DIGITALES — ALCANCE ULOGIX
A2: CAPEX solo incluye licencias perpetuas. Suscripciones y hosting alimentan OPEX mensual; los elementos excluidos quedan en cero para conservar trazabilidad.
A4: software / plataforma | B4: alcance | C4: modalidad | D4: cant. | E4: moneda | F4: precio unitario | G4: CAPEX inicial COP | H4: OPEX mensual COP | I4: fuente / supuesto
A5: ABB RobotStudio Premium | B5: Ingenieria offline celdas L1-L2 y L3 | C5: Anual | D5: 2 | E5: USD | F5: 1200 | G5: =IF($C5="Perpetua",$D5*$F5*IF($E5="USD",Parametros!$B$5,1),0) -> 0 | H5: =IF($C5="Anual",$D5*$F5*IF($E5="USD",Parametros!$B$5,1)/12,IF($C5="Mensual",$D5*$F5*IF($E5="USD",Parametros!$B$5,1),0)) -> 649774 | I5: Benchmark proveedor; cantidad editable
A6: Studio 5000 Logix Designer | B6: PLC CompactLogix transversal | C6: Perpetua | D6: 2 | E6: USD | F6: 4500 | G6: =IF($C6="Perpetua",$D6*$F6*IF($E6="USD",Parametros!$B$5,1),0) -> 29239830 | H6: =IF($C6="Anual",$D6*$F6*IF($E6="USD",Parametros!$B$5,1)/12,IF($C6="Mensual",$D6*$F6*IF($E6="USD",Parametros!$B$5,1),0)) -> 0 | I6: Licencia capitalizable; cantidad editable
A7: Siemens NX X Manufacturing | B7: Gemelos digitales de celdas y lineas | C7: Mensual | D7: 2 | E7: USD | F7: 220 | G7: =IF($C7="Perpetua",$D7*$F7*IF($E7="USD",Parametros!$B$5,1),0) -> 0 | H7: =IF($C7="Anual",$D7*$F7*IF($E7="USD",Parametros!$B$5,1)/12,IF($C7="Mensual",$D7*$F7*IF($E7="USD",Parametros!$B$5,1),0)) -> 1429502.8 | I7: Suscripcion de ingenieria
A8: Siemens Plant Simulation X Std | B8: Simulacion integral de planta (Tecnomatix) | C8: Anual | D8: 1 | E8: USD | F8: 12587.4 | G8: =IF($C8="Perpetua",$D8*$F8*IF($E8="USD",Parametros!$B$5,1),0) -> 0 | H8: =IF($C8="Anual",$D8*$F8*IF($E8="USD",Parametros!$B$5,1)/12,IF($C8="Mensual",$D8*$F8*IF($E8="USD",Parametros!$B$5,1),0)) -> 3407902.2 | I8: Suscripcion de ingenieria
A9: Ignition SCADA — plataforma + aplicacion + historian + alarmas + integracion | B9: SCADA, historico y alarmas L1-L2-L3 | C9: Perpetua | D9: 1 | E9: USD | F9: 25500 | G9: =IF($C9="Perpetua",$D9*$F9*IF($E9="USD",Parametros!$B$5,1),0) -> 82846185 | H9: =IF($C9="Anual",$D9*$F9*IF($E9="USD",Parametros!$B$5,1)/12,IF($C9="Mensual",$D9*$F9*IF($E9="USD",Parametros!$B$5,1),0)) -> 0 | I9: Lista oficial: 1.200 + 13.500 + 3.500 + 3.200 + 4.100 USD
A10: Coreflux Growth — broker MQTT / UNS | B10: UNS productivo L1-L2-L3 | C10: Anual | D10: 1 | E10: COP | F10: {=2450*INDEX(Parametros!$B:$B,MATCH("eur_cop",Parametros!$A:$A,0))} -> 9347975 | G10: =IF($C10="Perpetua",$D10*$F10*IF($E10="USD",Parametros!$B$5,1),0) -> 0 | H10: =IF($C10="Anual",$D10*$F10*IF($E10="USD",Parametros!$B$5,1)/12,IF($C10="Mensual",$D10*$F10*IF($E10="USD",Parametros!$B$5,1),0)) -> 778997.92 | I10: Precio oficial desde EUR 2.450/año; cloud gestionado es add-on
A11: Odoo Custom — API externa XML-RPC | B11: ERP/MRP/inventario/facturacion | C11: Mensual | D11: 5 | E11: USD | F11: 49 | G11: =IF($C11="Perpetua",$D11*$F11*IF($E11="USD",Parametros!$B$5,1),0) -> 0 | H11: =IF($C11="Anual",$D11*$F11*IF($E11="USD",Parametros!$B$5,1)/12,IF($C11="Mensual",$D11*$F11*IF($E11="USD",Parametros!$B$5,1),0)) -> 795973.15 | I11: Plan con API; supuesto editable de 5 usuarios internos
A12: Hosting MES/ERP + base de datos, backups y observabilidad | B12: mes.ulogix.online y servicios del ERP | C12: Mensual | D12: 1 | E12: COP | F12: 1200000 | G12: =IF($C12="Perpetua",$D12*$F12*IF($E12="USD",Parametros!$B$5,1),0) -> 0 | H12: =IF($C12="Anual",$D12*$F12*IF($E12="USD",Parametros!$B$5,1)/12,IF($C12="Mensual",$D12*$F12*IF($E12="USD",Parametros!$B$5,1),0)) -> 1200000 | I12: Reserva operativa editable; Odoo Online ya incluye su hosting
A13: NI LabVIEW Full | B13: No requerido por el alcance ULogix | C13: Excluida | D13: 0 | E13: USD | F13: 1731 | G13: =IF($C13="Perpetua",$D13*$F13*IF($E13="USD",Parametros!$B$5,1),0) -> 0 | H13: =IF($C13="Anual",$D13*$F13*IF($E13="USD",Parametros!$B$5,1)/12,IF($C13="Mensual",$D13*$F13*IF($E13="USD",Parametros!$B$5,1),0)) -> 0 | I13: Conservado para trazabilidad; no suma
A14: Microsoft Azure IoT + storage | B14: Sustituido por Coreflux + hosting MES/ERP | C14: Excluida | D14: 0 | E14: COP | F14: 6000000 | G14: =IF($C14="Perpetua",$D14*$F14*IF($E14="USD",Parametros!$B$5,1),0) -> 0 | H14: =IF($C14="Anual",$D14*$F14*IF($E14="USD",Parametros!$B$5,1)/12,IF($C14="Mensual",$D14*$F14*IF($E14="USD",Parametros!$B$5,1),0)) -> 0 | I14: Conservado para trazabilidad; no suma
A15: Node-RED, Python, Streamlit y SQLite | B15: Middleware, MES/ERP y dashboard | C15: Open source | D15: 1 | E15: COP | F15: 0 | G15: =IF($C15="Perpetua",$D15*$F15*IF($E15="USD",Parametros!$B$5,1),0) -> 0 | H15: =IF($C15="Anual",$D15*$F15*IF($E15="USD",Parametros!$B$5,1)/12,IF($C15="Mensual",$D15*$F15*IF($E15="USD",Parametros!$B$5,1),0)) -> 0 | I15: Sin costo de licencia; soporte en APU/hosting
A17: CAPEX software capitalizable | B17: Solo licencias perpetuas | G17: =SUM(G5:G15) -> 112086015
A18: OPEX mensual licencias | B18: Suscripciones + hosting operativo | H18: =SUM(H5:H15) -> 8262150.1

Sheet APU_Ingenieria
A1: APU (Analisis de Precios Unitarios) — costos de ingenieria que cobra ULogix
A2: Metodologia: costo directo (mano de obra propia + subcontratistas/OEM + materiales + logistica) x (1 + AIU). AIU = Administracion + Imprevistos + Utilidad, referencia estandar de la industria de construccion/EPC en Colombia (banda de mercado 25-30%; NO es una tarifa fijada por ley — desde la desregulacion de honorarios profesionales, COPNIA no fija tarifas minimas, es de negociacion contractual). La mano de obra propia usa una formula viva contra RRHH en Sheets; los rubros de terceros/OEM son supuestos de mercado documentados, a validar con cotizacion real antes de contratar.
A4: RESUMEN
A5: item | B5: costo_directo_cop | C5: pct_administracion | D5: pct_imprevistos | E5: pct_utilidad | F5: pct_aiu_total | G5: aiu_cop | H5: precio_total_cop
A6: Ingenieria de detalle, FAT/SAT y PMO | B6: =SUMIF($A$12:$A$200,A6,$G$12:$G$200) -> 428622620 | C6: 0.15165441 | D6: 0.05055147 | E6: 0.072794117 | F6: =SUM(C6:E6) -> 0.275 | G6: =B6*F6 -> 117871220 | H6: =B6+G6 -> 546493840
A7: Instalacion y puesta en marcha (EPC) | B7: =SUMIF($A$12:$A$200,A7,$G$12:$G$200) -> 753387600 | C7: 0.15441176 | D7: 0.051470588 | E7: 0.074117647 | F7: =SUM(C7:E7) -> 0.28 | G7: =B7*F7 -> 210948528 | H7: =B7+G7 -> 964336128
A8: Capacitacion y gestion del cambio | B8: =SUMIF($A$12:$A$200,A8,$G$12:$G$200) -> 140040700 | C8: 0.15441176 | D8: 0.051470588 | E8: 0.074117647 | F8: =SUM(C8:E8) -> 0.28 | G8: =B8*F8 -> 39211396 | H8: =B8+G8 -> 179252096
A10: DETALLE
A11: item | B11: componente | C11: descripcion | D11: cantidad | E11: unidad | F11: valor_unitario_cop | G11: subtotal_cop | H11: tipo_costo
A12: Ingenieria de detalle, FAT/SAT y PMO | B12: Ingenieria de proceso y dimensionamiento de capacidad | C12: Balance antes/despues, OEE, demanda, holgura y especificacion de llenadoras usadas | D12: 320 | E12: horas | F12: {=INDEX(RRHH!$G:$G,MATCH("Equipo diseno y desarrollo ULogix",RRHH!$A:$A,0))/160} -> 77823 | G12: =D12*F12 -> 24903360 | H12: Mano de obra propia
A13: Ingenieria de detalle, FAT/SAT y PMO | B13: Diseño mecanico encajonadora 30x30 y GANTRY compartido | C13: Layout, grippers, transportadores, alternancia L1/L2, planos y BOM | D13: 480 | E13: horas | F13: {=INDEX(RRHH!$G:$G,MATCH("Equipo diseno y desarrollo ULogix",RRHH!$A:$A,0))/160} -> 77823 | G13: =D13*F13 -> 37355040 | H13: Mano de obra propia
A14: Ingenieria de detalle, FAT/SAT y PMO | B14: Ingenieria electrica, seguridad y control ABB | C14: IRC5, servos, I/O, redes, interlocks, matrices causa-efecto y filosofia de control | D14: 420 | E14: horas | F14: {=INDEX(RRHH!$G:$G,MATCH("Equipo diseno y desarrollo ULogix",RRHH!$A:$A,0))/160} -> 77823 | G14: =D14*F14 -> 32685660 | H14: Mano de obra propia
A15: Ingenieria de detalle, FAT/SAT y PMO | B15: ABB RobotStudio: trayectorias y virtual commissioning | C15: RAPID, colisiones, ciclos, grippers y validacion virtual de celdas | D15: 320 | E15: horas | F15: {=INDEX(RRHH!$G:$G,MATCH("Equipo diseno y desarrollo ULogix",RRHH!$A:$A,0))/160} -> 77823 | G15: =D15*F15 -> 24903360 | H15: Mano de obra propia
A16: Ingenieria de detalle, FAT/SAT y PMO | B16: Siemens NX: gemelos digitales mecatronicos | C16: Celdas, embotellado, encajonado y paletizado; interfaces CAD con RobotStudio | D16: 360 | E16: horas | F16: {=INDEX(RRHH!$G:$G,MATCH("Equipo diseno y desarrollo ULogix",RRHH!$A:$A,0))/160} -> 77823 | G16: =D16*F16 -> 28016280 | H16: Mano de obra propia
A17: Ingenieria de detalle, FAT/SAT y PMO | B17: Tecnomatix Plant Simulation: modelo integral de planta | C17: L1-L3, turnos, buffers, fallas, OEE, escenarios y capacidad | D17: 400 | E17: horas | F17: {=INDEX(RRHH!$G:$G,MATCH("Equipo diseno y desarrollo ULogix",RRHH!$A:$A,0))/160} -> 77823 | G17: =D17*F17 -> 31129200 | H17: Mano de obra propia
A18: Ingenieria de detalle, FAT/SAT y PMO | B18: Ignition SCADA e historian | C18: Sinopticos, tags, alarmas, tendencias, presion y equipos de las tres lineas | D18: 360 | E18: horas | F18: {=INDEX(RRHH!$G:$G,MATCH("Equipo diseno y desarrollo ULogix",RRHH!$A:$A,0))/160} -> 77823 | G18: =D18*F18 -> 28016280 | H18: Mano de obra propia
A19: Ingenieria de detalle, FAT/SAT y PMO | B19: MES, Coreflux MQTT y UNS | C19: 79 topicos, OEE/KPI/eventos/alarmas, trazabilidad y AvailableQuantity | D19: 480 | E19: horas | F19: {=INDEX(RRHH!$G:$G,MATCH("Equipo diseno y desarrollo ULogix",RRHH!$A:$A,0))/160} -> 77823 | G19: =D19*F19 -> 37355040 | H19: Mano de obra propia
A20: Ingenieria de detalle, FAT/SAT y PMO | B20: ERP/Odoo y analitica de demanda | C20: Pronostico, MRP, inventarios, compras, MO, ventas, facturacion e integracion MES | D20: 320 | E20: horas | F20: {=INDEX(RRHH!$G:$G,MATCH("Equipo diseno y desarrollo ULogix",RRHH!$A:$A,0))/160} -> 77823 | G20: =D20*F20 -> 24903360 | H20: Mano de obra propia
A21: Ingenieria de detalle, FAT/SAT y PMO | B21: Ciberseguridad OT, edge y arquitectura de datos | C21: Segmentacion, backups, hardening, usuarios, certificados y recuperacion | D21: 160 | E21: horas | F21: {=INDEX(RRHH!$G:$G,MATCH("Equipo diseno y desarrollo ULogix",RRHH!$A:$A,0))/160} -> 77823 | G21: =D21*F21 -> 12451680 | H21: Mano de obra propia
A22: Ingenieria de detalle, FAT/SAT y PMO | B22: PMO, documentacion, QA y protocolos FAT/SAT | C22: Plan maestro, riesgos, control de cambios, manuales y trazabilidad de pruebas | D22: 320 | E22: horas | F22: {=INDEX(RRHH!$G:$G,MATCH("Equipo diseno y desarrollo ULogix",RRHH!$A:$A,0))/160} -> 77823 | G22: =D22*F22 -> 24903360 | H22: Mano de obra propia
A23: Ingenieria de detalle, FAT/SAT y PMO | B23: Inspeccion tecnica y due diligence de maquinaria usada | C23: Llenadoras KRONES L1/L2: condicion, formatos, repuestos y prueba en vacio | D23: 2 | E23: equipos | F23: 45000000 | G23: =D23*F23 -> 90000000 | H23: Subcontratado / terceros
A24: Ingenieria de detalle, FAT/SAT y PMO | B24: FAT remoto/presencial y viaticos | C24: Pruebas de fillers/Variopac y celdas; cotizar antes de adjudicar | D24: 1 | E24: global | F24: 32000000 | G24: =D24*F24 -> 32000000 | H24: Logistica / viajes
C25: Costo Directo — Ingenieria de detalle, FAT/SAT y PMO | G25: =B6 -> 428622620 | H25: Subtotal
C26: AIU 27.5% (Admin 15.2% + Imprev 5.1% + Util 7.3%) | G26: =G6 -> 117871220 | H26: AIU
C27: PRECIO TOTAL — Ingenieria de detalle, FAT/SAT y PMO (= CAPEX hoja Servicios) | G27: =H6 -> 546493840 | H27: Total
A29: Instalacion y puesta en marcha (EPC) | B29: Supervision ULogix de desmontaje, montaje y comisionamiento | C29: Coordinacion mecanica, electrica, automatizacion, software y arranque | D29: 1200 | E29: horas | F29: {=INDEX(RRHH!$G:$G,MATCH("Equipo diseno y desarrollo ULogix",RRHH!$A:$A,0))/160} -> 77823 | G29: =D29*F29 -> 93387600 | H29: Mano de obra propia
A30: Instalacion y puesta en marcha (EPC) | B30: Especialistas OEM maquinaria KRONES usada L1/L2 | C30: Ajuste de formatos, overhaul selectivo, puesta a punto y SAT | D30: 1 | E30: global | F30: 180000000 | G30: =D30*F30 -> 180000000 | H30: Subcontratado / terceros
A31: Instalacion y puesta en marcha (EPC) | B31: Cuadrillas mecanicas/electricas y rigging | C31: Montaje de fillers, Variopac, encajonadora, conveyors y celdas | D31: 1 | E31: global | F31: 220000000 | G31: =D31*F31 -> 220000000 | H31: Subcontratado / terceros
A32: Instalacion y puesta en marcha (EPC) | B32: Comisionamiento celdas ABB y GANTRY | C32: GANTRY compartido L1/L2 y robot garrafones L3 | D32: 1 | E32: global | F32: 45000000 | G32: =D32*F32 -> 45000000 | H32: Subcontratado / terceros
A33: Instalacion y puesta en marcha (EPC) | B33: Gruas, montacargas, alineacion y andamios | C33: Ventanas de parada coordinadas por linea | D33: 1 | E33: global | F33: 45000000 | G33: =D33*F33 -> 45000000 | H33: Equipos / alquiler
A34: Instalacion y puesta en marcha (EPC) | B34: Cableado, canaletas, soporteria y consumibles | C34: Material menor no incluido en BOM de equipos | D34: 1 | E34: global | F34: 90000000 | G34: =D34*F34 -> 90000000 | H34: Materiales
A35: Instalacion y puesta en marcha (EPC) | B35: Seguridad industrial HSE | C35: Permisos, LOTO, EPP, pruebas de seguridad y dossier | D35: 1 | E35: global | F35: 25000000 | G35: =D35*F35 -> 25000000 | H35: Materiales
A36: Instalacion y puesta en marcha (EPC) | B36: Transporte local, izaje y nacionalizacion complementaria | C36: No duplica envios incluidos en cotizaciones EUROBOTS/IGAM | D36: 1 | E36: global | F36: 55000000 | G36: =D36*F36 -> 55000000 | H36: Logistica / viajes
C37: Costo Directo — Instalacion y puesta en marcha (EPC) | G37: =B7 -> 753387600 | H37: Subtotal
C38: AIU 28.0% (Admin 15.4% + Imprev 5.1% + Util 7.4%) | G38: =G7 -> 210948528 | H38: AIU
C39: PRECIO TOTAL — Instalacion y puesta en marcha (EPC) (= CAPEX hoja Servicios) | G39: =H7 -> 964336128 | H39: Total
A41: Capacitacion y gestion del cambio | B41: Diseño y facilitacion de capacitacion ULogix | C41: Operaciones, mantenimiento, SCADA, MES, ERP, UNS, NX, Tecnomatix y RobotStudio | D41: 900 | E41: horas | F41: {=INDEX(RRHH!$G:$G,MATCH("Equipo diseno y desarrollo ULogix",RRHH!$A:$A,0))/160} -> 77823 | G41: =D41*F41 -> 70040700 | H41: Mano de obra propia
A42: Capacitacion y gestion del cambio | B42: Manuales, videos, SOP y escenarios de simulacion | C42: Entregables editables y ejercicios por rol | D42: 1 | E42: global | F42: 25000000 | G42: =D42*F42 -> 25000000 | H42: Materiales
A43: Capacitacion y gestion del cambio | B43: Especialistas externos/OEM | C43: Formacion especifica KRONES y ABB | D43: 1 | E43: global | F43: 20000000 | G43: =D43*F43 -> 20000000 | H43: Subcontratado / terceros
A44: Capacitacion y gestion del cambio | B44: Logistica de entrenamiento por turnos | C44: Cobertura L1/L2 tres turnos y L3 un turno | D44: 1 | E44: global | F44: 25000000 | G44: =D44*F44 -> 25000000 | H44: Logistica / viajes
C45: Costo Directo — Capacitacion y gestion del cambio | G45: =B8 -> 140040700 | H45: Subtotal
C46: AIU 28.0% (Admin 15.4% + Imprev 5.1% + Util 7.4%) | G46: =G8 -> 39211396 | H46: AIU
C47: PRECIO TOTAL — Capacitacion y gestion del cambio (= CAPEX hoja Servicios) | G47: =H8 -> 179252096 | H47: Total

Sheet Costos_Lote
A1: Costos variables por lote — FINANZAS/PRODUCCION
A2: Base financiera (editable): componentes por lote de referencia → costo unitario. El ER usa estos costos unitarios; margen = precio (Parametros) − costo.
A4: P1 · Coca-Cola 330/350 mL retornable
A5: componente | B5: costo por lote COP | C5: % del total
A6: Jarabe base / concentrado | B6: 105000000 | C6: =B6/B16 -> 0.37674919
A7: Agua tratada | B7: 7000000 | C7: =B7/B16 -> 0.025116613
A8: CO2 | B8: 6900000 | C8: =B8/B16 -> 0.024757804
A9: Lavado y sanitizacion envase | B9: 12000000 | C9: =B9/B16 -> 0.043057051
A10: Tapas | B10: 27000000 | C10: =B10/B16 -> 0.096878364
A11: Etiquetas | B11: 18000000 | C11: =B11/B16 -> 0.064585576
A12: Energia y utilidades variables | B12: 15000000 | C12: =B12/B16 -> 0.053821313
A13: Control de calidad | B13: 1800000 | C13: =B13/B16 -> 0.0064585576
A14: Rotura / merma envase retornable | B14: 80000000 | C14: =B14/B16 -> 0.287047
A15: Materiales auxiliares | B15: 6000000 | C15: =B15/B16 -> 0.021528525
A16: Total lote | B16: =SUM(B6:B15) -> 278700000
A17: Lote de referencia (u) | B17: 300000
A18: COSTO UNITARIO (→ ER) | B18: =B16/B17 -> 929
A20: P2 · Coca-Cola PET 1.5 L
A21: componente | B21: costo por lote COP | C21: % del total
A22: Preforma / botella PET | B22: 115000000 | C22: =B22/B31 -> 0.43071161
A23: Jarabe base / concentrado | B23: 82000000 | C23: =B23/B31 -> 0.3071161
A24: Agua tratada | B24: 10500000 | C24: =B24/B31 -> 0.039325843
A25: CO2 | B25: 3800000 | C25: =B25/B31 -> 0.01423221
A26: Tapas | B26: 12000000 | C26: =B26/B31 -> 0.04494382
A27: Etiquetas | B27: 9000000 | C27: =B27/B31 -> 0.033707865
A28: Energia y utilidades | B28: 8500000 | C28: =B28/B31 -> 0.031835206
A29: Control de calidad | B29: 1200000 | C29: =B29/B31 -> 0.004494382
A30: Materiales auxiliares | B30: 25000000 | C30: =B30/B31 -> 0.093632959
A31: Total lote | B31: =SUM(B22:B30) -> 267000000
A32: Lote de referencia (u) | B32: 100000
A33: COSTO UNITARIO (→ ER) | B33: =B31/B32 -> 2670
A35: P3 · Garrafon agua 25 L
A36: componente | B36: costo por lote COP | C36: % del total
A37: Tratamiento de agua | B37: 5600000 | C37: =B37/B44 -> 0.23045267
A38: Lavado / sanitizacion garrafon | B38: 4900000 | C38: =B38/B44 -> 0.20164609
A39: Tapas y sellos | B39: 2100000 | C39: =B39/B44 -> 0.086419753
A40: Energia y utilidades | B40: 3150000 | C40: =B40/B44 -> 0.12962963
A41: Reposicion parque garrafones | B41: 7000000 | C41: =B41/B44 -> 0.28806584
A42: Control de calidad | B42: 700000 | C42: =B42/B44 -> 0.028806584
A43: Materiales auxiliares | B43: 850000 | C43: =B43/B44 -> 0.034979424
A44: Total lote | B44: =SUM(B37:B43) -> 24300000
A45: Lote de referencia (u) | B45: 3500
A46: COSTO UNITARIO (→ ER) | B46: =B44/B45 -> 6942.8571

Sheet Flujo_Caja
A1: Flujo de caja del proyecto (incremental) — 60 meses
A2: FCF = EBITDA incremental − impuesto − CAPEX en fases − equipo de implementacion ± capital de trabajo. Indicadores abajo (VPN, TIR, ROI, paybacks).
A3: TMAR mensual | B3: =(1+Parametros!$B$7)^(1/12)-1 -> 0.01388843
A5: Mes | B5: 1 | C5: 2 | D5: 3 | E5: 4 | F5: 5 | G5: 6 | H5: 7 | I5: 8 | J5: 9 | K5: 10 | L5: 11 | M5: 12 | N5: 13 | O5: 14 | P5: 15 | Q5: 16 | R5: 17 | S5: 18 | T5: 19 | U5: 20 | V5: 21 | W5: 22 | X5: 23 | Y5: 24 | Z5: 25 | AA5: 26 | AB5: 27 | AC5: 28 | AD5: 29 | AE5: 30 | AF5: 31 | AG5: 32 | AH5: 33 | AI5: 34 | AJ5: 35 | AK5: 36 | AL5: 37 | AM5: 38 | AN5: 39 | AO5: 40 | AP5: 41 | AQ5: 42 | AR5: 43 | AS5: 44 | AT5: 45 | AU5: 46 | AV5: 47 | AW5: 48 | AX5: 49 | AY5: 50 | AZ5: 51 | BA5: 52 | BB5: 53 | BC5: 54 | BD5: 55 | BE5: 56 | BF5: 57 | BG5: 58 | BH5: 59 | BI5: 60
A6: EBITDA incremental | B6: =ER_Proyecto!B25 -> 0 | C6: =ER_Proyecto!C25 -> 0 | D6: =ER_Proyecto!D25 -> 0 | E6: =ER_Proyecto!E25 -> 0 | F6: =ER_Proyecto!F25 -> 5.2145757e+08 | G6: =ER_Proyecto!G25 -> 776016769 | H6: =ER_Proyecto!H25 -> 7.9257968e+08 | I6: =ER_Proyecto!I25 -> 8.2950631e+08 | ... BI6: =ER_Proyecto!BI25 -> 8.2377453e+08
A7: (−) Impuesto | B7: =-ER_Proyecto!B28 -> 0 | C7: =-ER_Proyecto!C28 -> 0 | D7: =-ER_Proyecto!D28 -> 0 | E7: =-ER_Proyecto!E28 -> 0 | F7: =-ER_Proyecto!F28 -> -1.4921832e+08 | G7: =-ER_Proyecto!G28 -> -2.3831405e+08 | H7: =-ER_Proyecto!H28 -> -2.4411106e+08 | I7: =-ER_Proyecto!I28 -> -2.5703539e+08 | ... BI7: =-ER_Proyecto!BI28 -> -2.5502926e+08
A8: (−) CAPEX (fases) | B8: {=-INDEX(CAPEX!$G:$G,MATCH("CAPEX TOTAL (con contingencia)",CAPEX!$C:$C,0))*Parametros!$B$28} -> -1833110849 | C8: {=-INDEX(CAPEX!$G:$G,MATCH("CAPEX TOTAL (con contingencia)",CAPEX!$C:$C,0))*Parametros!$B$29} -> -3207943986 | D8: {=-INDEX(CAPEX!$G:$G,MATCH("CAPEX TOTAL (con contingencia)",CAPEX!$C:$C,0))*Parametros!$B$30} -> -2474699646 | E8: {=-INDEX(CAPEX!$G:$G,MATCH("CAPEX TOTAL (con contingencia)",CAPEX!$C:$C,0))*Parametros!$B$31} -> -1649799764 | F8: =0 -> 0 | G8: =0 -> 0 | H8: =0 -> 0 | I8: =0 -> 0 | J8: =0 -> 0 | K8: =0 -> 0 | L8: =0 -> 0 | M8: =0 -> 0 | ... BI8: =0 -> 0
A9: (−) Equipo implementacion ULogix | B9: {=-INDEX(RRHH!$E:$E,MATCH("Costo mensual IMPLEMENTACION (→ pre-op)",RRHH!$A:$A,0))} -> -87161760 | C9: {=-INDEX(RRHH!$E:$E,MATCH("Costo mensual IMPLEMENTACION (→ pre-op)",RRHH!$A:$A,0))} -> -87161760 | D9: {=-INDEX(RRHH!$E:$E,MATCH("Costo mensual IMPLEMENTACION (→ pre-op)",RRHH!$A:$A,0))} -> -87161760 | E9: {=-INDEX(RRHH!$E:$E,MATCH("Costo mensual IMPLEMENTACION (→ pre-op)",RRHH!$A:$A,0))} -> -87161760 | F9: =0 -> 0 | G9: =0 -> 0 | H9: =0 -> 0 | I9: =0 -> 0 | J9: =0 -> 0 | K9: =0 -> 0 | L9: =0 -> 0 | M9: =0 -> 0 | ... BI9: =0 -> 0
A10: Δ Capital de trabajo | B10: =0 -> 0 | C10: =0 -> 0 | D10: =0 -> 0 | E10: =0 -> 0 | F10: =-Parametros!$B$16*(ER_Proyecto!$G$17-ER_Proyecto!$G$9) -> -1.2499736e+08 | G10: =0 -> 0 | H10: =0 -> 0 | I10: =0 -> 0 | J10: =0 -> 0 | K10: =0 -> 0 | L10: =0 -> 0 | M10: =0 -> 0 | N10: =0 -> 0 | ... BH10: =0 -> 0 | BI10: =Parametros!$B$16*(ER_Proyecto!$G$17-ER_Proyecto!$G$9) -> 1.2499736e+08
A11: FCF del proyecto | B11: =B6+B7+B8+B9+B10 -> -1920272609 | C11: =C6+C7+C8+C9+C10 -> -3295105746 | D11: =D6+D7+D8+D9+D10 -> -2561861406 | E11: =E6+E7+E8+E9+E10 -> -1736961524 | F11: =F6+F7+F8+F9+F10 -> 2.4724188e+08 | G11: =G6+G7+G8+G9+G10 -> 537702723 | H11: =H6+H7+H8+H9+H10 -> 5.4846861e+08 | I11: =I6+I7+I8+I9+I10 -> 5.7247093e+08 | ... BI11: =BI6+BI7+BI8+BI9+BI10 -> 6.9374263e+08
A12: Factor de descuento | B12: =1/(1+$B$3)^1 -> 0.98630182 | C12: =1/(1+$B$3)^2 -> 0.97279127 | D12: =1/(1+$B$3)^3 -> 0.9594658 | E12: =1/(1+$B$3)^4 -> 0.94632286 | F12: =1/(1+$B$3)^5 -> 0.93335995 | G12: =1/(1+$B$3)^6 -> 0.92057462 | H12: =1/(1+$B$3)^7 -> 0.90796442 | I12: =1/(1+$B$3)^8 -> 0.89552695 | J12: =1/(1+$B$3)^9 -> 0.88325986 | K12: =1/(1+$B$3)^10 -> 0.8711608 | L12: =1/(1+$B$3)^11 -> 0.85922748 | M12: =1/(1+$B$3)^12 -> 0.84745763 | N12: =1/(1+$B$3)^13 -> 0.835849 | O12: =1/(1+$B$3)^14 -> 0.82439938 | P12: =1/(1+$B$3)^15 -> 0.81310661 | Q12: =1/(1+$B$3)^16 -> 0.80196852 | R12: =1/(1+$B$3)^17 -> 0.79098301 | S12: =1/(1+$B$3)^18 -> 0.78014798 | T12: =1/(1+$B$3)^19 -> 0.76946137 | U12: =1/(1+$B$3)^20 -> 0.75892115 | V12: =1/(1+$B$3)^21 -> 0.74852531 | W12: =1/(1+$B$3)^22 -> 0.73827187 | X12: =1/(1+$B$3)^23 -> 0.72815888 | Y12: =1/(1+$B$3)^24 -> 0.71818443 | Z12: =1/(1+$B$3)^25 -> 0.70834661 | AA12: =1/(1+$B$3)^26 -> 0.69864355 | AB12: =1/(1+$B$3)^27 -> 0.6890734 | AC12: =1/(1+$B$3)^28 -> 0.67963434 | AD12: =1/(1+$B$3)^29 -> 0.67032459 | AE12: =1/(1+$B$3)^30 -> 0.66114236 | AF12: =1/(1+$B$3)^31 -> 0.65208591 | AG12: =1/(1+$B$3)^32 -> 0.64315351 | AH12: =1/(1+$B$3)^33 -> 0.63434348 | AI12: =1/(1+$B$3)^34 -> 0.62565413 | AJ12: =1/(1+$B$3)^35 -> 0.6170838 | AK12: =1/(1+$B$3)^36 -> 0.60863087 | AL12: =1/(1+$B$3)^37 -> 0.60029374 | AM12: =1/(1+$B$3)^38 -> 0.5920708 | AN12: =1/(1+$B$3)^39 -> 0.58396051 | AO12: =1/(1+$B$3)^40 -> 0.57596131 | AP12: =1/(1+$B$3)^41 -> 0.56807168 | AQ12: =1/(1+$B$3)^42 -> 0.56029013 | AR12: =1/(1+$B$3)^43 -> 0.55261518 | AS12: =1/(1+$B$3)^44 -> 0.54504535 | AT12: =1/(1+$B$3)^45 -> 0.53757922 | AU12: =1/(1+$B$3)^46 -> 0.53021536 | AV12: =1/(1+$B$3)^47 -> 0.52295237 | AW12: =1/(1+$B$3)^48 -> 0.51578888 | AX12: =1/(1+$B$3)^49 -> 0.5087235 | AY12: =1/(1+$B$3)^50 -> 0.50175492 | AZ12: =1/(1+$B$3)^51 -> 0.49488178 | BA12: =1/(1+$B$3)^52 -> 0.4881028 | BB12: =1/(1+$B$3)^53 -> 0.48141668 | BC12: =1/(1+$B$3)^54 -> 0.47482215 | BD12: =1/(1+$B$3)^55 -> 0.46831795 | BE12: =1/(1+$B$3)^56 -> 0.46190284 | BF12: =1/(1+$B$3)^57 -> 0.45557561 | BG12: =1/(1+$B$3)^58 -> 0.44933505 | BH12: =1/(1+$B$3)^59 -> 0.44317998 | BI12: =1/(1+$B$3)^60 -> 0.43710922
A13: FCF descontado | B13: =B11*B12 -> -1893968361 | C13: =C11*C12 -> -3205450110 | D13: =D11*D12 -> -2458018399 | E13: =E11*E12 -> -1643726396 | F13: =F11*F12 -> 2.3076567e+08 | G13: =G11*G12 -> 4.9499548e+08 | H13: =H11*H12 -> 4.9798999e+08 | I13: =I11*I12 -> 5.1266314e+08 | ... BI13: =BI11*BI12 -> 3.032413e+08
A14: FCF acumulado | B14: =B11 -> -1920272609 | C14: =B14+C11 -> -5215378355 | D14: =C14+D11 -> -7777239761 | E14: =D14+E11 -> -9514201285 | F14: =E14+F11 -> -9266959408 | G14: =F14+G11 -> -8729256685 | H14: =G14+H11 -> -8180788071 | I14: =H14+I11 -> -7608317145 | J14: =I14+J11 -> -6956360105 | ... BI14: =BH14+BI11 -> 21567659470
A15: Acumulado descontado | B15: =B13 -> -1893968361 | C15: =B15+C13 -> -5099418472 | D15: =C15+D13 -> -7557436871 | E15: =D15+E13 -> -9201163266 | F15: =E15+F13 -> -8970397599 | G15: =F15+G13 -> -8475402120 | H15: =G15+H13 -> -7977412135 | I15: =H15+I13 -> -7464748990 | J15: =I15+J13 -> -6888901506 | ... BI15: =BH15+BI13 -> 11032069063
A18: INDICADORES DEL PROYECTO (demanda Base)
A19: VPN @ TMAR (COP) | B19: =SUM(B13:BI13) -> 11032069063
A20: TIR mensual | B20: =IRR(B11:BI11,0.02) -> 0.049302564
A21: TIR anual (E.A.) | B21: =(1+B20)^12-1 -> 0.78159428
A22: Inversion pre-operativa (COP) | B22: =-SUM(B11:E11) -> 9514201285
A23: Ganancia neta 60m (COP) | B23: =SUM(B11:BI11) -> 21567659470
A24: ROI 60 meses | B24: =B23/B22 -> 2.2668912
A25: ROI anualizado | B25: =(1+B24)^(12/60)-1 -> 0.26714681
A26: Payback simple (mes) | B26: =MATCH(TRUE(),INDEX(B14:BI14>0,0),0) -> 22
A27: Payback descontado (mes) | B27: =MATCH(TRUE(),INDEX(B15:BI15>0,0),0) -> 25
A28: EBITDA incremental 12m operativos | B28: =SUM(F6:Q6) -> 9406419488
A29: Capital de trabajo (m5→m60) | B29: =Parametros!$B$16*(ER_Proyecto!$G$17-ER_Proyecto!$G$9) -> 1.2499736e+08

Sheet Balance
A1: Balance general simplificado del PROYECTO — mensual
A2: Perspectiva incremental: CxC/Inv/CxP con DSO/DIO/DPO sobre los flujos incrementales; activo fijo = CAPEX pagado − D&A acumulada; patrimonio = aportes + resultados (plug). Chequeo = 0.
A4: Mes | B4: 1 | C4: 2 | D4: 3 | E4: 4 | F4: 5 | G4: 6 | H4: 7 | I4: 8 | J4: 9 | K4: 10 | L4: 11 | M4: 12 | N4: 13 | O4: 14 | P4: 15 | Q4: 16 | R4: 17 | S4: 18 | T4: 19 | U4: 20 | V4: 21 | W4: 22 | X4: 23 | Y4: 24 | Z4: 25 | AA4: 26 | AB4: 27 | AC4: 28 | AD4: 29 | AE4: 30 | AF4: 31 | AG4: 32 | AH4: 33 | AI4: 34 | AJ4: 35 | AK4: 36 | AL4: 37 | AM4: 38 | AN4: 39 | AO4: 40 | AP4: 41 | AQ4: 42 | AR4: 43 | AS4: 44 | AT4: 45 | AU4: 46 | AV4: 47 | AW4: 48 | AX4: 49 | AY4: 50 | AZ4: 51 | BA4: 52 | BB4: 53 | BC4: 54 | BD4: 55 | BE4: 56 | BF4: 57 | BG4: 58 | BH4: 59 | BI4: 60
A5: ACTIVOS
A6: Caja (acumulada, piso 0) | B6: =MAX(0,Flujo_Caja!B14) -> 0 | C6: =MAX(0,Flujo_Caja!C14) -> 0 | D6: =MAX(0,Flujo_Caja!D14) -> 0 | E6: =MAX(0,Flujo_Caja!E14) -> 0 | F6: =MAX(0,Flujo_Caja!F14) -> 0 | G6: =MAX(0,Flujo_Caja!G14) -> 0 | H6: =MAX(0,Flujo_Caja!H14) -> 0 | I6: =MAX(0,Flujo_Caja!I14) -> 0 | ... BI6: =MAX(0,Flujo_Caja!BI14) -> 21567659470
A7: Cuentas por cobrar (DSO) | B7: =Parametros!$B$17/30*(ER_Proyecto!B17-ER_Proyecto!B9) -> 0 | C7: =Parametros!$B$17/30*(ER_Proyecto!C17-ER_Proyecto!C9) -> 0 | D7: =Parametros!$B$17/30*(ER_Proyecto!D17-ER_Proyecto!D9) -> 0 | E7: =Parametros!$B$17/30*(ER_Proyecto!E17-ER_Proyecto!E9) -> 0 | F7: =Parametros!$B$17/30*(ER_Proyecto!F17-ER_Proyecto!F9) -> 8.928858e+08 | G7: =Parametros!$B$17/30*(ER_Proyecto!G17-ER_Proyecto!G9) -> 1302055867 | H7: =Parametros!$B$17/30*(ER_Proyecto!H17-ER_Proyecto!H9) -> 1328294842 | I7: =Parametros!$B$17/30*(ER_Proyecto!I17-ER_Proyecto!I9) -> 1399781279 | ... BI7: =Parametros!$B$17/30*(ER_Proyecto!BI17-ER_Proyecto!BI9) -> 1388666499
A8: Inventarios (DIO) | B8: =Parametros!$B$18/30*(ER_Proyecto!B18-ER_Proyecto!B10) -> 0 | C8: =Parametros!$B$18/30*(ER_Proyecto!C18-ER_Proyecto!C10) -> 0 | D8: =Parametros!$B$18/30*(ER_Proyecto!D18-ER_Proyecto!D10) -> 0 | E8: =Parametros!$B$18/30*(ER_Proyecto!E18-ER_Proyecto!E10) -> 0 | F8: =Parametros!$B$18/30*(ER_Proyecto!F18-ER_Proyecto!F10) -> 3.4120312e+08 | G8: =Parametros!$B$18/30*(ER_Proyecto!G18-ER_Proyecto!G10) -> 4.9803912e+08 | H8: =Parametros!$B$18/30*(ER_Proyecto!H18-ER_Proyecto!H10) -> 5.0659982e+08 | I8: =Parametros!$B$18/30*(ER_Proyecto!I18-ER_Proyecto!I10) -> 5.3462546e+08 | ... BI8: =Parametros!$B$18/30*(ER_Proyecto!BI18-ER_Proyecto!BI10) -> 5.3026249e+08
A9: Activo fijo e intangible neto | B9: =-Flujo_Caja!B8-ER_Proyecto!B26 -> 1833110849 | C9: =B9-Flujo_Caja!C8-ER_Proyecto!C26 -> 5041054835 | D9: =C9-Flujo_Caja!D8-ER_Proyecto!D26 -> 7515754481 | E9: =D9-Flujo_Caja!E8-ER_Proyecto!E26 -> 9165554245 | F9: =E9-Flujo_Caja!F8-ER_Proyecto!F26 -> 9070434751 | G9: =F9-Flujo_Caja!G8-ER_Proyecto!G26 -> 8975315256 | H9: =G9-Flujo_Caja!H8-ER_Proyecto!H26 -> 8880195761 | I9: =H9-Flujo_Caja!I8-ER_Proyecto!I26 -> 8785076266 | J9: =I9-Flujo_Caja!J8-ER_Proyecto!J26 -> 8689956771 | ... BI9: =BH9-Flujo_Caja!BI8-ER_Proyecto!BI26 -> 3838862531
A10: TOTAL ACTIVOS | B10: =SUM(B6:B9) -> 1833110849 | C10: =SUM(C6:C9) -> 5041054835 | D10: =SUM(D6:D9) -> 7515754481 | E10: =SUM(E6:E9) -> 9165554245 | F10: =SUM(F6:F9) -> 10304523673 | G10: =SUM(G6:G9) -> 10775410242 | H10: =SUM(H6:H9) -> 10715090421 | I10: =SUM(I6:I9) -> 10719483004 | ... BI10: =SUM(BI6:BI9) -> 27325450994
A11: PASIVOS
A12: Cuentas por pagar (DPO) | B12: =Parametros!$B$19/30*(ER_Proyecto!B18-ER_Proyecto!B10) -> 0 | C12: =Parametros!$B$19/30*(ER_Proyecto!C18-ER_Proyecto!C10) -> 0 | D12: =Parametros!$B$19/30*(ER_Proyecto!D18-ER_Proyecto!D10) -> 0 | E12: =Parametros!$B$19/30*(ER_Proyecto!E18-ER_Proyecto!E10) -> 0 | F12: =Parametros!$B$19/30*(ER_Proyecto!F18-ER_Proyecto!F10) -> 6.0212316e+08 | G12: =Parametros!$B$19/30*(ER_Proyecto!G18-ER_Proyecto!G10) -> 8.7889256e+08 | H12: =Parametros!$B$19/30*(ER_Proyecto!H18-ER_Proyecto!H10) -> 8.9399968e+08 | I12: =Parametros!$B$19/30*(ER_Proyecto!I18-ER_Proyecto!I10) -> 9.4345669e+08 | ... BI12: =Parametros!$B$19/30*(ER_Proyecto!BI18-ER_Proyecto!BI10) -> 9.3575734e+08
A13: Impuestos por pagar (mes corriente) | B13: =ER_Proyecto!B28 -> 0 | C13: =ER_Proyecto!C28 -> 0 | D13: =ER_Proyecto!D28 -> 0 | E13: =ER_Proyecto!E28 -> 0 | F13: =ER_Proyecto!F28 -> 1.4921832e+08 | G13: =ER_Proyecto!G28 -> 2.3831405e+08 | H13: =ER_Proyecto!H28 -> 2.4411106e+08 | I13: =ER_Proyecto!I28 -> 2.5703539e+08 | ... BI13: =ER_Proyecto!BI28 -> 2.5502926e+08
A14: TOTAL PASIVOS | B14: =B12+B13 -> 0 | C14: =C12+C13 -> 0 | D14: =D12+D13 -> 0 | E14: =E12+E13 -> 0 | F14: =F12+F13 -> 7.5134148e+08 | G14: =G12+G13 -> 1117206610 | H14: =H12+H13 -> 1138110743 | I14: =I12+I13 -> 1200492078 | ... BI14: =BI12+BI13 -> 1190786604
A15: Patrimonio (aportes + resultados) | B15: =B10-B14 -> 1833110849 | C15: =C10-C14 -> 5041054835 | D15: =D10-D14 -> 7515754481 | E15: =E10-E14 -> 9165554245 | F15: =F10-F14 -> 9553182190 | G15: =G10-G14 -> 9658203632 | H15: =H10-H14 -> 9576979678 | I15: =I10-I14 -> 9518990926 | ... BI15: =BI10-BI14 -> 26134664389
A16: Chequeo balance (=0) | B16: =B10-B14-B15 -> 0 | C16: =C10-C14-C15 -> 0 | D16: =D10-D14-D15 -> 0 | E16: =E10-E14-E15 -> 0 | F16: =F10-F14-F15 -> 0 | G16: =G10-G14-G15 -> 0 | H16: =H10-H14-H15 -> 0 | I16: =I10-I14-I15 -> 0 | ... BI16: =BI10-BI14-BI15 -> 0

Sheet FinancieroEscenario
A1: Evaluacion del ESCENARIO ACTIVO del ERP
A2: Mismo motor del caso base pero sobre la hoja DemandaEscenario (la app la actualiza al Activar un escenario). Compara contra el caso base al final.
A3: TMAR mensual | B3: =(1+Parametros!$B$7)^(1/12)-1 -> 0.01388843
A5: Mes | B5: 1 | C5: 2 | D5: 3 | E5: 4 | F5: 5 | G5: 6 | H5: 7 | I5: 8 | J5: 9 | K5: 10 | L5: 11 | M5: 12 | N5: 13 | O5: 14 | P5: 15 | Q5: 16 | R5: 17 | S5: 18 | T5: 19 | U5: 20 | V5: 21 | W5: 22 | X5: 23 | Y5: 24 | Z5: 25 | AA5: 26 | AB5: 27 | AC5: 28 | AD5: 29 | AE5: 30 | AF5: 31 | AG5: 32 | AH5: 33 | AI5: 34 | AJ5: 35 | AK5: 36 | AL5: 37 | AM5: 38 | AN5: 39 | AO5: 40 | AP5: 41 | AQ5: 42 | AR5: 43 | AS5: 44 | AT5: 45 | AU5: 46 | AV5: 47 | AW5: 48 | AX5: 49 | AY5: 50 | AZ5: 51 | BA5: 52 | BB5: 53 | BC5: 54 | BD5: 55 | BE5: 56 | BF5: 57 | BG5: 58 | BH5: 59 | BI5: 60
A6: Escenario evaluado | B6: =DemandaEscenario!A5 -> Paro nacional / choque logistico
A7: u P1 / P2 / P3 (solo control) | B7: =DemandaEscenario!$D$5+DemandaEscenario!$E$5+DemandaEscenario!$F$5 -> 18622143 | C7: =DemandaEscenario!$D$6+DemandaEscenario!$E$6+DemandaEscenario!$F$6 -> 19198679 | D7: =DemandaEscenario!$D$7+DemandaEscenario!$E$7+DemandaEscenario!$F$7 -> 20142578 | E7: =DemandaEscenario!$D$8+DemandaEscenario!$E$8+DemandaEscenario!$F$8 -> 21420752 | F7: =DemandaEscenario!$D$9+DemandaEscenario!$E$9+DemandaEscenario!$F$9 -> 16259193 | G7: =DemandaEscenario!$D$10+DemandaEscenario!$E$10+DemandaEscenario!$F$10 -> 19302102 | H7: =DemandaEscenario!$D$11+DemandaEscenario!$E$11+DemandaEscenario!$F$11 -> 20712213 | I7: =DemandaEscenario!$D$12+DemandaEscenario!$E$12+DemandaEscenario!$F$12 -> 20875025 | J7: =DemandaEscenario!$D$13+DemandaEscenario!$E$13+DemandaEscenario!$F$13 -> 24266987 | K7: =DemandaEscenario!$D$14+DemandaEscenario!$E$14+DemandaEscenario!$F$14 -> 20022727 | L7: =DemandaEscenario!$D$15+DemandaEscenario!$E$15+DemandaEscenario!$F$15 -> 18528248 | M7: =DemandaEscenario!$D$16+DemandaEscenario!$E$16+DemandaEscenario!$F$16 -> 20722501 | N7: =DemandaEscenario!$D$5*(1+Parametros!$B$10)^1+DemandaEscenario!$E$5*(1+Parametros!$B$10)^1+DemandaEscenario!$F$5*(1+Parametros!$B$10)^1 -> 18622143 | O7: =DemandaEscenario!$D$6*(1+Parametros!$B$10)^1+DemandaEscenario!$E$6*(1+Parametros!$B$10)^1+DemandaEscenario!$F$6*(1+Parametros!$B$10)^1 -> 19198679 | P7: =DemandaEscenario!$D$7*(1+Parametros!$B$10)^1+DemandaEscenario!$E$7*(1+Parametros!$B$10)^1+DemandaEscenario!$F$7*(1+Parametros!$B$10)^1 -> 20142578 | Q7: =DemandaEscenario!$D$8*(1+Parametros!$B$10)^1+DemandaEscenario!$E$8*(1+Parametros!$B$10)^1+DemandaEscenario!$F$8*(1+Parametros!$B$10)^1 -> 21420752 | R7: =DemandaEscenario!$D$9*(1+Parametros!$B$10)^1+DemandaEscenario!$E$9*(1+Parametros!$B$10)^1+DemandaEscenario!$F$9*(1+Parametros!$B$10)^1 -> 16259193 | S7: =DemandaEscenario!$D$10*(1+Parametros!$B$10)^1+DemandaEscenario!$E$10*(1+Parametros!$B$10)^1+DemandaEscenario!$F$10*(1+Parametros!$B$10)^1 -> 19302102 | T7: =DemandaEscenario!$D$11*(1+Parametros!$B$10)^1+DemandaEscenario!$E$11*(1+Parametros!$B$10)^1+DemandaEscenario!$F$11*(1+Parametros!$B$10)^1 -> 20712213 | U7: =DemandaEscenario!$D$12*(1+Parametros!$B$10)^1+DemandaEscenario!$E$12*(1+Parametros!$B$10)^1+DemandaEscenario!$F$12*(1+Parametros!$B$10)^1 -> 20875025 | V7: =DemandaEscenario!$D$13*(1+Parametros!$B$10)^1+DemandaEscenario!$E$13*(1+Parametros!$B$10)^1+DemandaEscenario!$F$13*(1+Parametros!$B$10)^1 -> 24266987 | W7: =DemandaEscenario!$D$14*(1+Parametros!$B$10)^1+DemandaEscenario!$E$14*(1+Parametros!$B$10)^1+DemandaEscenario!$F$14*(1+Parametros!$B$10)^1 -> 20022727 | X7: =DemandaEscenario!$D$15*(1+Parametros!$B$10)^1+DemandaEscenario!$E$15*(1+Parametros!$B$10)^1+DemandaEscenario!$F$15*(1+Parametros!$B$10)^1 -> 18528248 | Y7: =DemandaEscenario!$D$16*(1+Parametros!$B$10)^1+DemandaEscenario!$E$16*(1+Parametros!$B$10)^1+DemandaEscenario!$F$16*(1+Parametros!$B$10)^1 -> 20722501 | Z7: =DemandaEscenario!$D$5*(1+Parametros!$B$10)^2+DemandaEscenario!$E$5*(1+Parametros!$B$10)^2+DemandaEscenario!$F$5*(1+Parametros!$B$10)^2 -> 18622143 | AA7: =DemandaEscenario!$D$6*(1+Parametros!$B$10)^2+DemandaEscenario!$E$6*(1+Parametros!$B$10)^2+DemandaEscenario!$F$6*(1+Parametros!$B$10)^2 -> 19198679 | AB7: =DemandaEscenario!$D$7*(1+Parametros!$B$10)^2+DemandaEscenario!$E$7*(1+Parametros!$B$10)^2+DemandaEscenario!$F$7*(1+Parametros!$B$10)^2 -> 20142578 | AC7: =DemandaEscenario!$D$8*(1+Parametros!$B$10)^2+DemandaEscenario!$E$8*(1+Parametros!$B$10)^2+DemandaEscenario!$F$8*(1+Parametros!$B$10)^2 -> 21420752 | AD7: =DemandaEscenario!$D$9*(1+Parametros!$B$10)^2+DemandaEscenario!$E$9*(1+Parametros!$B$10)^2+DemandaEscenario!$F$9*(1+Parametros!$B$10)^2 -> 16259193 | AE7: =DemandaEscenario!$D$10*(1+Parametros!$B$10)^2+DemandaEscenario!$E$10*(1+Parametros!$B$10)^2+DemandaEscenario!$F$10*(1+Parametros!$B$10)^2 -> 19302102 | AF7: =DemandaEscenario!$D$11*(1+Parametros!$B$10)^2+DemandaEscenario!$E$11*(1+Parametros!$B$10)^2+DemandaEscenario!$F$11*(1+Parametros!$B$10)^2 -> 20712213 | AG7: =DemandaEscenario!$D$12*(1+Parametros!$B$10)^2+DemandaEscenario!$E$12*(1+Parametros!$B$10)^2+DemandaEscenario!$F$12*(1+Parametros!$B$10)^2 -> 20875025 | AH7: =DemandaEscenario!$D$13*(1+Parametros!$B$10)^2+DemandaEscenario!$E$13*(1+Parametros!$B$10)^2+DemandaEscenario!$F$13*(1+Parametros!$B$10)^2 -> 24266987 | AI7: =DemandaEscenario!$D$14*(1+Parametros!$B$10)^2+DemandaEscenario!$E$14*(1+Parametros!$B$10)^2+DemandaEscenario!$F$14*(1+Parametros!$B$10)^2 -> 20022727 | AJ7: =DemandaEscenario!$D$15*(1+Parametros!$B$10)^2+DemandaEscenario!$E$15*(1+Parametros!$B$10)^2+DemandaEscenario!$F$15*(1+Parametros!$B$10)^2 -> 18528248 | AK7: =DemandaEscenario!$D$16*(1+Parametros!$B$10)^2+DemandaEscenario!$E$16*(1+Parametros!$B$10)^2+DemandaEscenario!$F$16*(1+Parametros!$B$10)^2 -> 20722501 | AL7: =DemandaEscenario!$D$5*(1+Parametros!$B$10)^3+DemandaEscenario!$E$5*(1+Parametros!$B$10)^3+DemandaEscenario!$F$5*(1+Parametros!$B$10)^3 -> 18622143 | AM7: =DemandaEscenario!$D$6*(1+Parametros!$B$10)^3+DemandaEscenario!$E$6*(1+Parametros!$B$10)^3+DemandaEscenario!$F$6*(1+Parametros!$B$10)^3 -> 19198679 | AN7: =DemandaEscenario!$D$7*(1+Parametros!$B$10)^3+DemandaEscenario!$E$7*(1+Parametros!$B$10)^3+DemandaEscenario!$F$7*(1+Parametros!$B$10)^3 -> 20142578 | AO7: =DemandaEscenario!$D$8*(1+Parametros!$B$10)^3+DemandaEscenario!$E$8*(1+Parametros!$B$10)^3+DemandaEscenario!$F$8*(1+Parametros!$B$10)^3 -> 21420752 | AP7: =DemandaEscenario!$D$9*(1+Parametros!$B$10)^3+DemandaEscenario!$E$9*(1+Parametros!$B$10)^3+DemandaEscenario!$F$9*(1+Parametros!$B$10)^3 -> 16259193 | AQ7: =DemandaEscenario!$D$10*(1+Parametros!$B$10)^3+DemandaEscenario!$E$10*(1+Parametros!$B$10)^3+DemandaEscenario!$F$10*(1+Parametros!$B$10)^3 -> 19302102 | AR7: =DemandaEscenario!$D$11*(1+Parametros!$B$10)^3+DemandaEscenario!$E$11*(1+Parametros!$B$10)^3+DemandaEscenario!$F$11*(1+Parametros!$B$10)^3 -> 20712213 | AS7: =DemandaEscenario!$D$12*(1+Parametros!$B$10)^3+DemandaEscenario!$E$12*(1+Parametros!$B$10)^3+DemandaEscenario!$F$12*(1+Parametros!$B$10)^3 -> 20875025 | AT7: =DemandaEscenario!$D$13*(1+Parametros!$B$10)^3+DemandaEscenario!$E$13*(1+Parametros!$B$10)^3+DemandaEscenario!$F$13*(1+Parametros!$B$10)^3 -> 24266987 | AU7: =DemandaEscenario!$D$14*(1+Parametros!$B$10)^3+DemandaEscenario!$E$14*(1+Parametros!$B$10)^3+DemandaEscenario!$F$14*(1+Parametros!$B$10)^3 -> 20022727 | AV7: =DemandaEscenario!$D$15*(1+Parametros!$B$10)^3+DemandaEscenario!$E$15*(1+Parametros!$B$10)^3+DemandaEscenario!$F$15*(1+Parametros!$B$10)^3 -> 18528248 | AW7: =DemandaEscenario!$D$16*(1+Parametros!$B$10)^3+DemandaEscenario!$E$16*(1+Parametros!$B$10)^3+DemandaEscenario!$F$16*(1+Parametros!$B$10)^3 -> 20722501 | AX7: =DemandaEscenario!$D$5*(1+Parametros!$B$10)^4+DemandaEscenario!$E$5*(1+Parametros!$B$10)^4+DemandaEscenario!$F$5*(1+Parametros!$B$10)^4 -> 18622143 | AY7: =DemandaEscenario!$D$6*(1+Parametros!$B$10)^4+DemandaEscenario!$E$6*(1+Parametros!$B$10)^4+DemandaEscenario!$F$6*(1+Parametros!$B$10)^4 -> 19198679 | AZ7: =DemandaEscenario!$D$7*(1+Parametros!$B$10)^4+DemandaEscenario!$E$7*(1+Parametros!$B$10)^4+DemandaEscenario!$F$7*(1+Parametros!$B$10)^4 -> 20142578 | BA7: =DemandaEscenario!$D$8*(1+Parametros!$B$10)^4+DemandaEscenario!$E$8*(1+Parametros!$B$10)^4+DemandaEscenario!$F$8*(1+Parametros!$B$10)^4 -> 21420752 | BB7: =DemandaEscenario!$D$9*(1+Parametros!$B$10)^4+DemandaEscenario!$E$9*(1+Parametros!$B$10)^4+DemandaEscenario!$F$9*(1+Parametros!$B$10)^4 -> 16259193 | BC7: =DemandaEscenario!$D$10*(1+Parametros!$B$10)^4+DemandaEscenario!$E$10*(1+Parametros!$B$10)^4+DemandaEscenario!$F$10*(1+Parametros!$B$10)^4 -> 19302102 | BD7: =DemandaEscenario!$D$11*(1+Parametros!$B$10)^4+DemandaEscenario!$E$11*(1+Parametros!$B$10)^4+DemandaEscenario!$F$11*(1+Parametros!$B$10)^4 -> 20712213 | BE7: =DemandaEscenario!$D$12*(1+Parametros!$B$10)^4+DemandaEscenario!$E$12*(1+Parametros!$B$10)^4+DemandaEscenario!$F$12*(1+Parametros!$B$10)^4 -> 20875025 | BF7: =DemandaEscenario!$D$13*(1+Parametros!$B$10)^4+DemandaEscenario!$E$13*(1+Parametros!$B$10)^4+DemandaEscenario!$F$13*(1+Parametros!$B$10)^4 -> 24266987 | BG7: =DemandaEscenario!$D$14*(1+Parametros!$B$10)^4+DemandaEscenario!$E$14*(1+Parametros!$B$10)^4+DemandaEscenario!$F$14*(1+Parametros!$B$10)^4 -> 20022727 | BH7: =DemandaEscenario!$D$15*(1+Parametros!$B$10)^4+DemandaEscenario!$E$15*(1+Parametros!$B$10)^4+DemandaEscenario!$F$15*(1+Parametros!$B$10)^4 -> 18528248 | BI7: =DemandaEscenario!$D$16*(1+Parametros!$B$10)^4+DemandaEscenario!$E$16*(1+Parametros!$B$10)^4+DemandaEscenario!$F$16*(1+Parametros!$B$10)^4 -> 20722501
A8: Ingresos base del escenario | B8: =DemandaEscenario!$D$5*Parametros!$B$20+DemandaEscenario!$E$5*Parametros!$B$21+DemandaEscenario!$F$5*Parametros!$B$22 -> 44132568350 | C8: =DemandaEscenario!$D$6*Parametros!$B$20+DemandaEscenario!$E$6*Parametros!$B$21+DemandaEscenario!$F$6*Parametros!$B$22 -> 45498896650 | D8: =DemandaEscenario!$D$7*Parametros!$B$20+DemandaEscenario!$E$7*Parametros!$B$21+DemandaEscenario!$F$7*Parametros!$B$22 -> 47305779900 | E8: =DemandaEscenario!$D$8*Parametros!$B$20+DemandaEscenario!$E$8*Parametros!$B$21+DemandaEscenario!$F$8*Parametros!$B$22 -> 50210008150 | F8: =DemandaEscenario!$D$9*Parametros!$B$20+DemandaEscenario!$E$9*Parametros!$B$21+DemandaEscenario!$F$9*Parametros!$B$22 -> 38455780700 | G8: =DemandaEscenario!$D$10*Parametros!$B$20+DemandaEscenario!$E$10*Parametros!$B$21+DemandaEscenario!$F$10*Parametros!$B$22 -> 45820124550 | H8: =DemandaEscenario!$D$11*Parametros!$B$20+DemandaEscenario!$E$11*Parametros!$B$21+DemandaEscenario!$F$11*Parametros!$B$22 -> 48613238450 | I8: =DemandaEscenario!$D$12*Parametros!$B$20+DemandaEscenario!$E$12*Parametros!$B$21+DemandaEscenario!$F$12*Parametros!$B$22 -> 49259134250 | J8: =DemandaEscenario!$D$13*Parametros!$B$20+DemandaEscenario!$E$13*Parametros!$B$21+DemandaEscenario!$F$13*Parametros!$B$22 -> 57344293500 | K8: =DemandaEscenario!$D$14*Parametros!$B$20+DemandaEscenario!$E$14*Parametros!$B$21+DemandaEscenario!$F$14*Parametros!$B$22 -> 47133099100 | L8: =DemandaEscenario!$D$15*Parametros!$B$20+DemandaEscenario!$E$15*Parametros!$B$21+DemandaEscenario!$F$15*Parametros!$B$22 -> 43616428950 | M8: =DemandaEscenario!$D$16*Parametros!$B$20+DemandaEscenario!$E$16*Parametros!$B$21+DemandaEscenario!$F$16*Parametros!$B$22 -> 48867980250 | N8: =DemandaEscenario!$D$5*(1+Parametros!$B$10)^1*Parametros!$B$20+DemandaEscenario!$E$5*(1+Parametros!$B$10)^1*Parametros!$B$21+DemandaEscenario!$F$5*(1+Parametros!$B$10)^1*Parametros!$B$22 -> 44132568350 | O8: =DemandaEscenario!$D$6*(1+Parametros!$B$10)^1*Parametros!$B$20+DemandaEscenario!$E$6*(1+Parametros!$B$10)^1*Parametros!$B$21+DemandaEscenario!$F$6*(1+Parametros!$B$10)^1*Parametros!$B$22 -> 45498896650 | P8: =DemandaEscenario!$D$7*(1+Parametros!$B$10)^1*Parametros!$B$20+DemandaEscenario!$E$7*(1+Parametros!$B$10)^1*Parametros!$B$21+DemandaEscenario!$F$7*(1+Parametros!$B$10)^1*Parametros!$B$22 -> 47305779900 | Q8: =DemandaEscenario!$D$8*(1+Parametros!$B$10)^1*Parametros!$B$20+DemandaEscenario!$E$8*(1+Parametros!$B$10)^1*Parametros!$B$21+DemandaEscenario!$F$8*(1+Parametros!$B$10)^1*Parametros!$B$22 -> 50210008150 | R8: =DemandaEscenario!$D$9*(1+Parametros!$B$10)^1*Parametros!$B$20+DemandaEscenario!$E$9*(1+Parametros!$B$10)^1*Parametros!$B$21+DemandaEscenario!$F$9*(1+Parametros!$B$10)^1*Parametros!$B$22 -> 38455780700 | S8: =DemandaEscenario!$D$10*(1+Parametros!$B$10)^1*Parametros!$B$20+DemandaEscenario!$E$10*(1+Parametros!$B$10)^1*Parametros!$B$21+DemandaEscenario!$F$10*(1+Parametros!$B$10)^1*Parametros!$B$22 -> 45820124550 | T8: =DemandaEscenario!$D$11*(1+Parametros!$B$10)^1*Parametros!$B$20+DemandaEscenario!$E$11*(1+Parametros!$B$10)^1*Parametros!$B$21+DemandaEscenario!$F$11*(1+Parametros!$B$10)^1*Parametros!$B$22 -> 48613238450 | U8: =DemandaEscenario!$D$12*(1+Parametros!$B$10)^1*Parametros!$B$20+DemandaEscenario!$E$12*(1+Parametros!$B$10)^1*Parametros!$B$21+DemandaEscenario!$F$12*(1+Parametros!$B$10)^1*Parametros!$B$22 -> 49259134250 | V8: =DemandaEscenario!$D$13*(1+Parametros!$B$10)^1*Parametros!$B$20+DemandaEscenario!$E$13*(1+Parametros!$B$10)^1*Parametros!$B$21+DemandaEscenario!$F$13*(1+Parametros!$B$10)^1*Parametros!$B$22 -> 57344293500 | W8: =DemandaEscenario!$D$14*(1+Parametros!$B$10)^1*Parametros!$B$20+DemandaEscenario!$E$14*(1+Parametros!$B$10)^1*Parametros!$B$21+DemandaEscenario!$F$14*(1+Parametros!$B$10)^1*Parametros!$B$22 -> 47133099100 | X8: =DemandaEscenario!$D$15*(1+Parametros!$B$10)^1*Parametros!$B$20+DemandaEscenario!$E$15*(1+Parametros!$B$10)^1*Parametros!$B$21+DemandaEscenario!$F$15*(1+Parametros!$B$10)^1*Parametros!$B$22 -> 43616428950 | Y8: =DemandaEscenario!$D$16*(1+Parametros!$B$10)^1*Parametros!$B$20+DemandaEscenario!$E$16*(1+Parametros!$B$10)^1*Parametros!$B$21+DemandaEscenario!$F$16*(1+Parametros!$B$10)^1*Parametros!$B$22 -> 48867980250 | Z8: =DemandaEscenario!$D$5*(1+Parametros!$B$10)^2*Parametros!$B$20+DemandaEscenario!$E$5*(1+Parametros!$B$10)^2*Parametros!$B$21+DemandaEscenario!$F$5*(1+Parametros!$B$10)^2*Parametros!$B$22 -> 44132568350 | AA8: =DemandaEscenario!$D$6*(1+Parametros!$B$10)^2*Parametros!$B$20+DemandaEscenario!$E$6*(1+Parametros!$B$10)^2*Parametros!$B$21+DemandaEscenario!$F$6*(1+Parametros!$B$10)^2*Parametros!$B$22 -> 45498896650 | AB8: =DemandaEscenario!$D$7*(1+Parametros!$B$10)^2*Parametros!$B$20+DemandaEscenario!$E$7*(1+Parametros!$B$10)^2*Parametros!$B$21+DemandaEscenario!$F$7*(1+Parametros!$B$10)^2*Parametros!$B$22 -> 47305779900 | AC8: =DemandaEscenario!$D$8*(1+Parametros!$B$10)^2*Parametros!$B$20+DemandaEscenario!$E$8*(1+Parametros!$B$10)^2*Parametros!$B$21+DemandaEscenario!$F$8*(1+Parametros!$B$10)^2*Parametros!$B$22 -> 50210008150 | AD8: =DemandaEscenario!$D$9*(1+Parametros!$B$10)^2*Parametros!$B$20+DemandaEscenario!$E$9*(1+Parametros!$B$10)^2*Parametros!$B$21+DemandaEscenario!$F$9*(1+Parametros!$B$10)^2*Parametros!$B$22 -> 38455780700 | AE8: =DemandaEscenario!$D$10*(1+Parametros!$B$10)^2*Parametros!$B$20+DemandaEscenario!$E$10*(1+Parametros!$B$10)^2*Parametros!$B$21+DemandaEscenario!$F$10*(1+Parametros!$B$10)^2*Parametros!$B$22 -> 45820124550 | AF8: =DemandaEscenario!$D$11*(1+Parametros!$B$10)^2*Parametros!$B$20+DemandaEscenario!$E$11*(1+Parametros!$B$10)^2*Parametros!$B$21+DemandaEscenario!$F$11*(1+Parametros!$B$10)^2*Parametros!$B$22 -> 48613238450 | AG8: =DemandaEscenario!$D$12*(1+Parametros!$B$10)^2*Parametros!$B$20+DemandaEscenario!$E$12*(1+Parametros!$B$10)^2*Parametros!$B$21+DemandaEscenario!$F$12*(1+Parametros!$B$10)^2*Parametros!$B$22 -> 49259134250 | AH8: =DemandaEscenario!$D$13*(1+Parametros!$B$10)^2*Parametros!$B$20+DemandaEscenario!$E$13*(1+Parametros!$B$10)^2*Parametros!$B$21+DemandaEscenario!$F$13*(1+Parametros!$B$10)^2*Parametros!$B$22 -> 57344293500 | AI8: =DemandaEscenario!$D$14*(1+Parametros!$B$10)^2*Parametros!$B$20+DemandaEscenario!$E$14*(1+Parametros!$B$10)^2*Parametros!$B$21+DemandaEscenario!$F$14*(1+Parametros!$B$10)^2*Parametros!$B$22 -> 47133099100 | AJ8: =DemandaEscenario!$D$15*(1+Parametros!$B$10)^2*Parametros!$B$20+DemandaEscenario!$E$15*(1+Parametros!$B$10)^2*Parametros!$B$21+DemandaEscenario!$F$15*(1+Parametros!$B$10)^2*Parametros!$B$22 -> 43616428950 | AK8: =DemandaEscenario!$D$16*(1+Parametros!$B$10)^2*Parametros!$B$20+DemandaEscenario!$E$16*(1+Parametros!$B$10)^2*Parametros!$B$21+DemandaEscenario!$F$16*(1+Parametros!$B$10)^2*Parametros!$B$22 -> 48867980250 | AL8: =DemandaEscenario!$D$5*(1+Parametros!$B$10)^3*Parametros!$B$20+DemandaEscenario!$E$5*(1+Parametros!$B$10)^3*Parametros!$B$21+DemandaEscenario!$F$5*(1+Parametros!$B$10)^3*Parametros!$B$22 -> 44132568350 | AM8: =DemandaEscenario!$D$6*(1+Parametros!$B$10)^3*Parametros!$B$20+DemandaEscenario!$E$6*(1+Parametros!$B$10)^3*Parametros!$B$21+DemandaEscenario!$F$6*(1+Parametros!$B$10)^3*Parametros!$B$22 -> 45498896650 | AN8: =DemandaEscenario!$D$7*(1+Parametros!$B$10)^3*Parametros!$B$20+DemandaEscenario!$E$7*(1+Parametros!$B$10)^3*Parametros!$B$21+DemandaEscenario!$F$7*(1+Parametros!$B$10)^3*Parametros!$B$22 -> 47305779900 | AO8: =DemandaEscenario!$D$8*(1+Parametros!$B$10)^3*Parametros!$B$20+DemandaEscenario!$E$8*(1+Parametros!$B$10)^3*Parametros!$B$21+DemandaEscenario!$F$8*(1+Parametros!$B$10)^3*Parametros!$B$22 -> 50210008150 | AP8: =DemandaEscenario!$D$9*(1+Parametros!$B$10)^3*Parametros!$B$20+DemandaEscenario!$E$9*(1+Parametros!$B$10)^3*Parametros!$B$21+DemandaEscenario!$F$9*(1+Parametros!$B$10)^3*Parametros!$B$22 -> 38455780700 | AQ8: =DemandaEscenario!$D$10*(1+Parametros!$B$10)^3*Parametros!$B$20+DemandaEscenario!$E$10*(1+Parametros!$B$10)^3*Parametros!$B$21+DemandaEscenario!$F$10*(1+Parametros!$B$10)^3*Parametros!$B$22 -> 45820124550 | AR8: =DemandaEscenario!$D$11*(1+Parametros!$B$10)^3*Parametros!$B$20+DemandaEscenario!$E$11*(1+Parametros!$B$10)^3*Parametros!$B$21+DemandaEscenario!$F$11*(1+Parametros!$B$10)^3*Parametros!$B$22 -> 48613238450 | AS8: =DemandaEscenario!$D$12*(1+Parametros!$B$10)^3*Parametros!$B$20+DemandaEscenario!$E$12*(1+Parametros!$B$10)^3*Parametros!$B$21+DemandaEscenario!$F$12*(1+Parametros!$B$10)^3*Parametros!$B$22 -> 49259134250 | AT8: =DemandaEscenario!$D$13*(1+Parametros!$B$10)^3*Parametros!$B$20+DemandaEscenario!$E$13*(1+Parametros!$B$10)^3*Parametros!$B$21+DemandaEscenario!$F$13*(1+Parametros!$B$10)^3*Parametros!$B$22 -> 57344293500 | AU8: =DemandaEscenario!$D$14*(1+Parametros!$B$10)^3*Parametros!$B$20+DemandaEscenario!$E$14*(1+Parametros!$B$10)^3*Parametros!$B$21+DemandaEscenario!$F$14*(1+Parametros!$B$10)^3*Parametros!$B$22 -> 47133099100 | AV8: =DemandaEscenario!$D$15*(1+Parametros!$B$10)^3*Parametros!$B$20+DemandaEscenario!$E$15*(1+Parametros!$B$10)^3*Parametros!$B$21+DemandaEscenario!$F$15*(1+Parametros!$B$10)^3*Parametros!$B$22 -> 43616428950 | AW8: =DemandaEscenario!$D$16*(1+Parametros!$B$10)^3*Parametros!$B$20+DemandaEscenario!$E$16*(1+Parametros!$B$10)^3*Parametros!$B$21+DemandaEscenario!$F$16*(1+Parametros!$B$10)^3*Parametros!$B$22 -> 48867980250 | AX8: =DemandaEscenario!$D$5*(1+Parametros!$B$10)^4*Parametros!$B$20+DemandaEscenario!$E$5*(1+Parametros!$B$10)^4*Parametros!$B$21+DemandaEscenario!$F$5*(1+Parametros!$B$10)^4*Parametros!$B$22 -> 44132568350 | AY8: =DemandaEscenario!$D$6*(1+Parametros!$B$10)^4*Parametros!$B$20+DemandaEscenario!$E$6*(1+Parametros!$B$10)^4*Parametros!$B$21+DemandaEscenario!$F$6*(1+Parametros!$B$10)^4*Parametros!$B$22 -> 45498896650 | AZ8: =DemandaEscenario!$D$7*(1+Parametros!$B$10)^4*Parametros!$B$20+DemandaEscenario!$E$7*(1+Parametros!$B$10)^4*Parametros!$B$21+DemandaEscenario!$F$7*(1+Parametros!$B$10)^4*Parametros!$B$22 -> 47305779900 | BA8: =DemandaEscenario!$D$8*(1+Parametros!$B$10)^4*Parametros!$B$20+DemandaEscenario!$E$8*(1+Parametros!$B$10)^4*Parametros!$B$21+DemandaEscenario!$F$8*(1+Parametros!$B$10)^4*Parametros!$B$22 -> 50210008150 | BB8: =DemandaEscenario!$D$9*(1+Parametros!$B$10)^4*Parametros!$B$20+DemandaEscenario!$E$9*(1+Parametros!$B$10)^4*Parametros!$B$21+DemandaEscenario!$F$9*(1+Parametros!$B$10)^4*Parametros!$B$22 -> 38455780700 | BC8: =DemandaEscenario!$D$10*(1+Parametros!$B$10)^4*Parametros!$B$20+DemandaEscenario!$E$10*(1+Parametros!$B$10)^4*Parametros!$B$21+DemandaEscenario!$F$10*(1+Parametros!$B$10)^4*Parametros!$B$22 -> 45820124550 | BD8: =DemandaEscenario!$D$11*(1+Parametros!$B$10)^4*Parametros!$B$20+DemandaEscenario!$E$11*(1+Parametros!$B$10)^4*Parametros!$B$21+DemandaEscenario!$F$11*(1+Parametros!$B$10)^4*Parametros!$B$22 -> 48613238450 | BE8: =DemandaEscenario!$D$12*(1+Parametros!$B$10)^4*Parametros!$B$20+DemandaEscenario!$E$12*(1+Parametros!$B$10)^4*Parametros!$B$21+DemandaEscenario!$F$12*(1+Parametros!$B$10)^4*Parametros!$B$22 -> 49259134250 | BF8: =DemandaEscenario!$D$13*(1+Parametros!$B$10)^4*Parametros!$B$20+DemandaEscenario!$E$13*(1+Parametros!$B$10)^4*Parametros!$B$21+DemandaEscenario!$F$13*(1+Parametros!$B$10)^4*Parametros!$B$22 -> 57344293500 | BG8: =DemandaEscenario!$D$14*(1+Parametros!$B$10)^4*Parametros!$B$20+DemandaEscenario!$E$14*(1+Parametros!$B$10)^4*Parametros!$B$21+DemandaEscenario!$F$14*(1+Parametros!$B$10)^4*Parametros!$B$22 -> 47133099100 | BH8: =DemandaEscenario!$D$15*(1+Parametros!$B$10)^4*Parametros!$B$20+DemandaEscenario!$E$15*(1+Parametros!$B$10)^4*Parametros!$B$21+DemandaEscenario!$F$15*(1+Parametros!$B$10)^4*Parametros!$B$22 -> 43616428950 | BI8: =DemandaEscenario!$D$16*(1+Parametros!$B$10)^4*Parametros!$B$20+DemandaEscenario!$E$16*(1+Parametros!$B$10)^4*Parametros!$B$21+DemandaEscenario!$F$16*(1+Parametros!$B$10)^4*Parametros!$B$22 -> 48867980250
A9: COGS base del escenario | B9: =DemandaEscenario!$D$5*Costos_Lote!$B$18+DemandaEscenario!$E$5*Costos_Lote!$B$33+DemandaEscenario!$F$5*Costos_Lote!$B$46 -> 24814730439 | C9: =DemandaEscenario!$D$6*Costos_Lote!$B$18+DemandaEscenario!$E$6*Costos_Lote!$B$33+DemandaEscenario!$F$6*Costos_Lote!$B$46 -> 25582985355 | D9: =DemandaEscenario!$D$7*Costos_Lote!$B$18+DemandaEscenario!$E$7*Costos_Lote!$B$33+DemandaEscenario!$F$7*Costos_Lote!$B$46 -> 26535689477 | E9: =DemandaEscenario!$D$8*Costos_Lote!$B$18+DemandaEscenario!$E$8*Costos_Lote!$B$33+DemandaEscenario!$F$8*Costos_Lote!$B$46 -> 28149319436 | F9: =DemandaEscenario!$D$9*Costos_Lote!$B$18+DemandaEscenario!$E$9*Costos_Lote!$B$33+DemandaEscenario!$F$9*Costos_Lote!$B$46 -> 21610748347 | G9: =DemandaEscenario!$D$10*Costos_Lote!$B$18+DemandaEscenario!$E$10*Costos_Lote!$B$33+DemandaEscenario!$F$10*Costos_Lote!$B$46 -> 25773962673 | H9: =DemandaEscenario!$D$11*Costos_Lote!$B$18+DemandaEscenario!$E$11*Costos_Lote!$B$33+DemandaEscenario!$F$11*Costos_Lote!$B$46 -> 27265671160 | I9: =DemandaEscenario!$D$12*Costos_Lote!$B$18+DemandaEscenario!$E$12*Costos_Lote!$B$33+DemandaEscenario!$F$12*Costos_Lote!$B$46 -> 27667334573 | J9: =DemandaEscenario!$D$13*Costos_Lote!$B$18+DemandaEscenario!$E$13*Costos_Lote!$B$33+DemandaEscenario!$F$13*Costos_Lote!$B$46 -> 32221629023 | K9: =DemandaEscenario!$D$14*Costos_Lote!$B$18+DemandaEscenario!$E$14*Costos_Lote!$B$33+DemandaEscenario!$F$14*Costos_Lote!$B$46 -> 26454639275 | L9: =DemandaEscenario!$D$15*Costos_Lote!$B$18+DemandaEscenario!$E$15*Costos_Lote!$B$33+DemandaEscenario!$F$15*Costos_Lote!$B$46 -> 24480745588 | M9: =DemandaEscenario!$D$16*Costos_Lote!$B$18+DemandaEscenario!$E$16*Costos_Lote!$B$33+DemandaEscenario!$F$16*Costos_Lote!$B$46 -> 27441536624 | N9: =DemandaEscenario!$D$5*(1+Parametros!$B$10)^1*Costos_Lote!$B$18+DemandaEscenario!$E$5*(1+Parametros!$B$10)^1*Costos_Lote!$B$33+DemandaEscenario!$F$5*(1+Parametros!$B$10)^1*Costos_Lote!$B$46 -> 24814730439 | O9: =DemandaEscenario!$D$6*(1+Parametros!$B$10)^1*Costos_Lote!$B$18+DemandaEscenario!$E$6*(1+Parametros!$B$10)^1*Costos_Lote!$B$33+DemandaEscenario!$F$6*(1+Parametros!$B$10)^1*Costos_Lote!$B$46 -> 25582985355 | P9: =DemandaEscenario!$D$7*(1+Parametros!$B$10)^1*Costos_Lote!$B$18+DemandaEscenario!$E$7*(1+Parametros!$B$10)^1*Costos_Lote!$B$33+DemandaEscenario!$F$7*(1+Parametros!$B$10)^1*Costos_Lote!$B$46 -> 26535689477 | Q9: =DemandaEscenario!$D$8*(1+Parametros!$B$10)^1*Costos_Lote!$B$18+DemandaEscenario!$E$8*(1+Parametros!$B$10)^1*Costos_Lote!$B$33+DemandaEscenario!$F$8*(1+Parametros!$B$10)^1*Costos_Lote!$B$46 -> 28149319436 | R9: =DemandaEscenario!$D$9*(1+Parametros!$B$10)^1*Costos_Lote!$B$18+DemandaEscenario!$E$9*(1+Parametros!$B$10)^1*Costos_Lote!$B$33+DemandaEscenario!$F$9*(1+Parametros!$B$10)^1*Costos_Lote!$B$46 -> 21610748347 | S9: =DemandaEscenario!$D$10*(1+Parametros!$B$10)^1*Costos_Lote!$B$18+DemandaEscenario!$E$10*(1+Parametros!$B$10)^1*Costos_Lote!$B$33+DemandaEscenario!$F$10*(1+Parametros!$B$10)^1*Costos_Lote!$B$46 -> 25773962673 | T9: =DemandaEscenario!$D$11*(1+Parametros!$B$10)^1*Costos_Lote!$B$18+DemandaEscenario!$E$11*(1+Parametros!$B$10)^1*Costos_Lote!$B$33+DemandaEscenario!$F$11*(1+Parametros!$B$10)^1*Costos_Lote!$B$46 -> 27265671160 | U9: =DemandaEscenario!$D$12*(1+Parametros!$B$10)^1*Costos_Lote!$B$18+DemandaEscenario!$E$12*(1+Parametros!$B$10)^1*Costos_Lote!$B$33+DemandaEscenario!$F$12*(1+Parametros!$B$10)^1*Costos_Lote!$B$46 -> 27667334573 | V9: =DemandaEscenario!$D$13*(1+Parametros!$B$10)^1*Costos_Lote!$B$18+DemandaEscenario!$E$13*(1+Parametros!$B$10)^1*Costos_Lote!$B$33+DemandaEscenario!$F$13*(1+Parametros!$B$10)^1*Costos_Lote!$B$46 -> 32221629023 | W9: =DemandaEscenario!$D$14*(1+Parametros!$B$10)^1*Costos_Lote!$B$18+DemandaEscenario!$E$14*(1+Parametros!$B$10)^1*Costos_Lote!$B$33+DemandaEscenario!$F$14*(1+Parametros!$B$10)^1*Costos_Lote!$B$46 -> 26454639275 | X9: =DemandaEscenario!$D$15*(1+Parametros!$B$10)^1*Costos_Lote!$B$18+DemandaEscenario!$E$15*(1+Parametros!$B$10)^1*Costos_Lote!$B$33+DemandaEscenario!$F$15*(1+Parametros!$B$10)^1*Costos_Lote!$B$46 -> 24480745588 | Y9: =DemandaEscenario!$D$16*(1+Parametros!$B$10)^1*Costos_Lote!$B$18+DemandaEscenario!$E$16*(1+Parametros!$B$10)^1*Costos_Lote!$B$33+DemandaEscenario!$F$16*(1+Parametros!$B$10)^1*Costos_Lote!$B$46 -> 27441536624 | Z9: =DemandaEscenario!$D$5*(1+Parametros!$B$10)^2*Costos_Lote!$B$18+DemandaEscenario!$E$5*(1+Parametros!$B$10)^2*Costos_Lote!$B$33+DemandaEscenario!$F$5*(1+Parametros!$B$10)^2*Costos_Lote!$B$46 -> 24814730439 | AA9: =DemandaEscenario!$D$6*(1+Parametros!$B$10)^2*Costos_Lote!$B$18+DemandaEscenario!$E$6*(1+Parametros!$B$10)^2*Costos_Lote!$B$33+DemandaEscenario!$F$6*(1+Parametros!$B$10)^2*Costos_Lote!$B$46 -> 25582985355 | AB9: =DemandaEscenario!$D$7*(1+Parametros!$B$10)^2*Costos_Lote!$B$18+DemandaEscenario!$E$7*(1+Parametros!$B$10)^2*Costos_Lote!$B$33+DemandaEscenario!$F$7*(1+Parametros!$B$10)^2*Costos_Lote!$B$46 -> 26535689477 | AC9: =DemandaEscenario!$D$8*(1+Parametros!$B$10)^2*Costos_Lote!$B$18+DemandaEscenario!$E$8*(1+Parametros!$B$10)^2*Costos_Lote!$B$33+DemandaEscenario!$F$8*(1+Parametros!$B$10)^2*Costos_Lote!$B$46 -> 28149319436 | AD9: =DemandaEscenario!$D$9*(1+Parametros!$B$10)^2*Costos_Lote!$B$18+DemandaEscenario!$E$9*(1+Parametros!$B$10)^2*Costos_Lote!$B$33+DemandaEscenario!$F$9*(1+Parametros!$B$10)^2*Costos_Lote!$B$46 -> 21610748347 | AE9: =DemandaEscenario!$D$10*(1+Parametros!$B$10)^2*Costos_Lote!$B$18+DemandaEscenario!$E$10*(1+Parametros!$B$10)^2*Costos_Lote!$B$33+DemandaEscenario!$F$10*(1+Parametros!$B$10)^2*Costos_Lote!$B$46 -> 25773962673 | AF9: =DemandaEscenario!$D$11*(1+Parametros!$B$10)^2*Costos_Lote!$B$18+DemandaEscenario!$E$11*(1+Parametros!$B$10)^2*Costos_Lote!$B$33+DemandaEscenario!$F$11*(1+Parametros!$B$10)^2*Costos_Lote!$B$46 -> 27265671160 | AG9: =DemandaEscenario!$D$12*(1+Parametros!$B$10)^2*Costos_Lote!$B$18+DemandaEscenario!$E$12*(1+Parametros!$B$10)^2*Costos_Lote!$B$33+DemandaEscenario!$F$12*(1+Parametros!$B$10)^2*Costos_Lote!$B$46 -> 27667334573 | AH9: =DemandaEscenario!$D$13*(1+Parametros!$B$10)^2*Costos_Lote!$B$18+DemandaEscenario!$E$13*(1+Parametros!$B$10)^2*Costos_Lote!$B$33+DemandaEscenario!$F$13*(1+Parametros!$B$10)^2*Costos_Lote!$B$46 -> 32221629023 | AI9: =DemandaEscenario!$D$14*(1+Parametros!$B$10)^2*Costos_Lote!$B$18+DemandaEscenario!$E$14*(1+Parametros!$B$10)^2*Costos_Lote!$B$33+DemandaEscenario!$F$14*(1+Parametros!$B$10)^2*Costos_Lote!$B$46 -> 26454639275 | AJ9: =DemandaEscenario!$D$15*(1+Parametros!$B$10)^2*Costos_Lote!$B$18+DemandaEscenario!$E$15*(1+Parametros!$B$10)^2*Costos_Lote!$B$33+DemandaEscenario!$F$15*(1+Parametros!$B$10)^2*Costos_Lote!$B$46 -> 24480745588 | AK9: =DemandaEscenario!$D$16*(1+Parametros!$B$10)^2*Costos_Lote!$B$18+DemandaEscenario!$E$16*(1+Parametros!$B$10)^2*Costos_Lote!$B$33+DemandaEscenario!$F$16*(1+Parametros!$B$10)^2*Costos_Lote!$B$46 -> 27441536624 | AL9: =DemandaEscenario!$D$5*(1+Parametros!$B$10)^3*Costos_Lote!$B$18+DemandaEscenario!$E$5*(1+Parametros!$B$10)^3*Costos_Lote!$B$33+DemandaEscenario!$F$5*(1+Parametros!$B$10)^3*Costos_Lote!$B$46 -> 24814730439 | AM9: =DemandaEscenario!$D$6*(1+Parametros!$B$10)^3*Costos_Lote!$B$18+DemandaEscenario!$E$6*(1+Parametros!$B$10)^3*Costos_Lote!$B$33+DemandaEscenario!$F$6*(1+Parametros!$B$10)^3*Costos_Lote!$B$46 -> 25582985355 | AN9: =DemandaEscenario!$D$7*(1+Parametros!$B$10)^3*Costos_Lote!$B$18+DemandaEscenario!$E$7*(1+Parametros!$B$10)^3*Costos_Lote!$B$33+DemandaEscenario!$F$7*(1+Parametros!$B$10)^3*Costos_Lote!$B$46 -> 26535689477 | AO9: =DemandaEscenario!$D$8*(1+Parametros!$B$10)^3*Costos_Lote!$B$18+DemandaEscenario!$E$8*(1+Parametros!$B$10)^3*Costos_Lote!$B$33+DemandaEscenario!$F$8*(1+Parametros!$B$10)^3*Costos_Lote!$B$46 -> 28149319436 | AP9: =DemandaEscenario!$D$9*(1+Parametros!$B$10)^3*Costos_Lote!$B$18+DemandaEscenario!$E$9*(1+Parametros!$B$10)^3*Costos_Lote!$B$33+DemandaEscenario!$F$9*(1+Parametros!$B$10)^3*Costos_Lote!$B$46 -> 21610748347 | AQ9: =DemandaEscenario!$D$10*(1+Parametros!$B$10)^3*Costos_Lote!$B$18+DemandaEscenario!$E$10*(1+Parametros!$B$10)^3*Costos_Lote!$B$33+DemandaEscenario!$F$10*(1+Parametros!$B$10)^3*Costos_Lote!$B$46 -> 25773962673 | AR9: =DemandaEscenario!$D$11*(1+Parametros!$B$10)^3*Costos_Lote!$B$18+DemandaEscenario!$E$11*(1+Parametros!$B$10)^3*Costos_Lote!$B$33+DemandaEscenario!$F$11*(1+Parametros!$B$10)^3*Costos_Lote!$B$46 -> 27265671160 | AS9: =DemandaEscenario!$D$12*(1+Parametros!$B$10)^3*Costos_Lote!$B$18+DemandaEscenario!$E$12*(1+Parametros!$B$10)^3*Costos_Lote!$B$33+DemandaEscenario!$F$12*(1+Parametros!$B$10)^3*Costos_Lote!$B$46 -> 27667334573 | AT9: =DemandaEscenario!$D$13*(1+Parametros!$B$10)^3*Costos_Lote!$B$18+DemandaEscenario!$E$13*(1+Parametros!$B$10)^3*Costos_Lote!$B$33+DemandaEscenario!$F$13*(1+Parametros!$B$10)^3*Costos_Lote!$B$46 -> 32221629023 | AU9: =DemandaEscenario!$D$14*(1+Parametros!$B$10)^3*Costos_Lote!$B$18+DemandaEscenario!$E$14*(1+Parametros!$B$10)^3*Costos_Lote!$B$33+DemandaEscenario!$F$14*(1+Parametros!$B$10)^3*Costos_Lote!$B$46 -> 26454639275 | AV9: =DemandaEscenario!$D$15*(1+Parametros!$B$10)^3*Costos_Lote!$B$18+DemandaEscenario!$E$15*(1+Parametros!$B$10)^3*Costos_Lote!$B$33+DemandaEscenario!$F$15*(1+Parametros!$B$10)^3*Costos_Lote!$B$46 -> 24480745588 | AW9: =DemandaEscenario!$D$16*(1+Parametros!$B$10)^3*Costos_Lote!$B$18+DemandaEscenario!$E$16*(1+Parametros!$B$10)^3*Costos_Lote!$B$33+DemandaEscenario!$F$16*(1+Parametros!$B$10)^3*Costos_Lote!$B$46 -> 27441536624 | AX9: =DemandaEscenario!$D$5*(1+Parametros!$B$10)^4*Costos_Lote!$B$18+DemandaEscenario!$E$5*(1+Parametros!$B$10)^4*Costos_Lote!$B$33+DemandaEscenario!$F$5*(1+Parametros!$B$10)^4*Costos_Lote!$B$46 -> 24814730439 | AY9: =DemandaEscenario!$D$6*(1+Parametros!$B$10)^4*Costos_Lote!$B$18+DemandaEscenario!$E$6*(1+Parametros!$B$10)^4*Costos_Lote!$B$33+DemandaEscenario!$F$6*(1+Parametros!$B$10)^4*Costos_Lote!$B$46 -> 25582985355 | AZ9: =DemandaEscenario!$D$7*(1+Parametros!$B$10)^4*Costos_Lote!$B$18+DemandaEscenario!$E$7*(1+Parametros!$B$10)^4*Costos_Lote!$B$33+DemandaEscenario!$F$7*(1+Parametros!$B$10)^4*Costos_Lote!$B$46 -> 26535689477 | BA9: =DemandaEscenario!$D$8*(1+Parametros!$B$10)^4*Costos_Lote!$B$18+DemandaEscenario!$E$8*(1+Parametros!$B$10)^4*Costos_Lote!$B$33+DemandaEscenario!$F$8*(1+Parametros!$B$10)^4*Costos_Lote!$B$46 -> 28149319436 | BB9: =DemandaEscenario!$D$9*(1+Parametros!$B$10)^4*Costos_Lote!$B$18+DemandaEscenario!$E$9*(1+Parametros!$B$10)^4*Costos_Lote!$B$33+DemandaEscenario!$F$9*(1+Parametros!$B$10)^4*Costos_Lote!$B$46 -> 21610748347 | BC9: =DemandaEscenario!$D$10*(1+Parametros!$B$10)^4*Costos_Lote!$B$18+DemandaEscenario!$E$10*(1+Parametros!$B$10)^4*Costos_Lote!$B$33+DemandaEscenario!$F$10*(1+Parametros!$B$10)^4*Costos_Lote!$B$46 -> 25773962673 | BD9: =DemandaEscenario!$D$11*(1+Parametros!$B$10)^4*Costos_Lote!$B$18+DemandaEscenario!$E$11*(1+Parametros!$B$10)^4*Costos_Lote!$B$33+DemandaEscenario!$F$11*(1+Parametros!$B$10)^4*Costos_Lote!$B$46 -> 27265671160 | BE9: =DemandaEscenario!$D$12*(1+Parametros!$B$10)^4*Costos_Lote!$B$18+DemandaEscenario!$E$12*(1+Parametros!$B$10)^4*Costos_Lote!$B$33+DemandaEscenario!$F$12*(1+Parametros!$B$10)^4*Costos_Lote!$B$46 -> 27667334573 | BF9: =DemandaEscenario!$D$13*(1+Parametros!$B$10)^4*Costos_Lote!$B$18+DemandaEscenario!$E$13*(1+Parametros!$B$10)^4*Costos_Lote!$B$33+DemandaEscenario!$F$13*(1+Parametros!$B$10)^4*Costos_Lote!$B$46 -> 32221629023 | BG9: =DemandaEscenario!$D$14*(1+Parametros!$B$10)^4*Costos_Lote!$B$18+DemandaEscenario!$E$14*(1+Parametros!$B$10)^4*Costos_Lote!$B$33+DemandaEscenario!$F$14*(1+Parametros!$B$10)^4*Costos_Lote!$B$46 -> 26454639275 | BH9: =DemandaEscenario!$D$15*(1+Parametros!$B$10)^4*Costos_Lote!$B$18+DemandaEscenario!$E$15*(1+Parametros!$B$10)^4*Costos_Lote!$B$33+DemandaEscenario!$F$15*(1+Parametros!$B$10)^4*Costos_Lote!$B$46 -> 24480745588 | BI9: =DemandaEscenario!$D$16*(1+Parametros!$B$10)^4*Costos_Lote!$B$18+DemandaEscenario!$E$16*(1+Parametros!$B$10)^4*Costos_Lote!$B$33+DemandaEscenario!$F$16*(1+Parametros!$B$10)^4*Costos_Lote!$B$46 -> 27441536624
A10: Factor ventas (uplift monetizado) | B10: =1 -> 1 | C10: =1 -> 1 | D10: =1 -> 1 | E10: =1 -> 1 | F10: =1+Parametros!$B$13*Parametros!$B$11*Parametros!$B$12 -> 1.022847 | G10: =1+Parametros!$B$11*Parametros!$B$12 -> 1.0341 | H10: =1+Parametros!$B$11*Parametros!$B$12 -> 1.0341 | I10: =1+Parametros!$B$11*Parametros!$B$12 -> 1.0341 | J10: =1+Parametros!$B$11*Parametros!$B$12 -> 1.0341 | K10: =1+Parametros!$B$11*Parametros!$B$12 -> 1.0341 | L10: =1+Parametros!$B$11*Parametros!$B$12 -> 1.0341 | M10: =1+Parametros!$B$11*Parametros!$B$12 -> 1.0341 | N10: =1+Parametros!$B$11*Parametros!$B$12 -> 1.0341 | ... BI10: =1+Parametros!$B$11*Parametros!$B$12 -> 1.0341
A11: EBITDA incremental del escenario | B11: {=(B8-B9)*(B10-1)+B9*B10*Parametros!$B$14*0+Parametros!$B$15*0-Licencias!$H$14+INDEX(Parametros!$B:$B,MATCH("ahorro_laboral_monetizable_mes",Parametros!$A:$A,0))*IF(1<=4,0,IF(1=5,Parametros!$B$13,1))} -> 0 | C11: {=(C8-C9)*(C10-1)+C9*C10*Parametros!$B$14*0+Parametros!$B$15*0-Licencias!$H$14+INDEX(Parametros!$B:$B,MATCH("ahorro_laboral_monetizable_mes",Parametros!$A:$A,0))*IF(2<=4,0,IF(2=5,Parametros!$B$13,1))} -> 0 | D11: {=(D8-D9)*(D10-1)+D9*D10*Parametros!$B$14*0+Parametros!$B$15*0-Licencias!$H$14+INDEX(Parametros!$B:$B,MATCH("ahorro_laboral_monetizable_mes",Parametros!$A:$A,0))*IF(3<=4,0,IF(3=5,Parametros!$B$13,1))} -> 0 | E11: {=(E8-E9)*(E10-1)+E9*E10*Parametros!$B$14*0+Parametros!$B$15*0-Licencias!$H$14+INDEX(Parametros!$B:$B,MATCH("ahorro_laboral_monetizable_mes",Parametros!$A:$A,0))*IF(4<=4,0,IF(4=5,Parametros!$B$13,1))} -> 0 | F11: {=(F8-F9)*(F10-1)+F9*F10*Parametros!$B$14*Parametros!$B$13+Parametros!$B$15*Parametros!$B$13-(Parametros!$B$26-Parametros!$B$25)-Licencias!$H$14+INDEX(Parametros!$B:$B,MATCH("ahorro_laboral_monetizable_mes",Parametros!$A:$A,0))*IF(5<=4,0,IF(5=5,Parametros!$B$13,1))} -> 4.3567583e+08 | G11: {=(G8-G9)*(G10-1)+G9*G10*Parametros!$B$14*1+Parametros!$B$15*1-(Parametros!$B$26-Parametros!$B$25)-Licencias!$H$14+INDEX(Parametros!$B:$B,MATCH("ahorro_laboral_monetizable_mes",Parametros!$A:$A,0))*IF(6<=4,0,IF(6=5,Parametros!$B$13,1))} -> 7.7601641e+08 | H11: {=(H8-H9)*(H10-1)+H9*H10*Parametros!$B$14*1+Parametros!$B$15*1-(Parametros!$B$26-Parametros!$B$25)-Licencias!$H$14+INDEX(Parametros!$B:$B,MATCH("ahorro_laboral_monetizable_mes",Parametros!$A:$A,0))*IF(7<=4,0,IF(7=5,Parametros!$B$13,1))} -> 8.2101136e+08 | I11: {=(I8-I9)*(I10-1)+I9*I10*Parametros!$B$14*1+Parametros!$B$15*1-(Parametros!$B$26-Parametros!$B$25)-Licencias!$H$14+INDEX(Parametros!$B:$B,MATCH("ahorro_laboral_monetizable_mes",Parametros!$A:$A,0))*IF(8<=4,0,IF(8=5,Parametros!$B$13,1))} -> 8.2950583e+08 | J11: {=(J8-J9)*(J10-1)+J9*J10*Parametros!$B$14*1+Parametros!$B$15*1-(Parametros!$B$26-Parametros!$B$25)-Licencias!$H$14+INDEX(Parametros!$B:$B,MATCH("ahorro_laboral_monetizable_mes",Parametros!$A:$A,0))*IF(9<=4,0,IF(9=5,Parametros!$B$13,1))} -> 9.5179216e+08 | K11: {=(K8-K9)*(K10-1)+K9*K10*Parametros!$B$14*1+Parametros!$B$15*1-(Parametros!$B$26-Parametros!$B$25)-Licencias!$H$14+INDEX(Parametros!$B:$B,MATCH("ahorro_laboral_monetizable_mes",Parametros!$A:$A,0))*IF(10<=4,0,IF(10=5,Parametros!$B$13,1))} -> 797859323 | L11: {=(L8-L9)*(L10-1)+L9*L10*Parametros!$B$14*1+Parametros!$B$15*1-(Parametros!$B$26-Parametros!$B$25)-Licencias!$H$14+INDEX(Parametros!$B:$B,MATCH("ahorro_laboral_monetizable_mes",Parametros!$A:$A,0))*IF(11<=4,0,IF(11=5,Parametros!$B$13,1))} -> 7.4443416e+08 | M11: {=(M8-M9)*(M10-1)+M9*M10*Parametros!$B$14*1+Parametros!$B$15*1-(Parametros!$B$26-Parametros!$B$25)-Licencias!$H$14+INDEX(Parametros!$B:$B,MATCH("ahorro_laboral_monetizable_mes",Parametros!$A:$A,0))*IF(12<=4,0,IF(12=5,Parametros!$B$13,1))} -> 8.2377379e+08 | N11: {=(N8-N9)*(N10-1)+N9*N10*Parametros!$B$14*1+Parametros!$B$15*1-(Parametros!$B$26-Parametros!$B$25)-Licencias!$H$14+INDEX(Parametros!$B:$B,MATCH("ahorro_laboral_monetizable_mes",Parametros!$A:$A,0))*IF(13<=4,0,IF(13=5,Parametros!$B$13,1))} -> 7.5078378e+08 | O11: {=(O8-O9)*(O10-1)+O9*O10*Parametros!$B$14*1+Parametros!$B$15*1-(Parametros!$B$26-Parametros!$B$25)-Licencias!$H$14+INDEX(Parametros!$B:$B,MATCH("ahorro_laboral_monetizable_mes",Parametros!$A:$A,0))*IF(14<=4,0,IF(14=5,Parametros!$B$13,1))} -> 7.7149587e+08 | P11: {=(P8-P9)*(P10-1)+P9*P10*Parametros!$B$14*1+Parametros!$B$15*1-(Parametros!$B$26-Parametros!$B$25)-Licencias!$H$14+INDEX(Parametros!$B:$B,MATCH("ahorro_laboral_monetizable_mes",Parametros!$A:$A,0))*IF(15<=4,0,IF(15=5,Parametros!$B$13,1))} -> 801017452 | Q11: {=(Q8-Q9)*(Q10-1)+Q9*Q10*Parametros!$B$14*1+Parametros!$B$15*1-(Parametros!$B$26-Parametros!$B$25)-Licencias!$H$14+INDEX(Parametros!$B:$B,MATCH("ahorro_laboral_monetizable_mes",Parametros!$A:$A,0))*IF(16<=4,0,IF(16=5,Parametros!$B$13,1))} -> 8.4569432e+08 | R11: {=(R8-R9)*(R10-1)+R9*R10*Parametros!$B$14*1+Parametros!$B$15*1-(Parametros!$B$26-Parametros!$B$25)-Licencias!$H$14+INDEX(Parametros!$B:$B,MATCH("ahorro_laboral_monetizable_mes",Parametros!$A:$A,0))*IF(17<=4,0,IF(17=5,Parametros!$B$13,1))} -> 6.6513582e+08 | S11: {=(S8-S9)*(S10-1)+S9*S10*Parametros!$B$14*1+Parametros!$B$15*1-(Parametros!$B$26-Parametros!$B$25)-Licencias!$H$14+INDEX(Parametros!$B:$B,MATCH("ahorro_laboral_monetizable_mes",Parametros!$A:$A,0))*IF(18<=4,0,IF(18=5,Parametros!$B$13,1))} -> 7.7601641e+08 | T11: {=(T8-T9)*(T10-1)+T9*T10*Parametros!$B$14*1+Parametros!$B$15*1-(Parametros!$B$26-Parametros!$B$25)-Licencias!$H$14+INDEX(Parametros!$B:$B,MATCH("ahorro_laboral_monetizable_mes",Parametros!$A:$A,0))*IF(19<=4,0,IF(19=5,Parametros!$B$13,1))} -> 8.2101136e+08 | U11: {=(U8-U9)*(U10-1)+U9*U10*Parametros!$B$14*1+Parametros!$B$15*1-(Parametros!$B$26-Parametros!$B$25)-Licencias!$H$14+INDEX(Parametros!$B:$B,MATCH("ahorro_laboral_monetizable_mes",Parametros!$A:$A,0))*IF(20<=4,0,IF(20=5,Parametros!$B$13,1))} -> 8.2950583e+08 | V11: {=(V8-V9)*(V10-1)+V9*V10*Parametros!$B$14*1+Parametros!$B$15*1-(Parametros!$B$26-Parametros!$B$25)-Licencias!$H$14+INDEX(Parametros!$B:$B,MATCH("ahorro_laboral_monetizable_mes",Parametros!$A:$A,0))*IF(21<=4,0,IF(21=5,Parametros!$B$13,1))} -> 9.5179216e+08 | W11: {=(W8-W9)*(W10-1)+W9*W10*Parametros!$B$14*1+Parametros!$B$15*1-(Parametros!$B$26-Parametros!$B$25)-Licencias!$H$14+INDEX(Parametros!$B:$B,MATCH("ahorro_laboral_monetizable_mes",Parametros!$A:$A,0))*IF(22<=4,0,IF(22=5,Parametros!$B$13,1))} -> 797859323 | X11: {=(X8-X9)*(X10-1)+X9*X10*Parametros!$B$14*1+Parametros!$B$15*1-(Parametros!$B$26-Parametros!$B$25)-Licencias!$H$14+INDEX(Parametros!$B:$B,MATCH("ahorro_laboral_monetizable_mes",Parametros!$A:$A,0))*IF(23<=4,0,IF(23=5,Parametros!$B$13,1))} -> 7.4443416e+08 | Y11: {=(Y8-Y9)*(Y10-1)+Y9*Y10*Parametros!$B$14*1+Parametros!$B$15*1-(Parametros!$B$26-Parametros!$B$25)-Licencias!$H$14+INDEX(Parametros!$B:$B,MATCH("ahorro_laboral_monetizable_mes",Parametros!$A:$A,0))*IF(24<=4,0,IF(24=5,Parametros!$B$13,1))} -> 8.2377379e+08 | Z11: {=(Z8-Z9)*(Z10-1)+Z9*Z10*Parametros!$B$14*1+Parametros!$B$15*1-(Parametros!$B$26-Parametros!$B$25)-Licencias!$H$14+INDEX(Parametros!$B:$B,MATCH("ahorro_laboral_monetizable_mes",Parametros!$A:$A,0))*IF(25<=4,0,IF(25=5,Parametros!$B$13,1))} -> 7.5078378e+08 | AA11: {=(AA8-AA9)*(AA10-1)+AA9*AA10*Parametros!$B$14*1+Parametros!$B$15*1-(Parametros!$B$26-Parametros!$B$25)-Licencias!$H$14+INDEX(Parametros!$B:$B,MATCH("ahorro_laboral_monetizable_mes",Parametros!$A:$A,0))*IF(26<=4,0,IF(26=5,Parametros!$B$13,1))} -> 7.7149587e+08 | AB11: {=(AB8-AB9)*(AB10-1)+AB9*AB10*Parametros!$B$14*1+Parametros!$B$15*1-(Parametros!$B$26-Parametros!$B$25)-Licencias!$H$14+INDEX(Parametros!$B:$B,MATCH("ahorro_laboral_monetizable_mes",Parametros!$A:$A,0))*IF(27<=4,0,IF(27=5,Parametros!$B$13,1))} -> 801017452 | AC11: {=(AC8-AC9)*(AC10-1)+AC9*AC10*Parametros!$B$14*1+Parametros!$B$15*1-(Parametros!$B$26-Parametros!$B$25)-Licencias!$H$14+INDEX(Parametros!$B:$B,MATCH("ahorro_laboral_monetizable_mes",Parametros!$A:$A,0))*IF(28<=4,0,IF(28=5,Parametros!$B$13,1))} -> 8.4569432e+08 | AD11: {=(AD8-AD9)*(AD10-1)+AD9*AD10*Parametros!$B$14*1+Parametros!$B$15*1-(Parametros!$B$26-Parametros!$B$25)-Licencias!$H$14+INDEX(Parametros!$B:$B,MATCH("ahorro_laboral_monetizable_mes",Parametros!$A:$A,0))*IF(29<=4,0,IF(29=5,Parametros!$B$13,1))} -> 6.6513582e+08 | AE11: {=(AE8-AE9)*(AE10-1)+AE9*AE10*Parametros!$B$14*1+Parametros!$B$15*1-(Parametros!$B$26-Parametros!$B$25)-Licencias!$H$14+INDEX(Parametros!$B:$B,MATCH("ahorro_laboral_monetizable_mes",Parametros!$A:$A,0))*IF(30<=4,0,IF(30=5,Parametros!$B$13,1))} -> 7.7601641e+08 | AF11: {=(AF8-AF9)*(AF10-1)+AF9*AF10*Parametros!$B$14*1+Parametros!$B$15*1-(Parametros!$B$26-Parametros!$B$25)-Licencias!$H$14+INDEX(Parametros!$B:$B,MATCH("ahorro_laboral_monetizable_mes",Parametros!$A:$A,0))*IF(31<=4,0,IF(31=5,Parametros!$B$13,1))} -> 8.2101136e+08 | AG11: {=(AG8-AG9)*(AG10-1)+AG9*AG10*Parametros!$B$14*1+Parametros!$B$15*1-(Parametros!$B$26-Parametros!$B$25)-Licencias!$H$14+INDEX(Parametros!$B:$B,MATCH("ahorro_laboral_monetizable_mes",Parametros!$A:$A,0))*IF(32<=4,0,IF(32=5,Parametros!$B$13,1))} -> 8.2950583e+08 | AH11: {=(AH8-AH9)*(AH10-1)+AH9*AH10*Parametros!$B$14*1+Parametros!$B$15*1-(Parametros!$B$26-Parametros!$B$25)-Licencias!$H$14+INDEX(Parametros!$B:$B,MATCH("ahorro_laboral_monetizable_mes",Parametros!$A:$A,0))*IF(33<=4,0,IF(33=5,Parametros!$B$13,1))} -> 9.5179216e+08 | AI11: {=(AI8-AI9)*(AI10-1)+AI9*AI10*Parametros!$B$14*1+Parametros!$B$15*1-(Parametros!$B$26-Parametros!$B$25)-Licencias!$H$14+INDEX(Parametros!$B:$B,MATCH("ahorro_laboral_monetizable_mes",Parametros!$A:$A,0))*IF(34<=4,0,IF(34=5,Parametros!$B$13,1))} -> 797859323 | AJ11: {=(AJ8-AJ9)*(AJ10-1)+AJ9*AJ10*Parametros!$B$14*1+Parametros!$B$15*1-(Parametros!$B$26-Parametros!$B$25)-Licencias!$H$14+INDEX(Parametros!$B:$B,MATCH("ahorro_laboral_monetizable_mes",Parametros!$A:$A,0))*IF(35<=4,0,IF(35=5,Parametros!$B$13,1))} -> 7.4443416e+08 | AK11: {=(AK8-AK9)*(AK10-1)+AK9*AK10*Parametros!$B$14*1+Parametros!$B$15*1-(Parametros!$B$26-Parametros!$B$25)-Licencias!$H$14+INDEX(Parametros!$B:$B,MATCH("ahorro_laboral_monetizable_mes",Parametros!$A:$A,0))*IF(36<=4,0,IF(36=5,Parametros!$B$13,1))} -> 8.2377379e+08 | AL11: {=(AL8-AL9)*(AL10-1)+AL9*AL10*Parametros!$B$14*1+Parametros!$B$15*1-(Parametros!$B$26-Parametros!$B$25)-Licencias!$H$14+INDEX(Parametros!$B:$B,MATCH("ahorro_laboral_monetizable_mes",Parametros!$A:$A,0))*IF(37<=4,0,IF(37=5,Parametros!$B$13,1))} -> 7.5078378e+08 | AM11: {=(AM8-AM9)*(AM10-1)+AM9*AM10*Parametros!$B$14*1+Parametros!$B$15*1-(Parametros!$B$26-Parametros!$B$25)-Licencias!$H$14+INDEX(Parametros!$B:$B,MATCH("ahorro_laboral_monetizable_mes",Parametros!$A:$A,0))*IF(38<=4,0,IF(38=5,Parametros!$B$13,1))} -> 7.7149587e+08 | AN11: {=(AN8-AN9)*(AN10-1)+AN9*AN10*Parametros!$B$14*1+Parametros!$B$15*1-(Parametros!$B$26-Parametros!$B$25)-Licencias!$H$14+INDEX(Parametros!$B:$B,MATCH("ahorro_laboral_monetizable_mes",Parametros!$A:$A,0))*IF(39<=4,0,IF(39=5,Parametros!$B$13,1))} -> 801017452 | AO11: {=(AO8-AO9)*(AO10-1)+AO9*AO10*Parametros!$B$14*1+Parametros!$B$15*1-(Parametros!$B$26-Parametros!$B$25)-Licencias!$H$14+INDEX(Parametros!$B:$B,MATCH("ahorro_laboral_monetizable_mes",Parametros!$A:$A,0))*IF(40<=4,0,IF(40=5,Parametros!$B$13,1))} -> 8.4569432e+08 | AP11: {=(AP8-AP9)*(AP10-1)+AP9*AP10*Parametros!$B$14*1+Parametros!$B$15*1-(Parametros!$B$26-Parametros!$B$25)-Licencias!$H$14+INDEX(Parametros!$B:$B,MATCH("ahorro_laboral_monetizable_mes",Parametros!$A:$A,0))*IF(41<=4,0,IF(41=5,Parametros!$B$13,1))} -> 6.6513582e+08 | AQ11: {=(AQ8-AQ9)*(AQ10-1)+AQ9*AQ10*Parametros!$B$14*1+Parametros!$B$15*1-(Parametros!$B$26-Parametros!$B$25)-Licencias!$H$14+INDEX(Parametros!$B:$B,MATCH("ahorro_laboral_monetizable_mes",Parametros!$A:$A,0))*IF(42<=4,0,IF(42=5,Parametros!$B$13,1))} -> 7.7601641e+08 | AR11: {=(AR8-AR9)*(AR10-1)+AR9*AR10*Parametros!$B$14*1+Parametros!$B$15*1-(Parametros!$B$26-Parametros!$B$25)-Licencias!$H$14+INDEX(Parametros!$B:$B,MATCH("ahorro_laboral_monetizable_mes",Parametros!$A:$A,0))*IF(43<=4,0,IF(43=5,Parametros!$B$13,1))} -> 8.2101136e+08 | AS11: {=(AS8-AS9)*(AS10-1)+AS9*AS10*Parametros!$B$14*1+Parametros!$B$15*1-(Parametros!$B$26-Parametros!$B$25)-Licencias!$H$14+INDEX(Parametros!$B:$B,MATCH("ahorro_laboral_monetizable_mes",Parametros!$A:$A,0))*IF(44<=4,0,IF(44=5,Parametros!$B$13,1))} -> 8.2950583e+08 | AT11: {=(AT8-AT9)*(AT10-1)+AT9*AT10*Parametros!$B$14*1+Parametros!$B$15*1-(Parametros!$B$26-Parametros!$B$25)-Licencias!$H$14+INDEX(Parametros!$B:$B,MATCH("ahorro_laboral_monetizable_mes",Parametros!$A:$A,0))*IF(45<=4,0,IF(45=5,Parametros!$B$13,1))} -> 9.5179216e+08 | AU11: {=(AU8-AU9)*(AU10-1)+AU9*AU10*Parametros!$B$14*1+Parametros!$B$15*1-(Parametros!$B$26-Parametros!$B$25)-Licencias!$H$14+INDEX(Parametros!$B:$B,MATCH("ahorro_laboral_monetizable_mes",Parametros!$A:$A,0))*IF(46<=4,0,IF(46=5,Parametros!$B$13,1))} -> 797859323 | AV11: {=(AV8-AV9)*(AV10-1)+AV9*AV10*Parametros!$B$14*1+Parametros!$B$15*1-(Parametros!$B$26-Parametros!$B$25)-Licencias!$H$14+INDEX(Parametros!$B:$B,MATCH("ahorro_laboral_monetizable_mes",Parametros!$A:$A,0))*IF(47<=4,0,IF(47=5,Parametros!$B$13,1))} -> 7.4443416e+08 | AW11: {=(AW8-AW9)*(AW10-1)+AW9*AW10*Parametros!$B$14*1+Parametros!$B$15*1-(Parametros!$B$26-Parametros!$B$25)-Licencias!$H$14+INDEX(Parametros!$B:$B,MATCH("ahorro_laboral_monetizable_mes",Parametros!$A:$A,0))*IF(48<=4,0,IF(48=5,Parametros!$B$13,1))} -> 8.2377379e+08 | AX11: {=(AX8-AX9)*(AX10-1)+AX9*AX10*Parametros!$B$14*1+Parametros!$B$15*1-(Parametros!$B$26-Parametros!$B$25)-Licencias!$H$14+INDEX(Parametros!$B:$B,MATCH("ahorro_laboral_monetizable_mes",Parametros!$A:$A,0))*IF(49<=4,0,IF(49=5,Parametros!$B$13,1))} -> 7.5078378e+08 | AY11: {=(AY8-AY9)*(AY10-1)+AY9*AY10*Parametros!$B$14*1+Parametros!$B$15*1-(Parametros!$B$26-Parametros!$B$25)-Licencias!$H$14+INDEX(Parametros!$B:$B,MATCH("ahorro_laboral_monetizable_mes",Parametros!$A:$A,0))*IF(50<=4,0,IF(50=5,Parametros!$B$13,1))} -> 7.7149587e+08 | AZ11: {=(AZ8-AZ9)*(AZ10-1)+AZ9*AZ10*Parametros!$B$14*1+Parametros!$B$15*1-(Parametros!$B$26-Parametros!$B$25)-Licencias!$H$14+INDEX(Parametros!$B:$B,MATCH("ahorro_laboral_monetizable_mes",Parametros!$A:$A,0))*IF(51<=4,0,IF(51=5,Parametros!$B$13,1))} -> 801017452 | BA11: {=(BA8-BA9)*(BA10-1)+BA9*BA10*Parametros!$B$14*1+Parametros!$B$15*1-(Parametros!$B$26-Parametros!$B$25)-Licencias!$H$14+INDEX(Parametros!$B:$B,MATCH("ahorro_laboral_monetizable_mes",Parametros!$A:$A,0))*IF(52<=4,0,IF(52=5,Parametros!$B$13,1))} -> 8.4569432e+08 | BB11: {=(BB8-BB9)*(BB10-1)+BB9*BB10*Parametros!$B$14*1+Parametros!$B$15*1-(Parametros!$B$26-Parametros!$B$25)-Licencias!$H$14+INDEX(Parametros!$B:$B,MATCH("ahorro_laboral_monetizable_mes",Parametros!$A:$A,0))*IF(53<=4,0,IF(53=5,Parametros!$B$13,1))} -> 6.6513582e+08 | BC11: {=(BC8-BC9)*(BC10-1)+BC9*BC10*Parametros!$B$14*1+Parametros!$B$15*1-(Parametros!$B$26-Parametros!$B$25)-Licencias!$H$14+INDEX(Parametros!$B:$B,MATCH("ahorro_laboral_monetizable_mes",Parametros!$A:$A,0))*IF(54<=4,0,IF(54=5,Parametros!$B$13,1))} -> 7.7601641e+08 | BD11: {=(BD8-BD9)*(BD10-1)+BD9*BD10*Parametros!$B$14*1+Parametros!$B$15*1-(Parametros!$B$26-Parametros!$B$25)-Licencias!$H$14+INDEX(Parametros!$B:$B,MATCH("ahorro_laboral_monetizable_mes",Parametros!$A:$A,0))*IF(55<=4,0,IF(55=5,Parametros!$B$13,1))} -> 8.2101136e+08 | BE11: {=(BE8-BE9)*(BE10-1)+BE9*BE10*Parametros!$B$14*1+Parametros!$B$15*1-(Parametros!$B$26-Parametros!$B$25)-Licencias!$H$14+INDEX(Parametros!$B:$B,MATCH("ahorro_laboral_monetizable_mes",Parametros!$A:$A,0))*IF(56<=4,0,IF(56=5,Parametros!$B$13,1))} -> 8.2950583e+08 | BF11: {=(BF8-BF9)*(BF10-1)+BF9*BF10*Parametros!$B$14*1+Parametros!$B$15*1-(Parametros!$B$26-Parametros!$B$25)-Licencias!$H$14+INDEX(Parametros!$B:$B,MATCH("ahorro_laboral_monetizable_mes",Parametros!$A:$A,0))*IF(57<=4,0,IF(57=5,Parametros!$B$13,1))} -> 9.5179216e+08 | BG11: {=(BG8-BG9)*(BG10-1)+BG9*BG10*Parametros!$B$14*1+Parametros!$B$15*1-(Parametros!$B$26-Parametros!$B$25)-Licencias!$H$14+INDEX(Parametros!$B:$B,MATCH("ahorro_laboral_monetizable_mes",Parametros!$A:$A,0))*IF(58<=4,0,IF(58=5,Parametros!$B$13,1))} -> 797859323 | BH11: {=(BH8-BH9)*(BH10-1)+BH9*BH10*Parametros!$B$14*1+Parametros!$B$15*1-(Parametros!$B$26-Parametros!$B$25)-Licencias!$H$14+INDEX(Parametros!$B:$B,MATCH("ahorro_laboral_monetizable_mes",Parametros!$A:$A,0))*IF(59<=4,0,IF(59=5,Parametros!$B$13,1))} -> 7.4443416e+08 | BI11: {=(BI8-BI9)*(BI10-1)+BI9*BI10*Parametros!$B$14*1+Parametros!$B$15*1-(Parametros!$B$26-Parametros!$B$25)-Licencias!$H$14+INDEX(Parametros!$B:$B,MATCH("ahorro_laboral_monetizable_mes",Parametros!$A:$A,0))*IF(60<=4,0,IF(60=5,Parametros!$B$13,1))} -> 8.2377379e+08
A12: D&A | B12: =0 -> 0 | C12: =0 -> 0 | D12: =0 -> 0 | E12: =0 -> 0 | F12: =Dep_Amort!$D$10 -> 95119495 | G12: =Dep_Amort!$D$10 -> 95119495 | H12: =Dep_Amort!$D$10 -> 95119495 | I12: =Dep_Amort!$D$10 -> 95119495 | J12: =Dep_Amort!$D$10 -> 95119495 | K12: =Dep_Amort!$D$10 -> 95119495 | L12: =Dep_Amort!$D$10 -> 95119495 | M12: =Dep_Amort!$D$10 -> 95119495 | ... BI12: =Dep_Amort!$D$10 -> 95119495
A13: Impuesto | B13: =MAX(0,B11-B12)*Parametros!$B$8 -> 0 | C13: =MAX(0,C11-C12)*Parametros!$B$8 -> 0 | D13: =MAX(0,D11-D12)*Parametros!$B$8 -> 0 | E13: =MAX(0,E11-E12)*Parametros!$B$8 -> 0 | F13: =MAX(0,F11-F12)*Parametros!$B$8 -> 1.1919472e+08 | G13: =MAX(0,G11-G12)*Parametros!$B$8 -> 2.3831392e+08 | H13: =MAX(0,H11-H12)*Parametros!$B$8 -> 2.5406215e+08 | I13: =MAX(0,I11-I12)*Parametros!$B$8 -> 2.5703522e+08 | ... BI13: =MAX(0,BI11-BI12)*Parametros!$B$8 -> 2.55029e+08
A14: FCF del escenario | B14: {=B11-B13-INDEX(CAPEX!$G:$G,MATCH("CAPEX TOTAL (con contingencia)",CAPEX!$C:$C,0))*Parametros!$B$28-INDEX(RRHH!$E:$E,MATCH("Costo mensual IMPLEMENTACION (→ pre-op)",RRHH!$A:$A,0))} -> -1920272609 | C14: {=C11-C13-INDEX(CAPEX!$G:$G,MATCH("CAPEX TOTAL (con contingencia)",CAPEX!$C:$C,0))*Parametros!$B$29-INDEX(RRHH!$E:$E,MATCH("Costo mensual IMPLEMENTACION (→ pre-op)",RRHH!$A:$A,0))} -> -3295105746 | D14: {=D11-D13-INDEX(CAPEX!$G:$G,MATCH("CAPEX TOTAL (con contingencia)",CAPEX!$C:$C,0))*Parametros!$B$30-INDEX(RRHH!$E:$E,MATCH("Costo mensual IMPLEMENTACION (→ pre-op)",RRHH!$A:$A,0))} -> -2561861406 | E14: {=E11-E13-INDEX(CAPEX!$G:$G,MATCH("CAPEX TOTAL (con contingencia)",CAPEX!$C:$C,0))*Parametros!$B$31-INDEX(RRHH!$E:$E,MATCH("Costo mensual IMPLEMENTACION (→ pre-op)",RRHH!$A:$A,0))} -> -1736961524 | F14: =F11-F13-Parametros!$B$16*($G$8*($G$10-1)) -> 1.9148381e+08 | G14: =G11-G13 -> 5.3770249e+08 | H14: =H11-H13 -> 5.6694921e+08 | I14: =I11-I13 -> 5.7247061e+08 | J14: =J11-J13 -> 6.5195673e+08 | K14: =K11-K13 -> 5.5190038e+08 | L14: =L11-L13 -> 517174030 | M14: =M11-M13 -> 5.6874479e+08 | N14: =N11-N13 -> 5.2130128e+08 | ... BH14: =BH11-BH13 -> 517174030 | BI14: =BI11-BI13+Parametros!$B$16*($G$8*($G$10-1)) -> 6.9374209e+08
A15: FCF descontado | B15: =B14/(1+$B$3)^1 -> -1893968361 | C15: =C14/(1+$B$3)^2 -> -3205450110 | D15: =D14/(1+$B$3)^3 -> -2458018399 | E15: =E14/(1+$B$3)^4 -> -1643726396 | F15: =F14/(1+$B$3)^5 -> 1.7872332e+08 | G15: =G14/(1+$B$3)^6 -> 4.9499526e+08 | H15: =H14/(1+$B$3)^7 -> 5.1476971e+08 | I15: =I14/(1+$B$3)^8 -> 5.1266286e+08 | J15: =J14/(1+$B$3)^9 -> 5.7584721e+08 | K15: =K14/(1+$B$3)^10 -> 4.8079398e+08 | L15: =L14/(1+$B$3)^11 -> 4.4437014e+08 | M15: =M14/(1+$B$3)^12 -> 4.8198711e+08 | N15: =N14/(1+$B$3)^13 -> 4.3572915e+08 | O15: =O14/(1+$B$3)^14 -> 4.4085922e+08 | P15: =P14/(1+$B$3)^15 -> 450422981 | Q15: =Q14/(1+$B$3)^16 -> 467542139 | R15: =R14/(1+$B$3)^17 -> 3.683055e+08 | S15: =S14/(1+$B$3)^18 -> 4.1948751e+08 | T15: =T14/(1+$B$3)^19 -> 4.3624552e+08 | U15: =U14/(1+$B$3)^20 -> 4.3446005e+08 | V15: =V14/(1+$B$3)^21 -> 4.8800611e+08 | W15: =W14/(1+$B$3)^22 -> 4.0745253e+08 | X15: =X14/(1+$B$3)^23 -> 3.7658486e+08 | Y15: =Y14/(1+$B$3)^24 -> 4.0846365e+08 | Z15: =Z14/(1+$B$3)^25 -> 369261995 | AA15: =AA14/(1+$B$3)^26 -> 3.7360951e+08 | AB15: =AB14/(1+$B$3)^27 -> 3.8171439e+08 | AC15: =AC14/(1+$B$3)^28 -> 3.9622215e+08 | AD15: =AD14/(1+$B$3)^29 -> 3.1212331e+08 | AE15: =AE14/(1+$B$3)^30 -> 3.5549789e+08 | AF15: =AF14/(1+$B$3)^31 -> 3.6969959e+08 | AG15: =AG14/(1+$B$3)^32 -> 3.6818649e+08 | AH15: =AH14/(1+$B$3)^33 -> 4.135645e+08 | AI15: =AI14/(1+$B$3)^34 -> 3.4529875e+08 | AJ15: =AJ14/(1+$B$3)^35 -> 3.1913972e+08 | AK15: =AK14/(1+$B$3)^36 -> 3.4615564e+08 | AL15: =AL14/(1+$B$3)^37 -> 312933894 | AM15: =AM14/(1+$B$3)^38 -> 3.1661823e+08 | AN15: =AN14/(1+$B$3)^39 -> 3.2348677e+08 | AO15: =AO14/(1+$B$3)^40 -> 3.3578148e+08 | AP15: =AP14/(1+$B$3)^41 -> 2.6451128e+08 | AQ15: =AQ14/(1+$B$3)^42 -> 3.012694e+08 | AR15: =AR14/(1+$B$3)^43 -> 3.1330474e+08 | AS15: =AS14/(1+$B$3)^44 -> 3.1202245e+08 | AT15: =AT14/(1+$B$3)^45 -> 3.5047839e+08 | AU15: =AU14/(1+$B$3)^46 -> 2.9262606e+08 | AV15: =AV14/(1+$B$3)^47 -> 2.7045739e+08 | AW15: =AW14/(1+$B$3)^48 -> 2.9335223e+08 | AX15: =AX14/(1+$B$3)^49 -> 2.6519822e+08 | AY15: =AY14/(1+$B$3)^50 -> 2.6832053e+08 | AZ15: =AZ14/(1+$B$3)^51 -> 274141332 | BA15: =BA14/(1+$B$3)^52 -> 2.8456058e+08 | BB15: =BB14/(1+$B$3)^53 -> 224162100 | BC15: =BC14/(1+$B$3)^54 -> 2.5531305e+08 | BD15: =BD14/(1+$B$3)^55 -> 2.6551249e+08 | BE15: =BE14/(1+$B$3)^56 -> 2.644258e+08 | BF15: =BF14/(1+$B$3)^57 -> 2.9701558e+08 | BG15: =BG14/(1+$B$3)^58 -> 247988187 | BH15: =BH14/(1+$B$3)^59 -> 2.2920117e+08 | BI15: =BI14/(1+$B$3)^60 -> 3.0324106e+08
A16: FCF acumulado | B16: =B14 -> -1920272609 | C16: =B16+C14 -> -5215378355 | D16: =C16+D14 -> -7777239761 | E16: =D16+E14 -> -9514201285 | F16: =E16+F14 -> -9322717476 | G16: =F16+G14 -> -8785014987 | H16: =G16+H14 -> -8218065778 | I16: =H16+I14 -> -7645595165 | J16: =I16+J14 -> -6993638438 | ... BI16: =BH16+BI14 -> 21271338298
A17: Acumulado descontado | B17: =B15 -> -1893968361 | C17: =B17+C15 -> -5099418472 | D17: =C17+D15 -> -7557436871 | E17: =D17+E15 -> -9201163266 | F17: =E17+F15 -> -9022439946 | G17: =F17+G15 -> -8527444684 | H17: =G17+H15 -> -8012674975 | I17: =H17+I15 -> -7500012111 | J17: =I17+J15 -> -6924164903 | ... BI17: =BH17+BI15 -> 10832941906
A20: INDICADORES DEL ESCENARIO vs BASE
A21: VPN escenario (COP) | B21: =SUM(B15:BI15) -> 10832941906
A22: Δ VPN vs Base (COP) | B22: =B21-Flujo_Caja!B19 -> -1.9912716e+08
A23: TIR mensual | B23: =IRR(B14:BI14,0.02) -> 0.04872009
A24: TIR anual (E.A.) | B24: =(1+B23)^12-1 -> 0.76976275
A25: ROI 60 meses | B25: =SUM(B14:BI14)/(-SUM(B14:E14)) -> 2.2357461
A26: Payback simple (mes) | B26: =MATCH(TRUE(),INDEX(B16:BI16>0,0),0) -> 22
A27: Payback descontado (mes) | B27: =MATCH(TRUE(),INDEX(B17:BI17>0,0),0) -> 26
A28: EBITDA incremental 12m operativos | B28: =SUM(F11:Q11) -> 9349060283
A29: ROI Anualizado | B29: =(1+B25)^(12/60)-1 -> 0.26472146

Sheet Sensibilidad
A1: Analisis de sensibilidad — tres escenarios (base financiera)
A2: Factores sobre el EBITDA incremental y el CAPEX + TMAR distinta, con formulas completas (el tornado parametrico detallado vive en la pagina Finanzas del dashboard).
A4: escenario | B4: factor ventas/beneficio | C4: factor CAPEX | D4: TMAR anual | E4: VPN (COP) | F4: TIR anual
A5: Conservador | B5: 0.95 | C5: 1.15 | D5: 0.2 | E5: =SUM(B11:BI11) -> 8014994753 | F5: =(1+IRR(B10:BI10,0.02))^12-1 -> 0.59806155
A6: Base | B6: 1 | C6: 1 | D6: 0.18 | E6: =SUM(B16:BI16) -> 11032069063 | F6: =(1+IRR(B15:BI15,0.02))^12-1 -> 0.78159428
A7: Optimista | B7: 1.05 | C7: 0.9 | D7: 0.16 | E7: =SUM(B21:BI21) -> 13751069360 | F7: =(1+IRR(B20:BI20,0.02))^12-1 -> 0.95882509
A10: Conservador — FCF ajustado | B10: {=-INDEX(CAPEX!$G:$G,MATCH("CAPEX TOTAL (con contingencia)",CAPEX!$C:$C,0))*$C$5*Parametros!$B$28-INDEX(RRHH!$E:$E,MATCH("Costo mensual IMPLEMENTACION (→ pre-op)",RRHH!$A:$A,0))-Licencias!$H$14} -> -2195239236 | C10: {=-INDEX(CAPEX!$G:$G,MATCH("CAPEX TOTAL (con contingencia)",CAPEX!$C:$C,0))*$C$5*Parametros!$B$29-INDEX(RRHH!$E:$E,MATCH("Costo mensual IMPLEMENTACION (→ pre-op)",RRHH!$A:$A,0))-Licencias!$H$14} -> -3776297344 | D10: {=-INDEX(CAPEX!$G:$G,MATCH("CAPEX TOTAL (con contingencia)",CAPEX!$C:$C,0))*$C$5*Parametros!$B$30-INDEX(RRHH!$E:$E,MATCH("Costo mensual IMPLEMENTACION (→ pre-op)",RRHH!$A:$A,0))-Licencias!$H$14} -> -2933066353 | E10: {=-INDEX(CAPEX!$G:$G,MATCH("CAPEX TOTAL (con contingencia)",CAPEX!$C:$C,0))*$C$5*Parametros!$B$31-INDEX(RRHH!$E:$E,MATCH("Costo mensual IMPLEMENTACION (→ pre-op)",RRHH!$A:$A,0))-Licencias!$H$14} -> -1984431489 | F10: =ER_Proyecto!F25*$B$5-MAX(0,ER_Proyecto!F25*$B$5-ER_Proyecto!F26)*Parametros!$B$8-Parametros!$B$16*(ER_Proyecto!$G$17-ER_Proyecto!$G$9)*$B$5 -> 2.3654437e+08 | G10: =ER_Proyecto!G25*$B$5-MAX(0,ER_Proyecto!G25*$B$5-ER_Proyecto!G26)*Parametros!$B$8 -> 512482178 | H10: =ER_Proyecto!H25*$B$5-MAX(0,ER_Proyecto!H25*$B$5-ER_Proyecto!H26)*Parametros!$B$8 -> 522709774 | I10: =ER_Proyecto!I25*$B$5-MAX(0,ER_Proyecto!I25*$B$5-ER_Proyecto!I26)*Parametros!$B$8 -> 5.4551197e+08 | J10: =ER_Proyecto!J25*$B$5-MAX(0,ER_Proyecto!J25*$B$5-ER_Proyecto!J26)*Parametros!$B$8 -> 6.2102378e+08 | K10: =ER_Proyecto!K25*$B$5-MAX(0,ER_Proyecto!K25*$B$5-ER_Proyecto!K26)*Parametros!$B$8 -> 5.2597047e+08 | L10: =ER_Proyecto!L25*$B$5-MAX(0,ER_Proyecto!L25*$B$5-ER_Proyecto!L26)*Parametros!$B$8 -> 4.9298036e+08 | M10: =ER_Proyecto!M25*$B$5-MAX(0,ER_Proyecto!M25*$B$5-ER_Proyecto!M26)*Parametros!$B$8 -> 5.419726e+08 | N10: =ER_Proyecto!N25*$B$5-MAX(0,ER_Proyecto!N25*$B$5-ER_Proyecto!N26)*Parametros!$B$8 -> 4.9690184e+08 | ... BH10: =ER_Proyecto!BH25*$B$5-MAX(0,ER_Proyecto!BH25*$B$5-ER_Proyecto!BH26)*Parametros!$B$8 -> 4.9298036e+08 | BI10: =ER_Proyecto!BI25*$B$5-MAX(0,ER_Proyecto!BI25*$B$5-ER_Proyecto!BI26)*Parametros!$B$8+Parametros!$B$16*(ER_Proyecto!$G$17-ER_Proyecto!$G$9)*$B$5 -> 6.6072009e+08
A11: FCF descontado | B11: =B10/((1+$D$5)^(1/12))^1 -> -2162138048 | C11: =C10/((1+$D$5)^(1/12))^2 -> -3663273200 | D11: =D10/((1+$D$5)^(1/12))^3 -> -2802377106 | E11: =E10/((1+$D$5)^(1/12))^4 -> -1867421528 | F11: =F10/((1+$D$5)^(1/12))^5 -> 2.1924033e+08 | G11: =G10/((1+$D$5)^(1/12))^6 -> 4.6783008e+08 | H11: =H10/((1+$D$5)^(1/12))^7 -> 4.6997154e+08 | I11: =I10/((1+$D$5)^(1/12))^8 -> 4.8307748e+08 | J11: =J10/((1+$D$5)^(1/12))^9 -> 5.4165442e+08 | K11: =K10/((1+$D$5)^(1/12))^10 -> 4.51832e+08 | L11: =L10/((1+$D$5)^(1/12))^11 -> 4.1710636e+08 | M11: =M10/((1+$D$5)^(1/12))^12 -> 4.5164383e+08 | N11: =N10/((1+$D$5)^(1/12))^13 -> 4.0784104e+08 | O11: =O10/((1+$D$5)^(1/12))^14 -> 4.1203045e+08 | P11: =P10/((1+$D$5)^(1/12))^15 -> 4.2033212e+08 | Q11: =Q10/((1+$D$5)^(1/12))^16 -> 4.3562776e+08 | R11: =R10/((1+$D$5)^(1/12))^17 -> 4.0401734e+08 | S11: =S10/((1+$D$5)^(1/12))^18 -> 3.898584e+08 | T11: =T10/((1+$D$5)^(1/12))^19 -> 3.9164295e+08 | U11: =U10/((1+$D$5)^(1/12))^20 -> 4.0256456e+08 | V11: =V10/((1+$D$5)^(1/12))^21 -> 451378687 | W11: =W10/((1+$D$5)^(1/12))^22 -> 3.7652667e+08 | X11: =X10/((1+$D$5)^(1/12))^23 -> 3.4758863e+08 | Y11: =Y10/((1+$D$5)^(1/12))^24 -> 3.7636986e+08 | Z11: =Z10/((1+$D$5)^(1/12))^25 -> 3.3986753e+08 | AA11: =AA10/((1+$D$5)^(1/12))^26 -> 3.4335871e+08 | AB11: =AB10/((1+$D$5)^(1/12))^27 -> 3.5027677e+08 | AC11: =AC10/((1+$D$5)^(1/12))^28 -> 363023133 | AD11: =AD10/((1+$D$5)^(1/12))^29 -> 3.3668112e+08 | AE11: =AE10/((1+$D$5)^(1/12))^30 -> 3.24882e+08 | AF11: =AF10/((1+$D$5)^(1/12))^31 -> 3.2636913e+08 | AG11: =AG10/((1+$D$5)^(1/12))^32 -> 3.3547047e+08 | AH11: =AH10/((1+$D$5)^(1/12))^33 -> 3.7614891e+08 | AI11: =AI10/((1+$D$5)^(1/12))^34 -> 3.1377222e+08 | AJ11: =AJ10/((1+$D$5)^(1/12))^35 -> 2.8965719e+08 | AK11: =AK10/((1+$D$5)^(1/12))^36 -> 3.1364155e+08 | AL11: =AL10/((1+$D$5)^(1/12))^37 -> 2.8322294e+08 | AM11: =AM10/((1+$D$5)^(1/12))^38 -> 2.8613226e+08 | AN11: =AN10/((1+$D$5)^(1/12))^39 -> 2.918973e+08 | AO11: =AO10/((1+$D$5)^(1/12))^40 -> 3.0251928e+08 | AP11: =AP10/((1+$D$5)^(1/12))^41 -> 2.805676e+08 | AQ11: =AQ10/((1+$D$5)^(1/12))^42 -> 2.70735e+08 | AR11: =AR10/((1+$D$5)^(1/12))^43 -> 2.7197427e+08 | AS11: =AS10/((1+$D$5)^(1/12))^44 -> 2.7955872e+08 | AT11: =AT10/((1+$D$5)^(1/12))^45 -> 3.1345742e+08 | AU11: =AU10/((1+$D$5)^(1/12))^46 -> 2.6147685e+08 | AV11: =AV10/((1+$D$5)^(1/12))^47 -> 2.4138099e+08 | AW11: =AW10/((1+$D$5)^(1/12))^48 -> 2.6136796e+08 | AX11: =AX10/((1+$D$5)^(1/12))^49 -> 2.3601912e+08 | AY11: =AY10/((1+$D$5)^(1/12))^50 -> 2.3844355e+08 | AZ11: =AZ10/((1+$D$5)^(1/12))^51 -> 2.4324775e+08 | BA11: =BA10/((1+$D$5)^(1/12))^52 -> 2.520994e+08 | BB11: =BB10/((1+$D$5)^(1/12))^53 -> 2.3380633e+08 | BC11: =BC10/((1+$D$5)^(1/12))^54 -> 225612501 | BD11: =BD10/((1+$D$5)^(1/12))^55 -> 2.2664523e+08 | BE11: =BE10/((1+$D$5)^(1/12))^56 -> 2.329656e+08 | BF11: =BF10/((1+$D$5)^(1/12))^57 -> 261214518 | BG11: =BG10/((1+$D$5)^(1/12))^58 -> 2.1789738e+08 | BH11: =BH10/((1+$D$5)^(1/12))^59 -> 2.0115083e+08 | BI11: =BI10/((1+$D$5)^(1/12))^60 -> 2.6552859e+08
A15: Base — FCF ajustado | B15: {=-INDEX(CAPEX!$G:$G,MATCH("CAPEX TOTAL (con contingencia)",CAPEX!$C:$C,0))*$C$6*Parametros!$B$28-INDEX(RRHH!$E:$E,MATCH("Costo mensual IMPLEMENTACION (→ pre-op)",RRHH!$A:$A,0))-Licencias!$H$14} -> -1920272609 | C15: {=-INDEX(CAPEX!$G:$G,MATCH("CAPEX TOTAL (con contingencia)",CAPEX!$C:$C,0))*$C$6*Parametros!$B$29-INDEX(RRHH!$E:$E,MATCH("Costo mensual IMPLEMENTACION (→ pre-op)",RRHH!$A:$A,0))-Licencias!$H$14} -> -3295105746 | D15: {=-INDEX(CAPEX!$G:$G,MATCH("CAPEX TOTAL (con contingencia)",CAPEX!$C:$C,0))*$C$6*Parametros!$B$30-INDEX(RRHH!$E:$E,MATCH("Costo mensual IMPLEMENTACION (→ pre-op)",RRHH!$A:$A,0))-Licencias!$H$14} -> -2561861406 | E15: {=-INDEX(CAPEX!$G:$G,MATCH("CAPEX TOTAL (con contingencia)",CAPEX!$C:$C,0))*$C$6*Parametros!$B$31-INDEX(RRHH!$E:$E,MATCH("Costo mensual IMPLEMENTACION (→ pre-op)",RRHH!$A:$A,0))-Licencias!$H$14} -> -1736961524 | F15: =ER_Proyecto!F25*$B$6-MAX(0,ER_Proyecto!F25*$B$6-ER_Proyecto!F26)*Parametros!$B$8-Parametros!$B$16*(ER_Proyecto!$G$17-ER_Proyecto!$G$9)*$B$6 -> 2.4724188e+08 | G15: =ER_Proyecto!G25*$B$6-MAX(0,ER_Proyecto!G25*$B$6-ER_Proyecto!G26)*Parametros!$B$8 -> 537702723 | H15: =ER_Proyecto!H25*$B$6-MAX(0,ER_Proyecto!H25*$B$6-ER_Proyecto!H26)*Parametros!$B$8 -> 5.4846861e+08 | I15: =ER_Proyecto!I25*$B$6-MAX(0,ER_Proyecto!I25*$B$6-ER_Proyecto!I26)*Parametros!$B$8 -> 5.7247093e+08 | J15: =ER_Proyecto!J25*$B$6-MAX(0,ER_Proyecto!J25*$B$6-ER_Proyecto!J26)*Parametros!$B$8 -> 6.5195704e+08 | K15: =ER_Proyecto!K25*$B$6-MAX(0,ER_Proyecto!K25*$B$6-ER_Proyecto!K26)*Parametros!$B$8 -> 551900924 | L15: =ER_Proyecto!L25*$B$6-MAX(0,ER_Proyecto!L25*$B$6-ER_Proyecto!L26)*Parametros!$B$8 -> 5.1717449e+08 | M15: =ER_Proyecto!M25*$B$6-MAX(0,ER_Proyecto!M25*$B$6-ER_Proyecto!M26)*Parametros!$B$8 -> 5.6874527e+08 | N15: =ER_Proyecto!N25*$B$6-MAX(0,ER_Proyecto!N25*$B$6-ER_Proyecto!N26)*Parametros!$B$8 -> 521302367 | ... BH15: =ER_Proyecto!BH25*$B$6-MAX(0,ER_Proyecto!BH25*$B$6-ER_Proyecto!BH26)*Parametros!$B$8 -> 5.1717449e+08 | BI15: =ER_Proyecto!BI25*$B$6-MAX(0,ER_Proyecto!BI25*$B$6-ER_Proyecto!BI26)*Parametros!$B$8+Parametros!$B$16*(ER_Proyecto!$G$17-ER_Proyecto!$G$9)*$B$6 -> 6.9374263e+08
A16: FCF descontado | B16: =B15/((1+$D$6)^(1/12))^1 -> -1893968361 | C16: =C15/((1+$D$6)^(1/12))^2 -> -3205450110 | D16: =D15/((1+$D$6)^(1/12))^3 -> -2458018399 | E16: =E15/((1+$D$6)^(1/12))^4 -> -1643726396 | F16: =F15/((1+$D$6)^(1/12))^5 -> 2.3076567e+08 | G16: =G15/((1+$D$6)^(1/12))^6 -> 4.9499548e+08 | H16: =H15/((1+$D$6)^(1/12))^7 -> 4.9798999e+08 | I16: =I15/((1+$D$6)^(1/12))^8 -> 5.1266314e+08 | J16: =J15/((1+$D$6)^(1/12))^9 -> 5.7584748e+08 | K16: =K15/((1+$D$6)^(1/12))^10 -> 4.8079445e+08 | L16: =L15/((1+$D$6)^(1/12))^11 -> 4.4437054e+08 | M16: =M15/((1+$D$6)^(1/12))^12 -> 4.8198752e+08 | N16: =N15/((1+$D$6)^(1/12))^13 -> 4.3573006e+08 | O16: =O15/((1+$D$6)^(1/12))^14 -> 4.4086012e+08 | P16: =P15/((1+$D$6)^(1/12))^15 -> 4.5042396e+08 | Q16: =Q15/((1+$D$6)^(1/12))^16 -> 4.6754233e+08 | R16: =R15/((1+$D$6)^(1/12))^17 -> 4.3414295e+08 | S16: =S15/((1+$D$6)^(1/12))^18 -> 4.1948769e+08 | T16: =T15/((1+$D$6)^(1/12))^19 -> 4.2202541e+08 | U16: =U15/((1+$D$6)^(1/12))^20 -> 4.3446029e+08 | V16: =V15/((1+$D$6)^(1/12))^21 -> 4.8800634e+08 | W16: =W15/((1+$D$6)^(1/12))^22 -> 4.0745293e+08 | X16: =X15/((1+$D$6)^(1/12))^23 -> 3.765852e+08 | Y16: =Y15/((1+$D$6)^(1/12))^24 -> 408463997 | Z16: =Z15/((1+$D$6)^(1/12))^25 -> 369262763 | AA16: =AA15/((1+$D$6)^(1/12))^26 -> 3.7361027e+08 | AB16: =AB15/((1+$D$6)^(1/12))^27 -> 3.8171522e+08 | AC16: =AC15/((1+$D$6)^(1/12))^28 -> 3.9622231e+08 | AD16: =AD15/((1+$D$6)^(1/12))^29 -> 3.6791776e+08 | AE16: =AE15/((1+$D$6)^(1/12))^30 -> 3.5549805e+08 | AF16: =AF15/((1+$D$6)^(1/12))^31 -> 3.5764865e+08 | AG16: =AG15/((1+$D$6)^(1/12))^32 -> 3.6818669e+08 | AH16: =AH15/((1+$D$6)^(1/12))^33 -> 4.135647e+08 | AI16: =AI15/((1+$D$6)^(1/12))^34 -> 345299090 | AJ16: =AJ15/((1+$D$6)^(1/12))^35 -> 3.1914e+08 | AK16: =AK15/((1+$D$6)^(1/12))^36 -> 3.4615593e+08 | AL16: =AL15/((1+$D$6)^(1/12))^37 -> 3.1293454e+08 | AM16: =AM15/((1+$D$6)^(1/12))^38 -> 3.1661887e+08 | AN16: =AN15/((1+$D$6)^(1/12))^39 -> 3.2348747e+08 | AO16: =AO15/((1+$D$6)^(1/12))^40 -> 3.3578162e+08 | AP16: =AP15/((1+$D$6)^(1/12))^41 -> 3.1179471e+08 | AQ16: =AQ15/((1+$D$6)^(1/12))^42 -> 3.0126953e+08 | AR16: =AR15/((1+$D$6)^(1/12))^43 -> 3.0309208e+08 | AS16: =AS15/((1+$D$6)^(1/12))^44 -> 3.1202262e+08 | AT16: =AT15/((1+$D$6)^(1/12))^45 -> 3.5047856e+08 | AU16: =AU15/((1+$D$6)^(1/12))^46 -> 2.9262635e+08 | AV16: =AV15/((1+$D$6)^(1/12))^47 -> 2.7045763e+08 | AW16: =AW15/((1+$D$6)^(1/12))^48 -> 2.9335248e+08 | AX16: =AX15/((1+$D$6)^(1/12))^49 -> 2.6519877e+08 | AY16: =AY15/((1+$D$6)^(1/12))^50 -> 2.6832108e+08 | AZ16: =AZ15/((1+$D$6)^(1/12))^51 -> 274141925 | BA16: =BA15/((1+$D$6)^(1/12))^52 -> 2.8456069e+08 | BB16: =BB15/((1+$D$6)^(1/12))^53 -> 2.642328e+08 | BC16: =BC15/((1+$D$6)^(1/12))^54 -> 2.5531316e+08 | BD16: =BD15/((1+$D$6)^(1/12))^55 -> 2.5685769e+08 | BE16: =BE15/((1+$D$6)^(1/12))^56 -> 2.6442595e+08 | BF16: =BF15/((1+$D$6)^(1/12))^57 -> 297015726 | BG16: =BG15/((1+$D$6)^(1/12))^58 -> 247988430 | BH16: =BH15/((1+$D$6)^(1/12))^59 -> 2.2920138e+08 | BI16: =BI15/((1+$D$6)^(1/12))^60 -> 3.032413e+08
A20: Optimista — FCF ajustado | B20: {=-INDEX(CAPEX!$G:$G,MATCH("CAPEX TOTAL (con contingencia)",CAPEX!$C:$C,0))*$C$7*Parametros!$B$28-INDEX(RRHH!$E:$E,MATCH("Costo mensual IMPLEMENTACION (→ pre-op)",RRHH!$A:$A,0))-Licencias!$H$14} -> -1736961524 | C20: {=-INDEX(CAPEX!$G:$G,MATCH("CAPEX TOTAL (con contingencia)",CAPEX!$C:$C,0))*$C$7*Parametros!$B$29-INDEX(RRHH!$E:$E,MATCH("Costo mensual IMPLEMENTACION (→ pre-op)",RRHH!$A:$A,0))-Licencias!$H$14} -> -2974311347 | D20: {=-INDEX(CAPEX!$G:$G,MATCH("CAPEX TOTAL (con contingencia)",CAPEX!$C:$C,0))*$C$7*Parametros!$B$30-INDEX(RRHH!$E:$E,MATCH("Costo mensual IMPLEMENTACION (→ pre-op)",RRHH!$A:$A,0))-Licencias!$H$14} -> -2314391442 | E20: {=-INDEX(CAPEX!$G:$G,MATCH("CAPEX TOTAL (con contingencia)",CAPEX!$C:$C,0))*$C$7*Parametros!$B$31-INDEX(RRHH!$E:$E,MATCH("Costo mensual IMPLEMENTACION (→ pre-op)",RRHH!$A:$A,0))-Licencias!$H$14} -> -1571981548 | F20: =ER_Proyecto!F25*$B$7-MAX(0,ER_Proyecto!F25*$B$7-ER_Proyecto!F26)*Parametros!$B$8-Parametros!$B$16*(ER_Proyecto!$G$17-ER_Proyecto!$G$9)*$B$7 -> 2.5793938e+08 | G20: =ER_Proyecto!G25*$B$7-MAX(0,ER_Proyecto!G25*$B$7-ER_Proyecto!G26)*Parametros!$B$8 -> 562923268 | H20: =ER_Proyecto!H25*$B$7-MAX(0,ER_Proyecto!H25*$B$7-ER_Proyecto!H26)*Parametros!$B$8 -> 574227453 | I20: =ER_Proyecto!I25*$B$7-MAX(0,ER_Proyecto!I25*$B$7-ER_Proyecto!I26)*Parametros!$B$8 -> 5.9942988e+08 | J20: =ER_Proyecto!J25*$B$7-MAX(0,ER_Proyecto!J25*$B$7-ER_Proyecto!J26)*Parametros!$B$8 -> 6.828903e+08 | K20: =ER_Proyecto!K25*$B$7-MAX(0,ER_Proyecto!K25*$B$7-ER_Proyecto!K26)*Parametros!$B$8 -> 577831379 | L20: =ER_Proyecto!L25*$B$7-MAX(0,ER_Proyecto!L25*$B$7-ER_Proyecto!L26)*Parametros!$B$8 -> 541368626 | M20: =ER_Proyecto!M25*$B$7-MAX(0,ER_Proyecto!M25*$B$7-ER_Proyecto!M26)*Parametros!$B$8 -> 5.9551794e+08 | N20: =ER_Proyecto!N25*$B$7-MAX(0,ER_Proyecto!N25*$B$7-ER_Proyecto!N26)*Parametros!$B$8 -> 5.4570289e+08 | ... BH20: =ER_Proyecto!BH25*$B$7-MAX(0,ER_Proyecto!BH25*$B$7-ER_Proyecto!BH26)*Parametros!$B$8 -> 541368626 | BI20: =ER_Proyecto!BI25*$B$7-MAX(0,ER_Proyecto!BI25*$B$7-ER_Proyecto!BI26)*Parametros!$B$8+Parametros!$B$16*(ER_Proyecto!$G$17-ER_Proyecto!$G$9)*$B$7 -> 7.2676517e+08
A21: FCF descontado | B21: =B20/((1+$D$7)^(1/12))^1 -> -1715610515 | C21: =C20/((1+$D$7)^(1/12))^2 -> -2901639334 | D21: =D20/((1+$D$7)^(1/12))^3 -> -2230089626 | E21: =E20/((1+$D$7)^(1/12))^4 -> -1496102840 | F21: =F20/((1+$D$7)^(1/12))^5 -> 2.424712e+08 | G21: =G20/((1+$D$7)^(1/12))^6 -> 5.2266113e+08 | H21: =H20/((1+$D$7)^(1/12))^7 -> 5.2660316e+08 | I21: =I20/((1+$D$7)^(1/12))^8 -> 5.429582e+08 | J21: =J20/((1+$D$7)^(1/12))^9 -> 6.1095251e+08 | K21: =K20/((1+$D$7)^(1/12))^10 -> 5.1060626e+08 | L21: =L20/((1+$D$7)^(1/12))^11 -> 4.725052e+08 | M21: =M20/((1+$D$7)^(1/12))^12 -> 513377536 | N21: =N20/((1+$D$7)^(1/12))^13 -> 4.6465089e+08 | O21: =O20/((1+$D$7)^(1/12))^14 -> 470827778 | P21: =P20/((1+$D$7)^(1/12))^15 -> 481777087 | Q21: =Q20/((1+$D$7)^(1/12))^16 -> 5.0087153e+08 | R21: =R20/((1+$D$7)^(1/12))^17 -> 4.6567529e+08 | S21: =S20/((1+$D$7)^(1/12))^18 -> 4.5056994e+08 | T21: =T20/((1+$D$7)^(1/12))^19 -> 4.5396824e+08 | U21: =U20/((1+$D$7)^(1/12))^20 -> 4.6806741e+08 | V21: =V20/((1+$D$7)^(1/12))^21 -> 5.266832e+08 | W21: =W20/((1+$D$7)^(1/12))^22 -> 4.4017781e+08 | X21: =X20/((1+$D$7)^(1/12))^23 -> 4.0733207e+08 | Y21: =Y20/((1+$D$7)^(1/12))^24 -> 4.4256684e+08 | Z21: =Z20/((1+$D$7)^(1/12))^25 -> 4.0056111e+08 | AA21: =AA20/((1+$D$7)^(1/12))^26 -> 4.0588602e+08 | AB21: =AB20/((1+$D$7)^(1/12))^27 -> 415325075 | AC21: =AC20/((1+$D$7)^(1/12))^28 -> 4.317858e+08 | AD21: =AD20/((1+$D$7)^(1/12))^29 -> 4.0144422e+08 | AE21: =AE20/((1+$D$7)^(1/12))^30 -> 3.8842236e+08 | AF21: =AF20/((1+$D$7)^(1/12))^31 -> 3.9135193e+08 | AG21: =AG20/((1+$D$7)^(1/12))^32 -> 4.0350639e+08 | AH21: =AH20/((1+$D$7)^(1/12))^33 -> 4.5403724e+08 | AI21: =AI20/((1+$D$7)^(1/12))^34 -> 3.7946363e+08 | AJ21: =AJ20/((1+$D$7)^(1/12))^35 -> 3.5114834e+08 | AK21: =AK20/((1+$D$7)^(1/12))^36 -> 3.8152314e+08 | AL21: =AL20/((1+$D$7)^(1/12))^37 -> 3.453113e+08 | AM21: =AM20/((1+$D$7)^(1/12))^38 -> 3.4990174e+08 | AN21: =AN20/((1+$D$7)^(1/12))^39 -> 3.5803886e+08 | AO21: =AO20/((1+$D$7)^(1/12))^40 -> 3.7222914e+08 | AP21: =AP20/((1+$D$7)^(1/12))^41 -> 3.460726e+08 | AQ21: =AQ20/((1+$D$7)^(1/12))^42 -> 3.3484687e+08 | AR21: =AR20/((1+$D$7)^(1/12))^43 -> 3.3737235e+08 | AS21: =AS20/((1+$D$7)^(1/12))^44 -> 3.4785034e+08 | AT21: =AT20/((1+$D$7)^(1/12))^45 -> 3.9141141e+08 | AU21: =AU20/((1+$D$7)^(1/12))^46 -> 327123816 | AV21: =AV20/((1+$D$7)^(1/12))^47 -> 3.0271408e+08 | AW21: =AW20/((1+$D$7)^(1/12))^48 -> 3.2889926e+08 | AX21: =AX20/((1+$D$7)^(1/12))^49 -> 2.9768216e+08 | AY21: =AY20/((1+$D$7)^(1/12))^50 -> 3.0163943e+08 | AZ21: =AZ20/((1+$D$7)^(1/12))^51 -> 3.0865419e+08 | BA21: =BA20/((1+$D$7)^(1/12))^52 -> 320887188 | BB21: =BB20/((1+$D$7)^(1/12))^53 -> 2.9833845e+08 | BC21: =BC20/((1+$D$7)^(1/12))^54 -> 288661091 | BD21: =BD20/((1+$D$7)^(1/12))^55 -> 2.9083824e+08 | BE21: =BE20/((1+$D$7)^(1/12))^56 -> 299870980 | BF21: =BF20/((1+$D$7)^(1/12))^57 -> 3.3742363e+08 | BG21: =BG20/((1+$D$7)^(1/12))^58 -> 2.8200329e+08 | BH21: =BH20/((1+$D$7)^(1/12))^59 -> 2.6096042e+08 | BI21: =BI20/((1+$D$7)^(1/12))^60 -> 3.4602236e+08
A24: TORNADO PARAMÉTRICO — margen bruto anual (escenario Base)
A25: Margen base: $297,851,331,711 COP. Cada parámetro se perturba individualmente entre su cota baja y alta manteniendo el resto en el valor base — el ranking indica dónde vale la pena invertir en mejor información (recalculado con `core/sensibilidad.py: tornado()`, snapshot al publicar; el interactivo vive en la página Finanzas del dashboard).
A26: parámetro | B26: cota baja→alta | C26: margen bajo (COP) | D26: margen alto (COP) | E26: Δ% bajo | F26: Δ% alto
A27: Precio de venta | C27: $270,288,932,361 | D27: $325,413,731,061 | E27: -9.25% | F27: +9.25%
A28: Costo de materiales | C28: $323,190,997,240 | D28: $272,511,666,182 | E28: +8.51% | F28: -8.51%
A29: OEE (+/-5 pts sobre ~77%) | C29: $278,555,538,566 | D29: $317,147,124,856 | E29: -6.48% | F29: +6.48%
A30: Participacion planta Bogota | C30: $297,752,034,148 | D30: $297,950,629,274 | E30: -0.03% | F30: +0.03%
A31: Participacion SKU en categoria | C31: $297,752,034,148 | D31: $297,950,629,274 | E31: -0.03% | F31: +0.03%
A32: Demanda sostenida (factor) | C32: $297,801,682,929 | D32: $297,900,980,493 | E32: -0.02% | F32: +0.02%
A34: ESCENARIOS DE PRONÓSTICO — cómo se propagan por el ERP
A35: Los 6 escenarios (`core/escenarios.py`) aplican factores multiplicativos mes a mes POR PRODUCTO sobre el pronóstico estadístico base (Holt-Winters + Bates-Granger óptimo) — el modelo nunca se recalibra, solo se escala. Se activan en la página *Escenarios* del dashboard (botón 'Activar'), y desde ahí la demanda del escenario elegido reemplaza a la Base en TODO el resto de la suite hasta que se vuelva a cambiar:
A36: ① Inventario / MRP (página *Inventario*): política (s,Q) y plan de compras se recalculan con la nueva demanda; la sección 'Capacidad y factibilidad de producción' muestra si cada línea sigue siendo factible con los turnos actuales.
A37: ② Compras (página *Órdenes Odoo*): el plan MRP que se convierte en purchase.order/mrp.production usa la demanda del escenario activo.
A38: ③ Finanzas (página *Finanzas*): el caso de negocio (VPN/TIR/ROI/payback) se recalcula para el escenario activo y se compara contra Base en la misma pantalla.
A39: ④ Sheets: al activar, la demanda del escenario se publica a la hoja `DemandaEscenario` (rango fijo A4:F16) — las hojas `FinancieroEscenario` y esta misma `Sensibilidad` (filas 1-21, arriba) leen de ahí.
A41: escenario | B41: justificación | C41: fuente
A42: Base | B42: Pronostico oficial v4 sin ajuste (HW + Bates-Granger optimo). | C42: Scripts 01-04 del repositorio; backtest un-paso 5 trimestres.
A43: Mundial 2026 | B43: Plan comercial KOF para el Mundial FIFA (11-jun a 19-jul-2026). v4 diferencia formatos: el consumo personal/on-premise (P1, 350 ml) capta mas el evento que el familiar (P2, 1.5 L hogar); garrafon casi ajeno (r=0.12 con refrescos). | C43: Refs [12],[13],[20] del reporte; historico de torneos en reportes KOF.
A44: Paro nacional / choque logistico | B44: Disrupcion de transporte ~2 semanas (ilustrada en agosto): -18% en las tres lineas por dias de despacho perdidos; octubre recupera +4% por pedidos represados. | C44: Impacto reportado por KOF/ANDI en el paro nacional de 2021.
A45: Recesion moderada | B45: Caida de ingreso disponible desde junio. v4 diferencia por downtrading hacia retornables (asequibilidad KOF): P1 -3%, P2 -7% (blend ~-5% del escenario original); garrafon (bien basico) -2%. | C45: Elasticidades LatAm citadas en el reporte; estrategia de asequibilidad KOF.
A46: Restriccion hidrica adicional (CAR) | B46: Endurecimiento de la Resolucion CAR 347/2026 (La Calera): -15% sostenido en garrafon desde julio; P1/P2 sin efecto (acueducto, no manantial). | C46: Ref [12] del reporte; racionamiento EAAB 2024-2025.
A47: Repunte agresivo post-impuesto | B47: La recuperacion de refrescos tras el impuesto saludable (+9.2% interanual real en 1T-2026) se sostiene mas alla del modelo base (ya conservador, phi<1): +5% sostenido en P1 y P2. | C47: Ref [21] del reporte; Ley 2277/2022.

Sheet Dep_Amort
A1: Depreciacion y amortizacion lineal — FINANZAS
A2: Base = SUMIF de la hoja CAPEX por categoria (sin contingencia); vidas editables. El cargo inicia en el mes 5 (activos en servicio).
A4: categoria | B4: base depreciable COP | C4: vida (años) | D4: cargo mensual COP | E4: comentario
A5: equipos | B5: =SUMIF(CAPEX!$I$5:$I$140,"equipos",CAPEX!$G$5:$G$140) -> 4450224237 | C5: 10 | D5: =B5/(C5*12) -> 37085202 | E5: Retrofits, celdas roboticas y equipos fisicos
A6: automatizacion | B6: =SUMIF(CAPEX!$I$5:$I$140,"automatizacion",CAPEX!$G$5:$G$140) -> 2079929725 | C6: 7 | D6: =B6/(C6*12) -> 24761068 | E6: PLC, HMI, vision, sensores, red, edge
A7: servicios | B7: =SUMIF(CAPEX!$I$5:$I$140,"servicios",CAPEX!$G$5:$G$140) -> 1510829968 | C7: 5 | D7: =B7/(C7*12) -> 25180499 | E7: Ingenieria, FAT/SAT, EPC (capitalizables)
A8: intangibles | B8: =SUMIF(CAPEX!$I$5:$I$140,"intangibles",CAPEX!$G$5:$G$140) -> 179252096 | C8: 3 | D8: =B8/(C8*12) -> 4979224.9 | E8: Capacitacion y gestion del cambio
A9: software | B9: =SUMIF(CAPEX!$I$5:$I$140,"software",CAPEX!$G$5:$G$140) -> 112086015 | C9: 3 | D9: =B9/(C9*12) -> 3113500.4 | E9: Licencias perpetuas
A10: D&A TOTAL MENSUAL (→ ER) | D10: =SUM(D5:D9) -> 95119495

Sheet Inventarios
A1: Inventarios y rotacion — INVENTARIO
A2: Bloque 1: politica (s,Q) escrita por la APP desde el ERP (rango fijo A4:I8; pagina Inventario → simular). Bloque 2: rotacion con formulas sobre la demanda y Costos_Lote.
A4: ts | B4: escenario | C4: sku | D4: punto_reorden_s | E4: stock_seguridad | F4: lote_Q | G4: pallets_por_lote | H4: fill_rate | I4: capital_inmovilizado_cop
A5: 2026-07-12T14:10:33+00:00 | B5: Base | C5: P2-QT1500-PET | D5: 1448132 | E5: 120855 | F5: 254520 | G5: 303 | H5: 0.9926578 | I5: 727280916
A6: (pendiente) | B6: — | C6: P3-GARR25L | D6: — | E6: — | F6: — | G6: — | H6: — | I6: —
A7: 2026-07-14T07:18:34.321336+00:00 | B7: Base | C7: P1-CC350-RGB | D7: 2369423 | E7: 393851 | F7: 803520 | G7: 496 | H7: 0.99708301 | I7: 733673474
A10: ROTACION DE INVENTARIOS (año 1)
A11: sku | B11: unidades año 1 | C11: COGS anual COP | D11: inv. promedio (DIO) COP | E11: rotacion (veces/año) | F11: dias de inventario | G11: rotacion real (capital ERP)
A12: P1-CC350-RGB | B12: =SUM(Demanda!D5:D16) -> 188337814 | C12: =B12*Costos_Lote!$B$18 -> 174965829206 | D12: =C12*Parametros!$B$18/365 -> 8149093415 | E12: =C12/D12 -> 21.470588 | F12: =365/E12 -> 17 | G12: =IFERROR(C12/I5,"pendiente app") -> 240.57531
A13: P2-QT1500-PET | B13: =SUM(Demanda!E5:E16) -> 54228683 | C13: =B13*Costos_Lote!$B$33 -> 144790583610 | D13: =C13*Parametros!$B$18/365 -> 6743671017 | E13: =C13/D13 -> 21.470588 | F13: =365/E13 -> 17 | G13: =IFERROR(C13/I6,"pendiente app") -> pendiente app
A14: P3-GARR25L | B14: =SUM(Demanda!F5:F16) -> 279149 | C14: =B14*Costos_Lote!$B$46 -> 1938091629 | D14: =C14*Parametros!$B$18/365 -> 90267281 | E14: =C14/D14 -> 21.470588 | F14: =365/E14 -> 17 | G14: =IFERROR(C14/I7,"pendiente app") -> 2.641627
A15: TOTAL portafolio | B15: =SUM(B12:B14) -> 242845646 | C15: =SUM(C12:C14) -> 321694504445 | D15: =SUM(D12:D14) -> 14983031714 | E15: =C15/D15 -> 21.470588 | F15: =365/E15 -> 17

Sheet Tiempos
A1: ESTUDIO DE TIEMPOS Y OEE — PLANTA KOF FONTIBÓN (CORREGIDO Y CONSOLIDADO) — DOCUMENTAL
A2: Fuente: Tiempos_Fontibon_Corregido.xlsx (auditoría APM, 8 hallazgos corregidos, ver Bloque 2). DOCUMENTAL: no está conectado al ERP en vivo — es referencia de ingeniería para el diseño del equipo. Los KPIs VIVOS de OEE/TEEP NO se gestionan en el ERP: llegan por MQTT según el UNS (FEMSA/+/MES/KPI/#) y se consultan en las páginas Producción MQTT y Base de datos (tabla kpi_uns). Consolidada 2026-07: esta hoja reemplaza a Tiempos + OEE_TEEP (redundante, borrada) — todo el contenido queda en un solo lugar.
A4: BLOQUE 1 · MEMORIA — METODOLOGÍA Y HALLAZGOS CLAVE
A5: CÁLCULO DE TIEMPOS — PLANTA KOF FONTIBÓN (CORREGIDO) · Formulación APM (apuntes del curso)
A6: Líneas: L1 = Coca-Cola 350 ml vidrio retornable · L2 = QuAtro 1.5 L PET NR · L3 = Garrafón 25 L. Demanda: pronóstico abr-2026→mar-2027 del proyecto.
A7: ■ Fuentes de las tasas nominales (Rp máquina)
A8: L1: 40.000–45.000 bph observados en visita técnica (se usa 42.500 central, rango en sensibilidad). L2: llenadora KRONES usada ~2004 tipo monoblock (referencias de mercado de usados equivalentes a los enlaces suministrados): 12.000 bph en botella 1,5 L (14.000 en 0,5 L). L3: no hay dato de planta; se adopta línea industrial de garrafón 3–5 gal tipo QGF-600 → 600 gfn/h (familia QGF: 100–1.200 bph; QGF-900 = 6 válvulas, 900 bph).
A9: ■ OEE bottom-up (no calibrado)
A10: El OEE se CONSTRUYE por línea desde los datos del sistema y el 75–78 % de la visita se usa solo como VALIDACIÓN: A = Ter/Tep con Tip=70 min (alistamiento+saneamiento, visita) y Tnp por línea (protocolo de fallas de la visita); SE = Rp real/Rp de diseño (L1: 40.000 del EBI / 42.500 de la llenadora = 94,1 %; L2: 12.000/13.000 usado; L3: 600/650); RE desde microparos medibles (reacción 5 min, chequeos horarios → 15–30 min/turno); Q = 99,93 % (archivo original). El OEE resultante cae por sí solo en el rango observado — fila de validación explícita.
A11: ■ Tiempos de la visita usados
A12: Alistamiento Tsu = 1 h + saneamiento 10 min = 70 min por corrida (notas de visita, línea PET). Cambio de producto 1 h (1 h 10 en L3-PET). Monitoreo de paneles cada 1 h; ante falla se detiene y se revisa la producción 1 h antes y 1 h después (usado en el bloque MTBF/MTTR ilustrativo).
A13: ■ Qué se corrigió del archivo original
... A24: BLOQUE 2 · CORRECCIONES — AUDITORÍA DEL ARCHIVO ORIGINAL (8 hallazgos)
A25: Hallazgo | B25: En el archivo original | C25: Corrección aplicada aquí
A26: 1. Takt ≠ Tiempo de ciclo | B26: Fila 'Tack Time = Tiempo ciclo' y SE calculado con Takt=Tc (SE=B9/B32). | C26: Takt = T_D/D depende de la DEMANDA (apuntes); Tc = 3600/Rp depende de la MÁQUINA. Se calculan por separado y se comparan (holgura Takt−Tc).
A27: 2. Tasas sin soporte | B27: 350 ml a 50.000 bph; '1L' con 40.000 y 60.000 en hojas distintas; garrafón '60 L/hora' (≈2,4 gfn/h, imposible). | C27: L1=42.500 bph (visita 40–45 k); L2=12.000 bph (KRONES usada 2004, refs. de mercado); L3=600 gfn/h (QGF-600). Fuente en comentario de cada celda.
A28: 3. RE = 1,10 > 1 | B28: Volumen real supuesto = objetivo y Tc inflado ×1,1 → RE imposible (>1). | C28: RE = (Vol.real×Tc)/Ter con Vol.real medido u objetivo×OEE; aquí PE=RE·SE se calibra al OEE observado (75–78 %) y RE≤1 por construcción.
A29: 4. SE = 0,8 'porque sí' | B29: Celda K8: 'Porque si'. | C29: SE = Tc diseñado/Tc real (apuntes). Con línea sincronizada al cuello, SE se estima de la razón velocidad real/nominal; queda editable y documentado.
A30: 5. Sin TEEP | B30: No existe. | C30: Hoja OEE_TEEP: TEEP = OEE × Carga calendario, por línea y escenario de turnos.
A31: 6. Sin vínculo a demanda | B31: Botellas/turno arbitrarias (210.000; 100.000; 5.000). | C31: Demanda = pronóstico del proyecto (abr-26→mar-27): Takt promedio y de mes pico (dic-26); PC vs demanda → Utilización U.
A32: 7. Sin Tb, Tp, MLT | B32: Fórmulas de lote y lead time ausentes. | C32: Tb=Tsu+Q·Tc; Tp=Tb/Q; Rp=60/Tp; MLT=Tsu(max)+Σ(Tci+Tnoi)+(Q−1)·Tc_n con estaciones reales (paletizado manual incluido).
A33: 8. Horas útiles fijas 7 h sin trazar | B33: Horas útiles' = 7 sin descomponer. | C33: Tt→Tip→Tep→Tnp→Ter explícitos (8,0−1,0=7,0; −0,75→6,25 h) → A=89,3 %, consistente con OEE 76,5 % de la visita.
A35: BLOQUE 3 · ANTES DEL PROYECTO — PARÁMETROS Y TIEMPOS BASE MEDIDOS (fórmulas APM: Tc/T_D/Takt/Q/Tb/Tp/Rp_lote/MLT/capacidad)
A36: linea | B36: producto | C36: rp_nominal_uph | D36: rp_diseno_uph | E36: ciclo_Tc_s | F36: turnos | G36: horas_turno | H36: dias_operativos_ano | I36: tsu_alistamiento_min | J36: q_lote_turno_und | K36: pallets_por_lote | L36: unidades_por_pallet | M36: tb_lote_h | N36: tp_s_por_und | O36: rp_lote_uph | P36: mlt_lote_h | Q36: capacidad_efectiva_anual_und
A37: L1 | B37: Coca-Cola 350 ml vidrio retornable | C37: 42500 | D37: 45000 | E37: =3600/C37 -> 0.084705882 | F37: 2 | G37: 8 | H37: 286 | I37: 70 | J37: =K37*L37 -> 262440 | K37: 162 | L37: 1620 | M37: =I37/60+J37*E37/3600 -> 7.3417255 | N37: =M37*3600/J37 -> 0.10070954 | O37: =3600/N37 -> 35746.365 | P37: =B56 -> 16.983536 | Q37: =C37*F37*G37*H37*H83 -> 1.4997288e+08
A38: L2 | B38: QuAtro 1.5 L PET NR | C38: 12000 | D38: 13000 | E38: =3600/C38 -> 0.3 | F38: 2 | G38: 8 | H38: 286 | I38: 70 | J38: =K38*L38 -> 73080 | K38: 87 | L38: 840 | M38: =I38/60+J38*E38/3600 -> 7.2566667 | N38: =M38*3600/J38 -> 0.35747126 | O38: =3600/N38 -> 10070.74 | P38: =B69 -> 19.258142 | Q38: =C38*F38*G38*H38*H84 -> 42005034
A39: L3 | B39: Garrafon 25 L retornable | C39: 480 | D39: 520 | E39: =3600/C39 -> 7.5 | F39: 1 | G39: 8 | H39: 120 | I39: 70 | J39: =K39*L39 -> 2880 | K39: 96 | L39: 30 | M39: =I39/60+J39*E39/3600 -> 7.1666667 | N39: =M39*3600/J39 -> 8.9583333 | O39: =3600/N39 -> 401.86047 | P39: =B79 -> 15.573906 | Q39: =C39*F39*G39*H39*H85 -> 347305.57
A40: Nota L3: cuello real es el paletizado MANUAL (2 operarios x 240 gfn/h), no la llenadora (600 gfn/h) — la celda robótica elimina ese cuello.
A42: BLOQUE 4 · MLT / VSM POR LÍNEA (Value Stream Map estación-por-estación) — MLT = Tsu(max) + Σ(Tc_i+Tno_i) + (Q−1)·Tc_cuello
A43: MLT = Tsu(max) + Σ(Tc_i + Tno_i) + (Q−1)·Tc_cuello — sobre la base de los VSM del proyecto
A44: Tc_i y disponibilidades por estación: VSM Línea 2 (330 mL→L1), VSM Línea 3 (1L-2L→L2), VSM Línea 7 (20L→L3). Tno_i = esperas de inventario del VSM (h→s). Q = lote de un turno. En L3 el paletizado es MANUAL (25 kg/gfn) y es la estación crítica.
A45: L1 · CC 350 (base VSM Línea 2)
A46: Estación (VSM) | B46: Tc_i (s) | C46: Disp. VSM | D46: Tno_i (h) | E46: Tno_i (s)
A47: Recepción | B47: 0.7 | C47: 0.97 | D47: 1.6 | E47: =D47*3600 -> 5760
A48: Lavado | B48: 0.8 | C48: 0.9 | D48: 1.28 | E48: =D48*3600 -> 4608
A49: Mezclado | B49: 0.6 | C49: 0.95 | D49: 0.96 | E49: =D49*3600 -> 3456
A50: Llenado | B50: 0.576 | C50: 0.92 | D50: 0.64 | E50: =D50*3600 -> 2304
A51: Tapado | B51: 0.576 | C51: 0.94 | D51: 0.64 | E51: =D51*3600 -> 2304
A52: Etiquetado | B52: 0.65 | C52: 0.95 | D52: 0.96 | E52: =D52*3600 -> 3456
A53: Inspección (HEUFT PRIME reasignada) | B53: 0.6 | C53: 0.93 | D53: 0.96 | E53: =D53*3600 -> 3456
A54: Paletizado manual | B54: 1.2 | C54: 0.93 | D54: 1 | E54: =D54*3600 -> 3600
A55: Almacenaje | B55: 0.9 | C55: 0.98 | D55: 1.6 | E55: =D55*3600 -> 5760
A56: MLT del lote-turno (h) | B56: =(I37*60+SUM(B47:B55)+SUM(E47:E55)+(J37-1)*E37)/3600 -> 16.983536 | F56: Alistamiento + paso por estaciones + esperas VSM + corrida del lote. Nota: en L3 el Tc del VSM del paletizado (4 s) se corrige a 15 s por la realidad manual de 25 kg — indicación del proyecto.
A57: L2 · QuAtro 1.5 (base VSM Línea 3)
A58: Estación (VSM) | B58: Tc_i (s) | C58: Disp. VSM | D58: Tno_i (h) | E58: Tno_i (s)
A59: Recepción preformas | B59: 0.7 | C59: 0.97 | D59: 2 | E59: =D59*3600 -> 7200
A60: Soplado | B60: 0.5 | C60: 0.93 | D60: 1.33 | E60: =D60*3600 -> 4788
A61: Enjuague | B61: 0.5 | C61: 0.95 | D61: 1.2 | E61: =D61*3600 -> 4320
A62: Mezclado | B62: 0.5 | C62: 0.95 | D62: 1.07 | E62: =D62*3600 -> 3852
A63: Llenado | B63: 0.48 | C63: 0.92 | D63: 0.8 | E63: =D63*3600 -> 2880
A64: Tapado | B64: 0.48 | C64: 0.94 | D64: 0.8 | E64: =D64*3600 -> 2880
A65: Etiquetado | B65: 0.65 | C65: 0.96 | D65: 0.8 | E65: =D65*3600 -> 2880
A66: Inspección (Linatronic reasignada) | B66: 0.6 | C66: 0.96 | D66: 1.07 | E66: =D66*3600 -> 3852
A67: Paletizado manual | B67: 1 | C67: 0.93 | D67: 1.33 | E67: =D67*3600 -> 4788
A68: Almacenaje | B68: 0.2 | C68: 0.98 | D68: 1.6 | E68: =D68*3600 -> 5760
A69: MLT del lote-turno (h) | B69: =(I38*60+SUM(B59:B68)+SUM(E59:E68)+(J38-1)*E38)/3600 -> 19.258142 | F69: Alistamiento + paso por estaciones + esperas VSM + corrida del lote. Nota: en L3 el Tc del VSM del paletizado (4 s) se corrige a 15 s por la realidad manual de 25 kg — indicación del proyecto.
A70: L3 · Garrafón (base VSM Línea 7)
A71: Estación (VSM) | B71: Tc_i (s) | C71: Disp. VSM | D71: Tno_i (h) | E71: Tno_i (s)
A72: Recepción | B72: 3.5 | C72: 0.97 | D72: 1.6 | E72: =D72*3600 -> 5760
A73: Lavado | B73: 3.2 | C73: 0.93 | D73: 1.2 | E73: =D73*3600 -> 4320
A74: Llenado | B74: 2.88 | C74: 0.92 | D74: 0.8 | E74: =D74*3600 -> 2880
A75: Tapado | B75: 2.88 | C75: 0.94 | D75: 0.8 | E75: =D75*3600 -> 2880
A76: Inspección | B76: 3.1 | C76: 0.96 | D76: 1.2 | E76: =D76*3600 -> 4320
A77: PALETIZADO MANUAL 25 kg (crítica) | B77: 15 | C77: 0.93 | D77: 1.2 | E77: =D77*3600 -> 4320
A78: Almacenaje | B78: 3 | C78: 0.98 | D78: 1.6 | E78: =D78*3600 -> 5760
A79: MLT del lote-turno (h) | B79: =(I39*60+SUM(B72:B78)+SUM(E72:E78)+(J39-1)*E39)/3600 -> 15.573906 | F79: Alistamiento + paso por estaciones + esperas VSM + corrida del lote. Nota: en L3 el Tc del VSM del paletizado (4 s) se corrige a 15 s por la realidad manual de 25 kg — indicación del proyecto.
A81: BLOQUE 5 · OEE BOTTOM-UP (base medido, valida 75-78% de la visita técnica) — A=Ter/Tep · SE=Rp_real/Rp_diseño · RE=microparos medidos · PE=RE×SE · Q=1−rechazo · OEE=A×PE×Q
A82: linea | B82: producto | C82: A_disponibilidad | D82: SE_tasa | E82: RE_microparos | F82: PE_desempeno | G82: Q_calidad | H82: oee_base | I82: carga_calendario | J82: teep | K82: tt_turno_h | L82: tip_parada_inherente_h | M82: tnp_parada_no_programada_h
A83: L1 | B83: Coca-Cola 350 ml vidrio retornable | C83: =(K83-L83-M83)/(K83-L83) -> 0.89024337 | D83: =C37/D37 -> 0.94444444 | E83: 0.9178 | F83: =D83*E83 -> 0.86681111 | G83: 0.99932 | H83: =C83*F83*G83 -> 0.7711481 | I83: =F37*G37*H37/(24*365) -> 0.52237443 | J83: =H83*I83 -> 0.40282805 | K83: 8 | L83: 1.1667 | M83: 0.75
A84: L2 | B84: QuAtro 1.5 L PET NR | C84: =(K84-L84-M84)/(K84-L84) -> 0.89024337 | D84: =C38/D38 -> 0.92307692 | E84: 0.9315 | F84: =D84*E84 -> 0.85984615 | G84: 0.99932 | H84: =C84*F84*G84 -> 0.76495181 | I84: =F38*G38*H38/(24*365) -> 0.52237443 | J84: =H84*I84 -> 0.39959127 | K84: 8 | L84: 1.1667 | M84: 0.75
A85: L3 | B85: Garrafon 25 L retornable | C85: =(K85-L85-M85)/(K85-L85) -> 0.89024337 | D85: =C39/D39 -> 0.92307692 | E85: 0.9178 | F85: =D85*E85 -> 0.8472 | G85: 0.99932 | H85: =C85*F85*G85 -> 0.75370131 | I85: =F39*G39*H39/(24*365) -> 0.10958904 | J85: =H85*I85 -> 0.082597404 | K85: 8 | L85: 1.1667 | M85: 0.75
A87: BLOQUE 6 · MEJORA DE OEE A IMPLEMENTAR — OBJETIVO ESTRICTO +5% RELATIVO (exacto por línea, no una cifra plana aproximada)
A88: oee_a_implementar = oee_base × 1.05 EXACTO para cada línea. El Δpp necesario varía por línea porque cada una parte de un OEE base distinto. Reparto 50% disponibilidad / 30% rendimiento / 20% calidad del Δpp exacto de cada línea (no 50/30/20 de una cifra fija repetida en las 3).
A89: linea | B89: oee_base | C89: oee_a_implementar | D89: mejora_total_pp | E89: mejora_disponibilidad_pp | F89: mejora_rendimiento_pp | G89: mejora_calidad_pp | H89: meta_programa_oee | I89: justificacion
A90: L1 | B90: =H83 -> 0.7711481 | C90: =B90*(105/100) -> 0.80970551 | D90: =(C90-B90)*100 -> 3.8557405 | E90: =D90*(50/100) -> 1.9278703 | F90: =D90*(30/100) -> 1.1567222 | G90: =D90*(20/100) -> 0.7711481 | H90: 0.86 | I90: +1.93pp A: celdas roboticas de paletizado eliminan microparos y bajan MTTR (UNS/MES) | +1.16pp SE/RE: retrofit de llenadoras | +0.77pp Q: reasignacion de inspectoras existentes HEUFT/Linatronic (capex-cero, ver Maquinas_Referencias) -- suma 3.856pp = exactamente +5% relativo (77.12% -> 80.97%)
A91: L2 | B91: =H84 -> 0.76495181 | C91: =B91*(105/100) -> 0.8031994 | D91: =(C91-B91)*100 -> 3.8247591 | E91: =D91*(50/100) -> 1.9123795 | F91: =D91*(30/100) -> 1.1474277 | G91: =D91*(20/100) -> 0.76495181 | H91: 0.86 | I91: +1.91pp A: celdas roboticas de paletizado eliminan microparos y bajan MTTR (UNS/MES) | +1.15pp SE/RE: retrofit de llenadoras | +0.76pp Q: reasignacion de inspectoras existentes HEUFT/Linatronic (capex-cero, ver Maquinas_Referencias) -- suma 3.825pp = exactamente +5% relativo (76.50% -> 80.32%)
A92: L3 | B92: =H85 -> 0.75370131 | C92: =B92*(105/100) -> 0.79138638 | D92: =(C92-B92)*100 -> 3.7685066 | E92: =D92*(50/100) -> 1.8842533 | F92: =D92*(30/100) -> 1.130552 | G92: =D92*(20/100) -> 0.75370131 | H92: 0.86 | I92: +1.88pp A: celdas roboticas de paletizado eliminan microparos y bajan MTTR (UNS/MES) | +1.13pp SE/RE: retrofit de llenadoras | +0.75pp Q: reasignacion de inspectoras existentes HEUFT/Linatronic (capex-cero, ver Maquinas_Referencias) -- suma 3.769pp = exactamente +5% relativo (75.37% -> 79.14%)
A93: Meta de programa (86%) es ASPIRACIONAL de largo plazo — distinta del +5% estricto del caso de negocio actual, no confundir ambas.
A95: CRONOGRAMA DE IMPLEMENTACIÓN (atado a las 4 fases de preoperación del CAPEX, core/finanzas_negocio.py: FASES_CAPEX)
A96: Fase | B96: Mes preop. | C96: % CAPEX fase | D96: Palanca | E96: Componente OEE | F96: Detalle
A97: 1 | B97: 1 | C97: 0.2 | D97: Ingenieria de detalle + pedidos de celdas roboticas y llenadoras | E97: — | F97: Sin ganancia de OEE aun -- fase de ingenieria/procura.
A98: 2 | B98: 2 | C98: 0.35 | D98: Instalacion y comisionamiento de celdas roboticas de paletizado (L1-L2/L3) | E98: disponibilidad | F98: Elimina microparos y esperas del paletizado manual; baja MTTR (monitoreable por UNS/MES) -> gana el componente de disponibilidad.
A99: 3 | B99: 3 | C99: 0.27 | D99: Cambio por llenadoras KRONES usadas en L1/L2; L3 conserva su llenadora | E99: rendimiento | F99: Estabiliza la velocidad real vs nominal (SE) y reduce microparos de llenado (RE) -> gana el componente de rendimiento.
A100: 4 | B100: 4 | C100: 0.18 | D100: Reasignacion de inspectoras existentes (HEUFT PRIME L2->L1, Linatronic 713 L1->L2, capex-cero) + arranque operativo pleno | E100: calidad | F100: Reduce scrap/reprocesos -> gana el componente de calidad. Al cierre de esta fase (mes 4 de preoperacion) el +5% relativo queda completo, justo antes de la rampa operativa del mes 5 (RAMPA_MES5 del modelo financiero).
A102: BLOQUE 7 · CAPACIDAD Y FACTIBILIDAD — ANTES vs DESPUÉS DEL PROYECTO (misma demanda; cambian equipos, OEE, tiempos y turnos)
A103: linea | B103: demanda_anual_und | C103: equipo_antes | D103: equipo_despues | E103: rp_antes_uph | F103: rp_despues_uph | G103: ciclo_antes_s | H103: ciclo_despues_s | I103: oee_antes | J103: oee_despues | K103: turnos_antes | L103: turnos_despues | M103: dias_operativos_ano | N103: q_antes_und | O103: q_despues_und | P103: mlt_antes_h | Q103: mlt_despues_h | R103: capacidad_antes_und | S103: capacidad_despues_mismos_turnos_und | T103: capacidad_despues_und | U103: U_antes | V103: U_despues | W103: incremento_capacidad_pct | X103: dictamen_antes | Y103: dictamen_despues | Z103: condicion_proyecto
A104: L1 | B104: =SUM(Demanda!D$5:D$16) -> 188337814 | C104: KRONES Mecafill usada 42.500 u/h + paletizado manual | D104: KRONES VODM/Modulfill usada 44.000 u/h + encajonadora 30x30 + GANTRY ABB | E104: 42500 | F104: 44000 | G104: =3600/E104 -> 0.084705882 | H104: =3600/F104 -> 0.081818182 | I104: =H83 -> 0.7711481 | J104: =C90 -> 0.80970551 | K104: 2 | L104: 3 | M104: 286 | N104: =J37 -> 262440 | O104: =ROUND(F104*G37*J104/L37,0)*L37 -> 285120 | P104: =P37 -> 16.983536 | Q104: =P104-(N104-1)*G104/3600+(O104-1)*H104/3600 -> 17.288478 | R104: =E104*K104*G37*M104*I104 -> 1.4997288e+08 | S104: =F104*K104*G37*M104*J104 -> 1.6302935e+08 | T104: =F104*L104*G37*M104*J104 -> 2.4454402e+08 | U104: =B104/R104 -> 1.2558124 | V104: =B104/T104 -> 0.77015915 | W104: =T104/R104-1 -> 0.63058824 | X104: =IF(U104>1,"INFACTIBLE","Factible") -> INFACTIBLE | Y104: =IF(V104>1,"INFACTIBLE","Factible") -> Factible | Z104: Cambio de llenadora, encajonadora custom, conveyors/VFD y GANTRY compartido L1-L2
A105: L2 | B105: =SUM(Demanda!E$5:E$16) -> 54228683 | C105: KRONES Contiform Bloc 2004 12.000 u/h + paletizado manual | D105: KRONES usada 18.000 u/h + Variopac termoencogible + GANTRY ABB compartido | E105: 12000 | F105: 18000 | G105: =3600/E105 -> 0.3 | H105: =3600/F105 -> 0.2 | I105: =H84 -> 0.76495181 | J105: =C91 -> 0.8031994 | K105: 2 | L105: 3 | M105: 286 | N105: =J38 -> 73080 | O105: =ROUND(F105*G38*J105/L38,0)*L38 -> 115920 | P105: =P38 -> 19.258142 | Q105: =P105-(N105-1)*G105/3600+(O105-1)*H105/3600 -> 19.608169 | R105: =E105*K105*G38*M105*I105 -> 42005034 | S105: =F105*K105*G38*M105*J105 -> 66157929 | T105: =F105*L105*G38*M105*J105 -> 99236893 | U105: =B105/R105 -> 1.2910044 | V105: =B105/T105 -> 0.54645688 | W105: =T105/R105-1 -> 1.3625 | X105: =IF(U105>1,"INFACTIBLE","Factible") -> INFACTIBLE | Y105: =IF(V105>1,"INFACTIBLE","Factible") -> Factible | Z105: Cambio de llenadora; Variopac prepara paquetes y el mismo GANTRY alterna el paletizado con L1
A106: L3 | B106: =SUM(Demanda!F$5:F$16) -> 279149 | C106: Monoblock 600 gfn/h limitado por paletizado manual a 480 gfn/h | D106: Llenadora/tapadora existente 600 gfn/h + robot ABB EUROBOTS | E106: 480 | F106: 600 | G106: =3600/E106 -> 7.5 | H106: =3600/F106 -> 6 | I106: =H85 -> 0.75370131 | J106: =C92 -> 0.79138638 | K106: 1 | L106: 1 | M106: 120 | N106: =J39 -> 2880 | O106: =ROUND(F106*G39*J106/L39,0)*L39 -> 3810 | P106: =P39 -> 15.573906 | Q106: =P106-(N106-1)*G106/3600+(O106-1)*H106/3600 -> 15.924322 | R106: =E106*K106*G39*M106*I106 -> 347305.57 | S106: =F106*K106*G39*M106*J106 -> 455838.56 | T106: =F106*L106*G39*M106*J106 -> 455838.56 | U106: =B106/R106 -> 0.80375619 | V106: =B106/T106 -> 0.61238567 | W106: =T106/R106-1 -> 0.3125 | X106: =IF(U106>1,"INFACTIBLE","Factible") -> Factible | Y106: =IF(V106>1,"INFACTIBLE","Factible") -> Factible | Z106: Se conserva la llenadora; solo se incorpora la celda robotica de paletizado
A107: La capacidad DESPUÉS con los mismos turnos separa el efecto tecnológico/OEE del efecto calendario. El proyecto completo usa 3 turnos en L1/L2 y 1 en L3.
A108: MLT DESPUÉS es una proyección: conserva las esperas del VSM base y recalcula la corrida con el nuevo cuello/lote. Debe reemplazarse por la medición SAT/comisionamiento.
A110: BLOQUE 8 · MÁQUINAS Y REFERENCIAS COMERCIALES POR ETAPA (tasas de catálogo/mercado de usados, referencia real)
A111: MÁQUINAS POR ETAPA — referencias comerciales realistas (equipos usados, planta de 15+ años)
A112: Tasas de catálogo/mercado de usados por marca (columna Ref → hoja Referencias). Tc = 3600/tasa. La estación con MENOR tasa define la línea (cuello = llenadora en L1/L2/L3).
A113: Etapa / máquina | B113: Referencia comercial (marca · modelo · condición) | C113: Tasa (und/h) | D113: Tc (s/und) | E113: Ref | F113: ¿Cuello? · Nota
A114: L1 · Coca-Cola 350 ml vidrio retornable (2 turnos × 8 h)
A115: Despaletizado / desencajonado | B115: MANUAL por cuadrillas (sin celdas robóticas en planta) | C115: manual | D115: — | E115: — | F115: No limita tasa (paralelo); suma Tno al MLT.
A116: Lavadora de botellas | B116: KRONES Lavatec (usada; clase 50–60k bph en vidrio retornable) | C116: 55000 | D116: =3600/C116 -> 0.065454545 | E116: [2] | F116: Sobredimensionada vs llenadora: absorbe paradas cortas.
A117: Inspección (vacía/llena) | B117: HEUFT PRIME reasignada DESDE L2 (72.000 cph): estaba sobredimensionada allí | C117: 72000 | D117: =3600/C117 -> 0.05 | E117: [9] | F117: Intercambio capex-cero propuesto: libera el cuello de 40k que imponía la Linatronic.
A118: Llenadora + tapadora (corona) | B118: KRONES Mecafill/Modulfill vidrio usada — 40–45k bph (visita) | C118: 42500 | D118: =3600/C118 -> 0.084705882 | E118: [2] | F118: SÍ — con la HEUFT en L1, la llenadora vuelve a ser la crítica.
...

Sheet PlanCompras
A1: PlanCompras — la escribe la APP por la API de Sheets
A2: COMPRAS · MRP explosionado (BOM x demanda del escenario activo).
A4: etiqueta_mes | B4: producto | C4: componente | D4: descripcion | E4: uom | F4: cantidad | G4: proveedor | H4: precio_unitario_cop | I4: subtotal_cop | J4: fecha_pedido | K4: fecha_necesidad
A5: Abr-26 | B5: P1-CC350-RGB | C5: TAP-CORONA | D5: Tapa corona 26 mm | E5: un | F5: 14646186 | G5: Tapas La Libertad | H5: 28 | I5: 410093208 | J5: 2026-03-18 | K5: 2026-04-01

Sheet LibroProduccion
A1: ts | B1: linea | C1: sku | D1: unidades | E1: precio_unit_cop | F1: costo_unit_cop | G1: ingreso_cop | H1: costo_cop | I1: margen_cop
A2: 2026-07-13T15:06:41+00:00 | B2: L1 | C2: P1-CC350-RGB | D2: 100 | E2: 1800 | F2: 929 | G2: 180000 | H2: 92900 | I2: 87100
A3: 2026-07-13T15:06:40+00:00 | B3: L2 | C3: P2-QT1500-PET | D3: 221 | E3: 4250 | F3: 2670 | G3: 939250 | H3: 590070 | I3: 349180
